Workbook

Sheet P&L
A2: Profit and Loss - Current Month
A3: Reporting Book: | C3: SS
A4: As of Date: | C4: 46270
A5: Location: | C5: GLOBAL
A6: MES | C6: 1 | D6: 2 | E6: 3 | F6: 4 | G6: 5 | H6: 6 | I6: 7 | J6: 8 | K6: 9 | L6: 10 | M6: 11 | N6: 12 | O6: 13 | P6: 14 | Q6: 15 | R6: 16 | S6: 17 | T6: 18 | U6: 19 | V6: 20 | W6: 21 | X6: 22 | Y6: 23 | Z6: 24 | AA6: 25 | AB6: 26 | AC6: 27 | AD6: 28 | AE6: 29 | AF6: 30 | AG6: 31 | AH6: 32 | AI6: 33 | AJ6: 34 | AK6: 35 | AL6: 36 | AM6: 37 | AN6: 38 | AO6: 39 | AP6: 40 | AQ6: 41 | AR6: 42 | AS6: 43 | AT6: 44 | AU6: 45 | AV6: 46 | AW6: 47 | AX6: 48 | AY6: 49 | AZ6: 50 | BA6: 51 | BB6: 52 | BC6: 53 | BD6: 54 | BE6: 55 | BF6: 56 | BG6: 57 | BH6: 58 | BI6: 59 | BJ6: 60 | BK6: 61 | BL6: 62 | BM6: 63 | BN6: 64 | BO6: 65 | BP6: 66 | BQ6: 67 | BR6: 68 | BS6: 69 | BT6: 70 | BU6: 71 | BV6: 72 | BW6: TOTAL
A7: Service per Month | C7: 0 | D7: 0 | E7: 0 | F7: 0 | G7: 0 | H7: 0 | I7: 150 | J7: 1100 | K7: 9666 | L7: 9776 | M7: 9821 | N7: 10854 | O7: 11606 | P7: 20415 | Q7: 27297 | R7: 39496 | S7: 39614 | T7: 87668 | U7: 87839 | V7: 104910 | W7: 105143 | X7: 105371 | Y7: 105610 | Z7: 105849 | AA7: 122084 | AB7: 122340 | AC7: 125593 | AD7: 125876 | AE7: 126164 | AF7: 126445 | AG7: 126732 | AH7: 127022 | AI7: 127313 | AJ7: 127602 | AK7: 127894 | AL7: 128192 | AM7: 128483 | AN7: 128783 | AO7: 129083 | AP7: 129380 | AQ7: 129685 | AR7: 129988 | AS7: 130291 | AT7: 130600 | AU7: 130905 | AV7: 131218 | AW7: 131530 | AX7: 131839 | AY7: 132155 | AZ7: 132474 | BA7: 132788 | BB7: 133108 | BC7: 133430 | BD7: 133754 | BE7: 134080 | BF7: 134406 | BG7: 134734 | BH7: 135066 | BI7: 135398 | BJ7: 135734 | BK7: 136066 | BL7: 136403 | BM7: 136743 | BN7: 137087 | BO7: 137429 | BP7: 137775 | BQ7: 138122 | BR7: 138473 | BS7: 138823 | BT7: 139176 | BU7: 139532 | BV7: 139889 | BW7: =SUM(C7:BV7) -> 7219872
A8: Revenue
C9: ='1_SEGUROS MONTERREY 🇲🇽'!B12 -> 0 | D9: ='1_SEGUROS MONTERREY 🇲🇽'!C12 -> 0 | E9: ='1_SEGUROS MONTERREY 🇲🇽'!D12 -> 0 | F9: ='1_SEGUROS MONTERREY 🇲🇽'!E12 -> 0 | G9: ='1_SEGUROS MONTERREY 🇲🇽'!F12 -> 0 | H9: ='1_SEGUROS MONTERREY 🇲🇽'!G12 -> 0 | I9: ='1_SEGUROS MONTERREY 🇲🇽'!H12 -> 0 | J9: ='1_SEGUROS MONTERREY 🇲🇽'!I12 -> 0 | ... BV9: ='1_SEGUROS MONTERREY 🇲🇽'!BU12 -> 72217
A10: ='2_SEGUROS MONTERREY 🇲🇽 - Hog'!A1 -> SEGUROS MONTERREY 🇲🇽 - Hogar | C10: ='2_SEGUROS MONTERREY 🇲🇽 - Hog'!B12 -> 0 | D10: ='2_SEGUROS MONTERREY 🇲🇽 - Hog'!C12 -> 0 | E10: ='2_SEGUROS MONTERREY 🇲🇽 - Hog'!D12 -> 0 | F10: ='2_SEGUROS MONTERREY 🇲🇽 - Hog'!E12 -> 0 | G10: ='2_SEGUROS MONTERREY 🇲🇽 - Hog'!F12 -> 0 | H10: ='2_SEGUROS MONTERREY 🇲🇽 - Hog'!G12 -> 0 | I10: ='2_SEGUROS MONTERREY 🇲🇽 - Hog'!H12 -> 0 | J10: ='2_SEGUROS MONTERREY 🇲🇽 - Hog'!I12 -> 0 | ... BV10: ='2_SEGUROS MONTERREY 🇲🇽 - Hog'!BU12 -> 30333
A11: ='3_CHUBB'!A1 -> CHUBB | C11: ='3_CHUBB'!B12 -> 0 | D11: ='3_CHUBB'!C12 -> 0 | E11: ='3_CHUBB'!D12 -> 0 | F11: ='3_CHUBB'!E12 -> 0 | G11: ='3_CHUBB'!F12 -> 0 | H11: ='3_CHUBB'!G12 -> 0 | I11: ='3_CHUBB'!H12 -> 0 | J11: ='3_CHUBB'!I12 -> 0 | ... BV11: ='3_CHUBB'!BU12 -> 988807
A12: ='4_CHUBB - Hogar Singapur'!A1 -> CHUBB - Hogar Singapur | C12: ='4_CHUBB - Hogar Singapur'!B12 -> 0 | D12: ='4_CHUBB - Hogar Singapur'!C12 -> 0 | E12: ='4_CHUBB - Hogar Singapur'!D12 -> 0 | F12: ='4_CHUBB - Hogar Singapur'!E12 -> 0 | G12: ='4_CHUBB - Hogar Singapur'!F12 -> 0 | H12: ='4_CHUBB - Hogar Singapur'!G12 -> 0 | I12: ='4_CHUBB - Hogar Singapur'!H12 -> 0 | J12: ='4_CHUBB - Hogar Singapur'!I12 -> 21000 | ... BV12: ='4_CHUBB - Hogar Singapur'!BU12 -> 23792
A13: ='5_CHUBB · Hogar Perú'!A1 -> Actor: CHUBB · Hogar Perú | C13: ='5_CHUBB · Hogar Perú'!B12 -> 0 | D13: ='5_CHUBB · Hogar Perú'!C12 -> 0 | E13: ='5_CHUBB · Hogar Perú'!D12 -> 0 | F13: ='5_CHUBB · Hogar Perú'!E12 -> 0 | G13: ='5_CHUBB · Hogar Perú'!F12 -> 0 | H13: ='5_CHUBB · Hogar Perú'!G12 -> 0 | I13: ='5_CHUBB · Hogar Perú'!H12 -> 6750 | J13: ='5_CHUBB · Hogar Perú'!I12 -> 6763 | ... BV13: ='5_CHUBB · Hogar Perú'!BU12 -> 7662
A14: ='6_CHUBB · Salud Chile'!A1 -> Actor: CHUBB · Salud Chile | C14: ='6_CHUBB · Salud Chile'!B12 -> 0 | D14: ='6_CHUBB · Salud Chile'!C12 -> 0 | E14: ='6_CHUBB · Salud Chile'!D12 -> 0 | F14: ='6_CHUBB · Salud Chile'!E12 -> 0 | G14: ='6_CHUBB · Salud Chile'!F12 -> 0 | H14: ='6_CHUBB · Salud Chile'!G12 -> 0 | I14: ='6_CHUBB · Salud Chile'!H12 -> 0 | J14: ='6_CHUBB · Salud Chile'!I12 -> 0 | ... BV14: ='6_CHUBB · Salud Chile'!BU12 -> 24876
A15: ='7_CHUBB - Salud Singapur'!A1 -> Actor: CHUBB - Salud Singapur | C15: ='7_CHUBB - Salud Singapur'!B12 -> 0 | D15: ='7_CHUBB - Salud Singapur'!C12 -> 0 | E15: ='7_CHUBB - Salud Singapur'!D12 -> 0 | F15: ='7_CHUBB - Salud Singapur'!E12 -> 0 | G15: ='7_CHUBB - Salud Singapur'!F12 -> 0 | H15: ='7_CHUBB - Salud Singapur'!G12 -> 0 | I15: ='7_CHUBB - Salud Singapur'!H12 -> 0 | J15: ='7_CHUBB - Salud Singapur'!I12 -> 0 | ... BV15: ='7_CHUBB - Salud Singapur'!BU12 -> 8633
A16: ='8_Kanguro Insurance'!A1 -> Actor: Kanguro Insurance | C16: ='8_Kanguro Insurance'!B12 -> 0 | D16: ='8_Kanguro Insurance'!C12 -> 0 | E16: ='8_Kanguro Insurance'!D12 -> 0 | F16: ='8_Kanguro Insurance'!E12 -> 0 | G16: ='8_Kanguro Insurance'!F12 -> 0 | H16: ='8_Kanguro Insurance'!G12 -> 0 | I16: ='8_Kanguro Insurance'!H12 -> 0 | J16: ='8_Kanguro Insurance'!I12 -> 22000 | ... BV16: ='8_Kanguro Insurance'!BU12 -> 49339
A17: ='9_Kanguro Insurance - Hogar'!A1 -> Actor: Kanguro Insurance - Hogar | C17: ='9_Kanguro Insurance - Hogar'!B12 -> 0 | D17: ='9_Kanguro Insurance - Hogar'!C12 -> 0 | E17: ='9_Kanguro Insurance - Hogar'!D12 -> 0 | F17: ='9_Kanguro Insurance - Hogar'!E12 -> 0 | G17: ='9_Kanguro Insurance - Hogar'!F12 -> 0 | H17: ='9_Kanguro Insurance - Hogar'!G12 -> 0 | I17: ='9_Kanguro Insurance - Hogar'!H12 -> 0 | J17: ='9_Kanguro Insurance - Hogar'!I12 -> 0 | ... BV17: ='9_Kanguro Insurance - Hogar'!BU12 -> 22961
A18: ='10_METLIFE'!A1 -> Actor: METLIFE | C18: ='10_METLIFE'!B12 -> 0 | D18: ='10_METLIFE'!C12 -> 0 | E18: ='10_METLIFE'!D12 -> 0 | F18: ='10_METLIFE'!E12 -> 0 | G18: ='10_METLIFE'!F12 -> 0 | H18: ='10_METLIFE'!G12 -> 0 | I18: ='10_METLIFE'!H12 -> 0 | J18: ='10_METLIFE'!I12 -> 31500 | ... BV18: ='10_METLIFE'!BU12 -> 35687
A19: ='11_METLIFE - Salud'!A1 -> Actor: METLIFE - Salud | C19: ='11_METLIFE - Salud'!B12 -> 0 | D19: ='11_METLIFE - Salud'!C12 -> 0 | E19: ='11_METLIFE - Salud'!D12 -> 0 | F19: ='11_METLIFE - Salud'!E12 -> 0 | G19: ='11_METLIFE - Salud'!F12 -> 0 | H19: ='11_METLIFE - Salud'!G12 -> 0 | I19: ='11_METLIFE - Salud'!H12 -> 0 | J19: ='11_METLIFE - Salud'!I12 -> 0 | ... BV19: ='11_METLIFE - Salud'!BU12 -> 33443
A20: ='12_Seguros Mundial 🇨🇴'!A1 -> Actor: Seguros Mundial 🇨🇴 | C20: ='12_Seguros Mundial 🇨🇴'!B12 -> 0 | D20: ='12_Seguros Mundial 🇨🇴'!C12 -> 0 | E20: ='12_Seguros Mundial 🇨🇴'!D12 -> 0 | F20: ='12_Seguros Mundial 🇨🇴'!E12 -> 0 | G20: ='12_Seguros Mundial 🇨🇴'!F12 -> 0 | H20: ='12_Seguros Mundial 🇨🇴'!G12 -> 0 | I20: ='12_Seguros Mundial 🇨🇴'!H12 -> 0 | J20: ='12_Seguros Mundial 🇨🇴'!I12 -> 0 | ... BV20: ='12_Seguros Mundial 🇨🇴'!BU12 -> 29860
A21: ='13_Seguros Mundial 🇨🇴 - Hogar'!A1 -> Actor: Seguros Mundial 🇨🇴 - Hogar | C21: ='13_Seguros Mundial 🇨🇴 - Hogar'!B12 -> 0 | D21: ='13_Seguros Mundial 🇨🇴 - Hogar'!C12 -> 0 | E21: ='13_Seguros Mundial 🇨🇴 - Hogar'!D12 -> 0 | F21: ='13_Seguros Mundial 🇨🇴 - Hogar'!E12 -> 0 | G21: ='13_Seguros Mundial 🇨🇴 - Hogar'!F12 -> 0 | H21: ='13_Seguros Mundial 🇨🇴 - Hogar'!G12 -> 0 | I21: ='13_Seguros Mundial 🇨🇴 - Hogar'!H12 -> 0 | J21: ='13_Seguros Mundial 🇨🇴 - Hogar'!I12 -> 0 | ... BV21: ='13_Seguros Mundial 🇨🇴 - Hogar'!BU12 -> 2886
A22: ='14_BNP Paribas Cardif'!A1 -> Actor: BNP Paribas Cardif | C22: ='14_BNP Paribas Cardif'!B12 -> 0 | D22: ='14_BNP Paribas Cardif'!C12 -> 0 | E22: ='14_BNP Paribas Cardif'!D12 -> 0 | F22: ='14_BNP Paribas Cardif'!E12 -> 0 | G22: ='14_BNP Paribas Cardif'!F12 -> 0 | H22: ='14_BNP Paribas Cardif'!G12 -> 0 | I22: ='14_BNP Paribas Cardif'!H12 -> 0 | J22: ='14_BNP Paribas Cardif'!I12 -> 0 | ... BV22: ='14_BNP Paribas Cardif'!BU12 -> 25030
A23: ='15_BNP Paribas Cardif - Hogar P'!A1 -> Actor: BNP Paribas Cardif - Hogar Perú | C23: ='15_BNP Paribas Cardif - Hogar P'!B12 -> 0 | D23: ='15_BNP Paribas Cardif - Hogar P'!C12 -> 0 | E23: ='15_BNP Paribas Cardif - Hogar P'!D12 -> 0 | F23: ='15_BNP Paribas Cardif - Hogar P'!E12 -> 0 | G23: ='15_BNP Paribas Cardif - Hogar P'!F12 -> 0 | H23: ='15_BNP Paribas Cardif - Hogar P'!G12 -> 0 | I23: ='15_BNP Paribas Cardif - Hogar P'!H12 -> 0 | J23: ='15_BNP Paribas Cardif - Hogar P'!I12 -> 0 | ... BV23: ='15_BNP Paribas Cardif - Hogar P'!BU12 -> 9270
A24: ='16_BNP Paribas Cardif - Vet Col'!A1 -> Actor: BNP Paribas Cardif - Vet Colombia | C24: ='16_BNP Paribas Cardif - Vet Col'!B12 -> 0 | D24: ='16_BNP Paribas Cardif - Vet Col'!C12 -> 0 | E24: ='16_BNP Paribas Cardif - Vet Col'!D12 -> 0 | F24: ='16_BNP Paribas Cardif - Vet Col'!E12 -> 0 | G24: ='16_BNP Paribas Cardif - Vet Col'!F12 -> 0 | H24: ='16_BNP Paribas Cardif - Vet Col'!G12 -> 0 | I24: ='16_BNP Paribas Cardif - Vet Col'!H12 -> 0 | J24: ='16_BNP Paribas Cardif - Vet Col'!I12 -> 0 | ... BV24: ='16_BNP Paribas Cardif - Vet Col'!BU12 -> 14219
A25: ='17_BNP Paribas Cardif - Salud M'!A1 -> Actor: BNP Paribas Cardif - Salud México | C25: ='17_BNP Paribas Cardif - Salud M'!B12 -> 0 | D25: ='17_BNP Paribas Cardif - Salud M'!C12 -> 0 | E25: ='17_BNP Paribas Cardif - Salud M'!D12 -> 0 | F25: ='17_BNP Paribas Cardif - Salud M'!E12 -> 0 | G25: ='17_BNP Paribas Cardif - Salud M'!F12 -> 0 | H25: ='17_BNP Paribas Cardif - Salud M'!G12 -> 0 | I25: ='17_BNP Paribas Cardif - Salud M'!H12 -> 0 | J25: ='17_BNP Paribas Cardif - Salud M'!I12 -> 0 | ... BV25: ='17_BNP Paribas Cardif - Salud M'!BU12 -> 23039
A26: ='18_BNP Paribas Cardif - Salud B'!A1 -> Actor: BNP Paribas Cardif - Salud Brasil | C26: ='18_BNP Paribas Cardif - Salud B'!B12 -> 0 | D26: ='18_BNP Paribas Cardif - Salud B'!C12 -> 0 | E26: ='18_BNP Paribas Cardif - Salud B'!D12 -> 0 | F26: ='18_BNP Paribas Cardif - Salud B'!E12 -> 0 | G26: ='18_BNP Paribas Cardif - Salud B'!F12 -> 0 | H26: ='18_BNP Paribas Cardif - Salud B'!G12 -> 0 | I26: ='18_BNP Paribas Cardif - Salud B'!H12 -> 0 | J26: ='18_BNP Paribas Cardif - Salud B'!I12 -> 0 | ... BV26: ='18_BNP Paribas Cardif - Salud B'!BU12 -> 268668
A27: ='19_Lemonade'!A1 -> Actor: Lemonade | C27: ='19_Lemonade'!B12 -> 0 | D27: ='19_Lemonade'!C12 -> 0 | E27: ='19_Lemonade'!D12 -> 0 | F27: ='19_Lemonade'!E12 -> 0 | G27: ='19_Lemonade'!F12 -> 0 | H27: ='19_Lemonade'!G12 -> 0 | I27: ='19_Lemonade'!H12 -> 0 | J27: ='19_Lemonade'!I12 -> 0 | ... BV27: ='19_Lemonade'!BU12 -> 808964
A28: ='20_Lemonade - Hogar'!A1 -> Actor: Lemonade - Hogar | C28: ='20_Lemonade - Hogar'!B12 -> 0 | D28: ='20_Lemonade - Hogar'!C12 -> 0 | E28: ='20_Lemonade - Hogar'!D12 -> 0 | F28: ='20_Lemonade - Hogar'!E12 -> 0 | G28: ='20_Lemonade - Hogar'!F12 -> 0 | H28: ='20_Lemonade - Hogar'!G12 -> 0 | I28: ='20_Lemonade - Hogar'!H12 -> 0 | J28: ='20_Lemonade - Hogar'!I12 -> 0 | ... BV28: ='20_Lemonade - Hogar'!BU12 -> 668616
A29: ='21_Consorcio'!A1 -> Actor: Consorcio | C29: ='21_Consorcio'!B12 -> 0 | D29: ='21_Consorcio'!C12 -> 0 | E29: ='21_Consorcio'!D12 -> 0 | F29: ='21_Consorcio'!E12 -> 0 | G29: ='21_Consorcio'!F12 -> 0 | H29: ='21_Consorcio'!G12 -> 0 | I29: ='21_Consorcio'!H12 -> 0 | J29: ='21_Consorcio'!I12 -> 0 | ... BV29: ='21_Consorcio'!BU12 -> 120246
A30: ='22_Consorcio - Hogar'!A1 -> Actor: Consorcio - Hogar | C30: ='22_Consorcio - Hogar'!B12 -> 0 | D30: ='22_Consorcio - Hogar'!C12 -> 0 | E30: ='22_Consorcio - Hogar'!D12 -> 0 | F30: ='22_Consorcio - Hogar'!E12 -> 0 | G30: ='22_Consorcio - Hogar'!F12 -> 0 | H30: ='22_Consorcio - Hogar'!G12 -> 0 | I30: ='22_Consorcio - Hogar'!H12 -> 0 | J30: ='22_Consorcio - Hogar'!I12 -> 0 | ... BV30: ='22_Consorcio - Hogar'!BU12 -> 37983
A31: ='23_Chilena Consolidada (Zurich)'!A1 -> Actor: Chilena Consolidada (Zurich) | C31: ='23_Chilena Consolidada (Zurich)'!B12 -> 0 | D31: ='23_Chilena Consolidada (Zurich)'!C12 -> 0 | E31: ='23_Chilena Consolidada (Zurich)'!D12 -> 0 | F31: ='23_Chilena Consolidada (Zurich)'!E12 -> 0 | G31: ='23_Chilena Consolidada (Zurich)'!F12 -> 0 | H31: ='23_Chilena Consolidada (Zurich)'!G12 -> 0 | I31: ='23_Chilena Consolidada (Zurich)'!H12 -> 0 | J31: ='23_Chilena Consolidada (Zurich)'!I12 -> 0 | ... BV31: ='23_Chilena Consolidada (Zurich)'!BU12 -> 360738
A32: ='24_Chilena Consolidada (Zurich)'!A1 -> Actor: Chilena Consolidada (Zurich) - Hogar | C32: ='24_Chilena Consolidada (Zurich)'!B12 -> 0 | D32: ='24_Chilena Consolidada (Zurich)'!C12 -> 0 | E32: ='24_Chilena Consolidada (Zurich)'!D12 -> 0 | F32: ='24_Chilena Consolidada (Zurich)'!E12 -> 0 | G32: ='24_Chilena Consolidada (Zurich)'!F12 -> 0 | H32: ='24_Chilena Consolidada (Zurich)'!G12 -> 0 | I32: ='24_Chilena Consolidada (Zurich)'!H12 -> 0 | J32: ='24_Chilena Consolidada (Zurich)'!I12 -> 0 | ... BV32: ='24_Chilena Consolidada (Zurich)'!BU12 -> 76112
A33: ='25_Allstate'!A1 -> Actor: Allstate | C33: ='25_Allstate'!B12 -> 0 | D33: ='25_Allstate'!C12 -> 0 | E33: ='25_Allstate'!D12 -> 0 | F33: ='25_Allstate'!E12 -> 0 | G33: ='25_Allstate'!F12 -> 0 | H33: ='25_Allstate'!G12 -> 0 | I33: ='25_Allstate'!H12 -> 0 | J33: ='25_Allstate'!I12 -> 0 | ... BV33: ='25_Allstate'!BU12 -> 2727445
A34: ='26_Allstate - Vehicular'!A1 -> Actor: Allstate - Vehicular | C34: ='26_Allstate - Vehicular'!B12 -> 0 | D34: ='26_Allstate - Vehicular'!C12 -> 0 | E34: ='26_Allstate - Vehicular'!D12 -> 0 | F34: ='26_Allstate - Vehicular'!E12 -> 0 | G34: ='26_Allstate - Vehicular'!F12 -> 0 | H34: ='26_Allstate - Vehicular'!G12 -> 0 | I34: ='26_Allstate - Vehicular'!H12 -> 0 | J34: ='26_Allstate - Vehicular'!I12 -> 0 | ... BV34: ='26_Allstate - Vehicular'!BU12 -> 1807064
A35: ='27_SURA Chile'!A1 -> Actor: SURA Chile | C35: ='27_SURA Chile'!B12 -> 0 | D35: ='27_SURA Chile'!C12 -> 0 | E35: ='27_SURA Chile'!D12 -> 0 | F35: ='27_SURA Chile'!E12 -> 0 | G35: ='27_SURA Chile'!F12 -> 0 | H35: ='27_SURA Chile'!G12 -> 0 | I35: ='27_SURA Chile'!H12 -> 0 | J35: ='27_SURA Chile'!I12 -> 0 | ... BV35: ='27_SURA Chile'!BU12 -> 379146
A36: ='28_SURA Chile - Hogar'!A1 -> Actor: SURA Chile - Hogar | C36: ='28_SURA Chile - Hogar'!B12 -> 0 | D36: ='28_SURA Chile - Hogar'!C12 -> 0 | E36: ='28_SURA Chile - Hogar'!D12 -> 0 | F36: ='28_SURA Chile - Hogar'!E12 -> 0 | G36: ='28_SURA Chile - Hogar'!F12 -> 0 | H36: ='28_SURA Chile - Hogar'!G12 -> 0 | I36: ='28_SURA Chile - Hogar'!H12 -> 0 | J36: ='28_SURA Chile - Hogar'!I12 -> 0 | ... BV36: ='28_SURA Chile - Hogar'!BU12 -> 132807
A37: ='29_SURA Colombia'!A1 -> Actor: SURA Colombia | C37: ='29_SURA Colombia'!B12 -> 0 | D37: ='29_SURA Colombia'!C12 -> 0 | E37: ='29_SURA Colombia'!D12 -> 0 | F37: ='29_SURA Colombia'!E12 -> 0 | G37: ='29_SURA Colombia'!F12 -> 0 | H37: ='29_SURA Colombia'!G12 -> 0 | I37: ='29_SURA Colombia'!H12 -> 0 | J37: ='29_SURA Colombia'!I12 -> 0 | ... BV37: ='29_SURA Colombia'!BU12 -> 460776
A38: ='30_SURA Colombia - Hogar'!A1 -> Actor: SURA Colombia - Hogar | C38: ='30_SURA Colombia - Hogar'!B12 -> 0 | D38: ='30_SURA Colombia - Hogar'!C12 -> 0 | E38: ='30_SURA Colombia - Hogar'!D12 -> 0 | F38: ='30_SURA Colombia - Hogar'!E12 -> 0 | G38: ='30_SURA Colombia - Hogar'!F12 -> 0 | H38: ='30_SURA Colombia - Hogar'!G12 -> 0 | I38: ='30_SURA Colombia - Hogar'!H12 -> 0 | J38: ='30_SURA Colombia - Hogar'!I12 -> 0 | ... BV38: ='30_SURA Colombia - Hogar'!BU12 -> 282726
A39: ='31_Liberty Mutual'!A1 -> Actor: Liberty Mutual | C39: ='31_Liberty Mutual'!B12 -> 0 | D39: ='31_Liberty Mutual'!C12 -> 0 | E39: ='31_Liberty Mutual'!D12 -> 0 | F39: ='31_Liberty Mutual'!E12 -> 0 | G39: ='31_Liberty Mutual'!F12 -> 0 | H39: ='31_Liberty Mutual'!G12 -> 0 | I39: ='31_Liberty Mutual'!H12 -> 0 | J39: ='31_Liberty Mutual'!I12 -> 0 | ... BV39: ='31_Liberty Mutual'!BU12 -> 1673652
A40: ='32_Liberty Mutual - Hogar'!A1 -> Actor: Liberty Mutual - Hogar | C40: ='32_Liberty Mutual - Hogar'!B12 -> 0 | D40: ='32_Liberty Mutual - Hogar'!C12 -> 0 | E40: ='32_Liberty Mutual - Hogar'!D12 -> 0 | F40: ='32_Liberty Mutual - Hogar'!E12 -> 0 | G40: ='32_Liberty Mutual - Hogar'!F12 -> 0 | H40: ='32_Liberty Mutual - Hogar'!G12 -> 0 | I40: ='32_Liberty Mutual - Hogar'!H12 -> 0 | J40: ='32_Liberty Mutual - Hogar'!I12 -> 0 | ... BV40: ='32_Liberty Mutual - Hogar'!BU12 -> 1655408
A42: Revenue - Services | C42: =SUM(C9:C41) -> 0 | D42: =SUM(D9:D41) -> 0 | E42: =SUM(E9:E41) -> 0 | F42: =SUM(F9:F41) -> 0 | G42: =SUM(G9:G41) -> 0 | H42: =SUM(H9:H41) -> 0 | I42: =SUM(I9:I41) -> 6750 | J42: =SUM(J9:J41) -> 81263 | ... BV42: =SUM(BV9:BV41) -> 12862405
A43: Revenue - Membership | C43: 0 | D43: 0 | E43: 0 | F43: 0 | G43: 0 | H43: 0 | I43: 2000 | J43: 8000 | K43: 18000 | L43: 18000 | M43: 18000 | N43: 18000 | O43: 20000 | P43: 20000 | Q43: 20000 | R43: 20000 | S43: 20000 | T43: 20000 | U43: 20000 | V43: 20000 | W43: 20000 | X43: 20000 | Y43: 20000 | Z43: 20000 | AA43: 30000 | AB43: =AA43 -> 30000 | AC43: =AB43 -> 30000 | AD43: =AC43 -> 30000 | AE43: =AD43 -> 30000 | AF43: =AE43 -> 30000 | AG43: =AF43 -> 30000 | AH43: =AG43 -> 30000 | AI43: =AH43 -> 30000 | ... BV43: =BU43 -> 30000
A44: Other Revenues | C44: 0 | D44: 0 | E44: 0 | F44: 0 | G44: 0 | H44: 0 | I44: 0 | J44: 0 | K44: 0 | L44: 0 | M44: 0 | N44: 0 | O44: 0 | P44: 0 | Q44: 0 | R44: 0 | S44: 0 | T44: 0 | U44: 0 | V44: 0 | W44: 0 | X44: 0 | Y44: 0 | Z44: 0 | AA44: 0 | AB44: 0 | AC44: 0 | AD44: 0 | AE44: 0 | AF44: 0 | AG44: 0 | AH44: 0 | AI44: 0 | AJ44: 0 | AK44: 0 | AL44: 0 | AM44: 0 | AN44: 0 | AO44: 0 | AP44: 0 | AQ44: 0 | AR44: 0 | AS44: 0 | AT44: 0 | AU44: 0 | AV44: 0 | AW44: 0 | AX44: 0 | AY44: 0 | AZ44: 0 | BA44: 0 | BB44: 0 | BC44: 0 | BD44: 0 | BE44: 0 | BF44: 0 | BG44: 0 | BH44: 0 | BI44: 0 | BJ44: 0 | BK44: 0 | BL44: 0 | BM44: 0 | BN44: 0 | BO44: 0 | BP44: 0 | BQ44: 0 | BR44: 0 | BS44: 0 | BT44: 0 | BU44: 0 | BV44: 0
A45: Total Revenue | C45: =C42+C43+C44 -> 0 | D45: =D42+D43+D44 -> 0 | E45: =E42+E43+E44 -> 0 | F45: =F42+F43+F44 -> 0 | G45: =G42+G43+G44 -> 0 | H45: =H42+H43+H44 -> 0 | I45: =I42+I43+I44 -> 8750 | J45: =J42+J43+J44 -> 89263 | ... BV45: =BV42+BV43+BV44 -> 12892405 | BW45: =SUM(C45:BV45) -> 657586600
A47: Cost of Revenue
A48: Fee & Comitions | C48: 0 | D48: 0 | E48: 0 | F48: 0 | G48: =G45*0.5% -> 0 | H48: =H45*0.5% -> 0 | I48: =I45*0.5% -> 43.75 | J48: =J45*0.5% -> 446.315 | K48: =K45*0.5% -> 4550.285 | L48: =L45*0.5% -> 4623.765 | M48: =M45*0.5% -> 4645.515 | N48: =N45*0.5% -> 4959.53 | ... BV48: =BV45*0.5% -> 64462.025
A49: Cost of Operations | C49: 0 | D49: 0 | E49: 0 | F49: 0 | G49: 0 | H49: 0 | I49: 4725 | J49: 59084 | K49: 699269 | L49: 709940 | M49: 713371 | N49: 757724 | O49: 784599 | P49: 1183191 | Q49: 1473943 | R49: 1823306 | S49: 1829394 | T49: 5519186 | U49: 5529099 | V49: 7235041 | W49: 7250536 | X49: 7266104 | Y49: 7281762 | Z49: 7297499 | AA49: 8593322 | AB49: 8610458 | AC49: 8987678 | AD49: 9008167 | AE49: 9028773 | AF49: 9049497 | AG49: 9070339 | AH49: 9091301 | AI49: 9112386 | AJ49: 9133589 | AK49: 9154916 | AL49: 9176367 | AM49: 9197944 | AN49: 9219648 | AO49: 9241478 | AP49: 9263440 | AQ49: 9285527 | AR49: 9307749 | AS49: 9330097 | AT49: 9352581 | AU49: 9375201 | AV49: 9397954 | AW49: 9420847 | AX49: 9443881 | AY49: 9467049 | AZ49: 9490360 | BA49: 9513815 | BB49: 9537410 | BC49: 9561147 | BD49: 9585038 | BE49: 9609073 | BF49: 9633256 | BG49: 9657591 | BH49: 9682071 | BI49: 9706713 | BJ49: 9731507 | BK49: 9756454 | BL49: 9781564 | BM49: 9806828 | BN49: 9832256 | BO49: 9857838 | BP49: 9883593 | BQ49: 9909506 | BR49: 9935591 | BS49: 9961839 | BT49: 9988259 | BU49: 10014849 | BV49: 10041613
A50: Avg Service Cost / Inlcuid Fee | C50: 0 | D50: 0 | E50: 0 | F50: 0 | G50: 0 | H50: 0 | I50: =I49/I7 -> 31.5 | J50: =J49/J7 -> 53.712727 | K50: =K49/K7 -> 72.343162 | L50: =L49/L7 -> 72.620704 | M50: =M49/M7 -> 72.637308 | N50: =N49/N7 -> 69.810577 | O50: =O49/O7 -> 67.602878 | P50: =P49/P7 -> 57.956943 | ... BV50: =BV49/BV7 -> 71.782721
A51: Total Cost of Revenue | C51: =C49+C48 -> 0 | D51: =D49+D48 -> 0 | E51: =E49+E48 -> 0 | F51: =F49+F48 -> 0 | G51: =G49+G48 -> 0 | H51: =H49+H48 -> 0 | I51: =I49+I48 -> 4768.75 | J51: =J49+J48 -> 59530.315 | ... BV51: =BV49+BV48 -> 10106075 | BW51: =SUM(C51:BV51) -> 514504066
A53: Gross Profit | C53: =C45-C51 -> 0 | D53: =D45-D51 -> 0 | E53: =E45-E51 -> 0 | F53: =F45-F51 -> 0 | G53: =G45-G51 -> 0 | H53: =H45-H51 -> 0 | I53: =I45-I51 -> 3981.25 | J53: =J45-J51 -> 29732.685 | ... BV53: =BV45-BV51 -> 2786330 | BW53: =SUM(C53:BV53) -> 143082534
A54: Gross Profit % | C54: 0 | D54: 0 | E54: 0 | F54: 0 | G54: 0 | H54: 0 | I54: =I53/I45 -> 0.455 | J54: =J53/J45 -> 0.33309081 | K54: =K53/K45 -> 0.22662066 | L54: =L53/L45 -> 0.2272923 | M54: =M53/M45 -> 0.22719385 | N54: =N53/N45 -> 0.23109294 | O54: =O53/O45 -> 0.23453732 | P54: =P53/P45 -> 0.25578006 | ... BV54: =BV53/BV45 -> 0.21612182
A56: Operating Expenses & Ai
A57: Software | C57: 0 | D57: 0 | E57: 0 | F57: 0 | G57: =G45*1% -> 0 | H57: =H45*1% -> 0 | I57: =I45*1% -> 87.5 | J57: =J45*1% -> 892.63 | K57: =K45*1% -> 9100.57 | L57: =L45*1% -> 9247.53 | M57: =M45*1% -> 9291.03 | N57: =N45*1% -> 9919.06 | ... BV57: =BV45*1% -> 128924.05
A58: Offices | C58: 0 | D58: 0 | E58: 0 | F58: 0 | G58: 0 | H58: 0 | I58: 0 | J58: 1000 | K58: =J58 -> 1000 | L58: =K58 -> 1000 | M58: =L58 -> 1000 | N58: =M58 -> 1000 | O58: =N58 -> 1000 | P58: =O58 -> 1000 | Q58: =P58 -> 1000 | R58: 4000 | S58: =R58 -> 4000 | T58: =S58 -> 4000 | U58: =T58 -> 4000 | V58: =U58 -> 4000 | W58: =V58 -> 4000 | X58: =W58 -> 4000 | Y58: =X58 -> 4000 | Z58: =Y58 -> 4000 | ... AC58: =AB58 -> 4000 | AD58: 9000 | AE58: =AD58 -> 9000 | AF58: =AE58 -> 9000 | AG58: =AF58 -> 9000 | AH58: =AG58 -> 9000 | AI58: =AH58 -> 9000 | AJ58: =AI58 -> 9000 | AK58: =AJ58 -> 9000 | AL58: =AK58 -> 9000 | ... BV58: =BU58 -> 9000
A59: Call Center Office | C59: =Formulas!E8 -> 0 | D59: =Formulas!F8 -> 0 | E59: =Formulas!G8 -> 0 | F59: =Formulas!H8 -> 0 | G59: =Formulas!I8 -> 0 | H59: =Formulas!J8 -> 0 | I59: =Formulas!K8 -> 12.5 | J59: =Formulas!L8 -> 91.666667 | ... BV59: =Formulas!BX8 -> 11657.417
A60: Costo de IA por llamada | C60: =Formulas!E16 -> 0 | D60: =Formulas!F16 -> 0 | E60: =Formulas!G16 -> 0 | F60: =Formulas!H16 -> 0 | G60: =Formulas!I16 -> 0 | H60: =Formulas!J16 -> 0 | I60: =Formulas!K16 -> 322.875 | J60: =Formulas!L16 -> 2367.75 | ... BV60: =Formulas!BX16 -> 301111.07
A61: Mails | C61: 0 | D61: 0 | E61: 0 | F61: 0 | G61: 30 | H61: =G61 -> 30 | I61: =H61 -> 30 | J61: =I61 -> 30 | K61: =J61 -> 30 | L61: =K61 -> 30 | M61: =L61 -> 30 | N61: =M61 -> 30 | O61: =N61 -> 30 | ... BS61: =BR61 -> 30 | BT61: 30 | BU61: 30 | BV61: 30
A62: QuickBook | C62: 0 | D62: 0 | E62: 0 | F62: 0 | G62: 0 | H62: 0 | I62: 25 | J62: =I62 -> 25 | K62: =J62 -> 25 | L62: =K62 -> 25 | M62: 150 | N62: =M62 -> 150 | O62: =N62 -> 150 | P62: =O62 -> 150 | Q62: =P62 -> 150 | R62: =Q62 -> 150 | S62: =R62 -> 150 | T62: =S62 -> 150 | U62: =T62 -> 150 | ... BS62: =BR62 -> 150 | BT62: 25 | BU62: 25 | BV62: 25
A63: Chat GPT | C63: 0 | D63: 0 | E63: 0 | F63: 0 | G63: 0 | H63: 0 | I63: 100 | J63: =I63 -> 100 | K63: =J63 -> 100 | L63: 1000 | M63: =L63 -> 1000 | N63: =M63 -> 1000 | O63: =N63 -> 1000 | P63: =O63 -> 1000 | Q63: =P63 -> 1000 | R63: =Q63 -> 1000 | S63: =R63 -> 1000 | T63: =S63 -> 1000 | ... BV63: =BU63 -> 1000
A64: Lovable | C64: 0 | D64: 50 | E64: 50 | F64: 50 | G64: 50 | H64: 50 | I64: 400 | J64: =I64 -> 400 | K64: =J64 -> 400 | L64: =K64 -> 400 | M64: =L64 -> 400 | N64: =M64 -> 400 | O64: =N64 -> 400 | P64: =O64 -> 400 | Q64: =P64 -> 400 | ... BS64: =BR64 -> 400 | BT64: 50 | BU64: 50 | BV64: 50
A65: Supabase | C65: 0 | D65: 0 | E65: 0 | F65: 0 | G65: 0 | H65: 0 | I65: 75 | J65: =I65 -> 75 | K65: =J65 -> 75 | L65: =K65 -> 75 | M65: =L65 -> 75 | N65: =M65 -> 75 | O65: =N65 -> 75 | P65: =O65 -> 75 | Q65: =P65 -> 75 | ... BV65: =BU65 -> 75
A66: Eleven labs | C66: 0 | D66: 0 | E66: 0 | F66: 0 | G66: 0 | H66: 0 | I66: 150 | J66: =I66 -> 150 | K66: =J66 -> 150 | L66: =K66 -> 150 | M66: =L66 -> 150 | N66: =M66 -> 150 | O66: =N66 -> 150 | P66: =O66 -> 150 | Q66: =P66 -> 150 | ... BV66: =BU66 -> 150
A67: Gemini | C67: 0 | D67: 0 | E67: 0 | F67: 0 | G67: 0 | H67: 0 | I67: 50 | J67: =I67 -> 50 | K67: =J67 -> 50 | L67: =K67 -> 50 | M67: =L67 -> 50 | N67: =M67 -> 50 | O67: =N67 -> 50 | P67: =O67 -> 50 | Q67: =P67 -> 50 | ... BV67: =BU67 -> 50
A68: Insurance | C68: 0 | D68: 0 | E68: 0 | F68: 0 | G68: 0 | H68: 0 | I68: 20 | J68: =I68 -> 20 | K68: =J68 -> 20 | L68: =K68 -> 20 | M68: =L68 -> 20 | N68: =M68 -> 20 | O68: =N68 -> 20 | P68: =O68 -> 20 | Q68: =P68 -> 20 | ... BS68: =BR68 -> 20 | BT68: 0 | BU68: 0 | BV68: 0
A70: Total Operating Expenses | C70: =SUM(C57:C68) -> 0 | D70: =SUM(D57:D68) -> 50 | E70: =SUM(E57:E68) -> 50 | F70: =SUM(F57:F68) -> 50 | G70: =SUM(G57:G68) -> 80 | H70: =SUM(H57:H68) -> 80 | I70: =SUM(I57:I68) -> 1272.875 | J70: =SUM(J57:J68) -> 5202.0467 | ... BV70: =SUM(BV57:BV68) -> 452072.54 | BW70: =SUM(C70:BV70) -> 23298671
A72: Payroll and Related Expenses
A73: Sebastian Sarovich - CEO | B73: 0.01 | C73: =C$53*$B73 -> 0 | D73: =D$53*$B73 -> 0 | E73: =E$53*$B73 -> 0 | F73: =F$53*$B73 -> 0 | G73: =G$53*$B73 -> 0 | H73: =H$53*$B73 -> 0 | I73: 0 | J73: 0 | K73: =K$53*$B73 -> 2062.3771 | L73: =L$53*$B73 -> 2101.8924 | M73: =M$53*$B73 -> 2110.8648 | N73: =N$53*$B73 -> 2292.2247 | O73: =O$53*$B73 -> 2419.8131 | P73: =P$53*$B73 -> 4094.0003 | Q73: =Q53*$B73 -> 5313.6806 | R73: =R53*$B73 -> 6780.3047 | S73: =S53*$B73 -> 6800.3083 | T73: =T53*$B73 -> 16223.777 | U73: =U53*$B73 -> 16253.928 | V73: =V53*$B73 -> 20567.396 | W73: =W53*$B73 -> 20611.456 | X73: =X53*$B73 -> 20655.781 | ... AE73: =AE53*$B73 -> 25096.739 | AF73: =AE73 -> 25096.739 | AG73: =AF73 -> 25096.739 | AH73: =AG73 -> 25096.739 | AI73: =AH73 -> 25096.739 | AJ73: =AI73 -> 25096.739 | AK73: =AJ73 -> 25096.739 | AL73: =AK73 -> 25096.739 | AM73: =AL73 -> 25096.739 | ... BV73: =BU73 -> 25096.739
A74: Ximena Hincapie | B74: 0.001 | C74: =C$53*$B74 -> 0 | D74: =D$53*$B74 -> 0 | E74: =E$53*$B74 -> 0 | F74: =F$53*$B74 -> 0 | G74: =G$53*$B74 -> 0 | H74: =H$53*$B74 -> 0 | I74: 0 | J74: 0 | K74: =K$53*$B74 -> 206.23772 | L74: =L$53*$B74 -> 210.18923 | M74: =M$53*$B74 -> 211.08649 | N74: =N$53*$B74 -> 229.22247 | O74: =O$53*$B74 -> 241.9813 | P74: =P$53*$B74 -> 409.40003 | Q74: =Q$53*$B74 -> 531.36806 | R74: =R$53*$B74 -> 678.03047 | ... V74: =V$53*$B74 -> 2056.7396 | W74: =V74 -> 2056.7396 | X74: =W74 -> 2056.7396 | Y74: =X74 -> 2056.7396 | Z74: =Y74 -> 2056.7396 | AA74: =Z74 -> 2056.7396 | AB74: =AA74 -> 2056.7396 | AC74: =AB74 -> 2056.7396 | AD74: =AC74 -> 2056.7396 | ... BV74: =BU74 -> 2056.7396
A75: Laura Ospina - CAIO | B75: 0.005 | C75: =C$53*$B75 -> 0 | D75: =D$53*$B75 -> 0 | E75: =E$53*$B75 -> 0 | F75: =F$53*$B75 -> 0 | G75: =G$53*$B75 -> 0 | H75: =H$53*$B75 -> 0 | I75: 0 | J75: =J$53*$B75 -> 148.66342 | K75: =K$53*$B75 -> 1031.1886 | L75: =L$53*$B75 -> 1050.9462 | M75: =M$53*$B75 -> 1055.4324 | N75: =N$53*$B75 -> 1146.1124 | O75: =O$53*$B75 -> 1209.9065 | P75: =P$53*$B75 -> 2047.0002 | Q75: =Q$53*$B75 -> 2656.8403 | ... T75: =T$53*$B75 -> 8111.8887 | U75: =T75 -> 8111.8887 | V75: =U75 -> 8111.8887 | W75: =V75 -> 8111.8887 | X75: =W75 -> 8111.8887 | Y75: =X75 -> 8111.8887 | Z75: =Y75 -> 8111.8887 | AA75: =Z75 -> 8111.8887 | AB75: =AA75 -> 8111.8887 | ... BV75: =BU75 -> 8111.8887
A76: Ai - Specialist 1 | B76: 0.005 | C76: =C$53*$B76 -> 0 | D76: =D$53*$B76 -> 0 | E76: =E$53*$B76 -> 0 | F76: =F$53*$B76 -> 0 | G76: =G$53*$B76 -> 0 | H76: =H$53*$B76 -> 0 | I76: 0 | J76: =J$53*$B76 -> 148.66342 | K76: =K$53*$B76 -> 1031.1886 | L76: =L$53*$B76 -> 1050.9462 | M76: =M$53*$B76 -> 1055.4324 | N76: =N$53*$B76 -> 1146.1124 | O76: =O$53*$B76 -> 1209.9065 | P76: =P$53*$B76 -> 2047.0002 | Q76: =P76 -> 2047.0002 | R76: =Q76 -> 2047.0002 | S76: =R76 -> 2047.0002 | T76: =S76 -> 2047.0002 | U76: =T76 -> 2047.0002 | V76: =U76 -> 2047.0002 | W76: =V76 -> 2047.0002 | X76: =W76 -> 2047.0002 | ... BV76: =BU76 -> 2047.0002
A77: Ai - Specialist 2 | B77: 0.005 | C77: =C$53*$B77 -> 0 | D77: =D$53*$B77 -> 0 | E77: =E$53*$B77 -> 0 | F77: =F$53*$B77 -> 0 | G77: =G$53*$B77 -> 0 | H77: =H$53*$B77 -> 0 | I77: 0 | J77: =J$53*$B77 -> 148.66342 | K77: =K$53*$B77 -> 1031.1886 | L77: =L$53*$B77 -> 1050.9462 | M77: =M$53*$B77 -> 1055.4324 | N77: =N$53*$B77 -> 1146.1124 | O77: =O$53*$B77 -> 1209.9065 | P77: =P$53*$B77 -> 2047.0002 | Q77: =P77 -> 2047.0002 | R77: =Q77 -> 2047.0002 | S77: =R77 -> 2047.0002 | T77: =S77 -> 2047.0002 | U77: =T77 -> 2047.0002 | V77: =U77 -> 2047.0002 | W77: =V77 -> 2047.0002 | X77: =W77 -> 2047.0002 | ... BV77: =BU77 -> 2047.0002
A78: Martin Baumann - CoS | B78: 0.007 | C78: =C$53*$B78 -> 0 | D78: =D$53*$B78 -> 0 | E78: =E$53*$B78 -> 0 | F78: =F$53*$B78 -> 0 | G78: =G$53*$B78 -> 0 | H78: =H$53*$B78 -> 0 | I78: 0 | J78: =J$53*$B78 -> 208.12879 | K78: =K$53*$B78 -> 1443.664 | L78: =L$53*$B78 -> 1471.3246 | M78: =M$53*$B78 -> 1477.6054 | N78: =N$53*$B78 -> 1604.5573 | O78: =O$53*$B78 -> 1693.8691 | P78: =P$53*$B78 -> 2865.8002 | Q78: =Q$53*$B78 -> 3719.5764 | ... U78: =U$53*$B78 -> 11377.749 | V78: =U78 -> 11377.749 | W78: =V78 -> 11377.749 | X78: =W78 -> 11377.749 | Y78: =X78 -> 11377.749 | Z78: =Y78 -> 11377.749 | AA78: =Z78 -> 11377.749 | AB78: =AA78 -> 11377.749 | AC78: =AB78 -> 11377.749 | ... BV78: =BU78 -> 11377.749
A79: CIO | B79: 0.003 | C79: =C$53*$B79 -> 0 | D79: =D$53*$B79 -> 0 | E79: =E$53*$B79 -> 0 | F79: =F$53*$B79 -> 0 | G79: =G$53*$B79 -> 0 | H79: =H$53*$B79 -> 0 | I79: 0 | J79: =J$53*$B79 -> 89.198055 | K79: =K$53*$B79 -> 618.71315 | L79: =L$53*$B79 -> 630.56771 | M79: =M$53*$B79 -> 633.25946 | N79: =N$53*$B79 -> 687.66741 | O79: =O$53*$B79 -> 725.94391 | P79: =P$53*$B79 -> 1228.2001 | Q79: =Q$53*$B79 -> 1594.1042 | ... AA79: =AA$53*$B79 -> 7202.8572 | AB79: =AA79 -> 7202.8572 | AC79: =AB79 -> 7202.8572 | AD79: =AC79 -> 7202.8572 | AE79: =AD79 -> 7202.8572 | AF79: =AE79 -> 7202.8572 | AG79: =AF79 -> 7202.8572 | AH79: =AG79 -> 7202.8572 | AI79: =AH79 -> 7202.8572 | ... BV79: =BU79 -> 7202.8572
A80: Information Team 1 | B80: 0.002 | C80: =C$53*$B80 -> 0 | D80: =D$53*$B80 -> 0 | E80: =E$53*$B80 -> 0 | F80: =F$53*$B80 -> 0 | G80: =G$53*$B80 -> 0 | H80: =H$53*$B80 -> 0 | I80: 0 | J80: =J$53*$B80 -> 59.46537 | K80: =K$53*$B80 -> 412.47543 | L80: =L$53*$B80 -> 420.37847 | M80: =M$53*$B80 -> 422.17297 | N80: =N$53*$B80 -> 458.44494 | O80: =O$53*$B80 -> 483.96261 | P80: =P$53*$B80 -> 818.80006 | Q80: =Q$53*$B80 -> 1062.7361 | ... T80: =T$53*$B80 -> 3244.7555 | U80: =T80 -> 3244.7555 | V80: =U80 -> 3244.7555 | W80: =V80 -> 3244.7555 | X80: =W80 -> 3244.7555 | Y80: =X80 -> 3244.7555 | Z80: =Y80 -> 3244.7555 | AA80: =Z80 -> 3244.7555 | AB80: =AA80 -> 3244.7555 | ... BV80: =BU80 -> 3244.7555
A81: Information Team 2 | B81: 0.002 | C81: =C$53*$B81 -> 0 | D81: =D$53*$B81 -> 0 | E81: =E$53*$B81 -> 0 | F81: =F$53*$B81 -> 0 | G81: =G$53*$B81 -> 0 | H81: =H$53*$B81 -> 0 | I81: 0 | J81: =J$53*$B81 -> 59.46537 | K81: =K$53*$B81 -> 412.47543 | L81: =L$53*$B81 -> 420.37847 | M81: =M$53*$B81 -> 422.17297 | N81: =N$53*$B81 -> 458.44494 | O81: =O$53*$B81 -> 483.96261 | P81: =P$53*$B81 -> 818.80006 | Q81: =Q$53*$B81 -> 1062.7361 | ... T81: =T$53*$B81 -> 3244.7555 | U81: =T81 -> 3244.7555 | V81: =U81 -> 3244.7555 | W81: =V81 -> 3244.7555 | X81: =W81 -> 3244.7555 | Y81: =X81 -> 3244.7555 | Z81: =Y81 -> 3244.7555 | AA81: =Z81 -> 3244.7555 | AB81: =AA81 -> 3244.7555 | ... BV81: =BU81 -> 3244.7555
A82: Eduardo Diaz - COO | B82: 0.007 | C82: =C$53*$B82 -> 0 | D82: =D$53*$B82 -> 0 | E82: =E$53*$B82 -> 0 | F82: =F$53*$B82 -> 0 | G82: =G$53*$B82 -> 0 | H82: =H$53*$B82 -> 0 | I82: =I$53*$B82 -> 27.86875 | J82: =J$53*$B82 -> 208.12879 | ... T82: =T$53*$B82 -> 11356.644 | U82: =T82 -> 11356.644 | V82: =U82 -> 11356.644 | W82: =V82 -> 11356.644 | X82: =W82 -> 11356.644 | Y82: =X82 -> 11356.644 | Z82: =Y82 -> 11356.644 | AA82: =Z82 -> 11356.644 | AB82: =AA82 -> 11356.644 | ... BV82: =BU82 -> 11356.644
A83: Operation Team 1 | B83: 0.0005 | C83: =C$53*$B83 -> 0 | D83: =D$53*$B83 -> 0 | E83: =E$53*$B83 -> 0 | F83: =F$53*$B83 -> 0 | G83: =G$53*$B83 -> 0 | H83: =H$53*$B83 -> 0 | I83: 0 | J83: =J$53*$B83 -> 14.866343 | K83: =K$53*$B83 -> 103.11886 | L83: =L$53*$B83 -> 105.09462 | M83: =M$53*$B83 -> 105.54324 | N83: =N$53*$B83 -> 114.61123 | O83: =O$53*$B83 -> 120.99065 | P83: =P$53*$B83 -> 204.70002 | Q83: =Q$53*$B83 -> 265.68403 | ... V83: =V$53*$B83 -> 1028.3698 | W83: =V83 -> 1028.3698 | X83: =W83 -> 1028.3698 | Y83: =X83 -> 1028.3698 | Z83: =Y83 -> 1028.3698 | AA83: =Z83 -> 1028.3698 | AB83: =AA83 -> 1028.3698 | AC83: =AB83 -> 1028.3698 | AD83: =AC83 -> 1028.3698 | ... BV83: =BU83 -> 1028.3698
A84: Operation Team 2 | B84: 0.0005 | C84: =C$53*$B84 -> 0 | D84: =D$53*$B84 -> 0 | E84: =E$53*$B84 -> 0 | F84: =F$53*$B84 -> 0 | G84: =G$53*$B84 -> 0 | H84: =H$53*$B84 -> 0 | I84: 0 | J84: =J$53*$B84 -> 14.866343 | K84: =K$53*$B84 -> 103.11886 | L84: =L$53*$B84 -> 105.09462 | M84: =M$53*$B84 -> 105.54324 | N84: =N$53*$B84 -> 114.61123 | O84: =O$53*$B84 -> 120.99065 | P84: =P$53*$B84 -> 204.70002 | Q84: =Q$53*$B84 -> 265.68403 | ... V84: =V$53*$B84 -> 1028.3698 | W84: =V84 -> 1028.3698 | X84: =W84 -> 1028.3698 | Y84: =X84 -> 1028.3698 | Z84: =Y84 -> 1028.3698 | AA84: =Z84 -> 1028.3698 | AB84: =AA84 -> 1028.3698 | AC84: =AB84 -> 1028.3698 | AD84: =AC84 -> 1028.3698 | ... BV84: =BU84 -> 1028.3698
A85: Operation Team 3 | B85: 0.0005 | C85: =C$53*$B85 -> 0 | D85: =D$53*$B85 -> 0 | E85: =E$53*$B85 -> 0 | F85: =F$53*$B85 -> 0 | G85: =G$53*$B85 -> 0 | H85: =H$53*$B85 -> 0 | I85: 0 | J85: =J$53*$B85 -> 14.866343 | K85: =K$53*$B85 -> 103.11886 | L85: =L$53*$B85 -> 105.09462 | M85: =M$53*$B85 -> 105.54324 | N85: =N$53*$B85 -> 114.61123 | O85: =O$53*$B85 -> 120.99065 | P85: =P$53*$B85 -> 204.70002 | Q85: =Q$53*$B85 -> 265.68403 | ... V85: =V$53*$B85 -> 1028.3698 | W85: =V85 -> 1028.3698 | X85: =W85 -> 1028.3698 | Y85: =X85 -> 1028.3698 | Z85: =Y85 -> 1028.3698 | AA85: =Z85 -> 1028.3698 | AB85: =AA85 -> 1028.3698 | AC85: =AB85 -> 1028.3698 | AD85: =AC85 -> 1028.3698 | ... BV85: =BU85 -> 1028.3698
A86: Operation Team 4 | B86: 0.0005 | C86: =C$53*$B86 -> 0 | D86: =D$53*$B86 -> 0 | E86: =E$53*$B86 -> 0 | F86: =F$53*$B86 -> 0 | G86: =G$53*$B86 -> 0 | H86: =H$53*$B86 -> 0 | I86: 0 | J86: =J$53*$B86 -> 14.866343 | K86: =K$53*$B86 -> 103.11886 | L86: =L$53*$B86 -> 105.09462 | M86: =M$53*$B86 -> 105.54324 | N86: =N$53*$B86 -> 114.61123 | O86: =O$53*$B86 -> 120.99065 | P86: =P$53*$B86 -> 204.70002 | Q86: =Q$53*$B86 -> 265.68403 | ... V86: =V$53*$B86 -> 1028.3698 | W86: =V86 -> 1028.3698 | X86: =W86 -> 1028.3698 | Y86: =X86 -> 1028.3698 | Z86: =Y86 -> 1028.3698 | AA86: =Z86 -> 1028.3698 | AB86: =AA86 -> 1028.3698 | AC86: =AB86 -> 1028.3698 | AD86: =AC86 -> 1028.3698 | ... BV86: =BU86 -> 1028.3698
A87: Operation Team 5 | B87: 0.0005 | C87: =C$53*$B87 -> 0 | D87: =D$53*$B87 -> 0 | E87: =E$53*$B87 -> 0 | F87: =F$53*$B87 -> 0 | G87: =G$53*$B87 -> 0 | H87: =H$53*$B87 -> 0 | I87: 0 | J87: =J$53*$B87 -> 14.866343 | K87: =K$53*$B87 -> 103.11886 | L87: =L$53*$B87 -> 105.09462 | M87: =M$53*$B87 -> 105.54324 | N87: =N$53*$B87 -> 114.61123 | O87: =O$53*$B87 -> 120.99065 | P87: =P$53*$B87 -> 204.70002 | Q87: =Q$53*$B87 -> 265.68403 | ... V87: =V$53*$B87 -> 1028.3698 | W87: =V87 -> 1028.3698 | X87: =W87 -> 1028.3698 | Y87: =X87 -> 1028.3698 | Z87: =Y87 -> 1028.3698 | AA87: =Z87 -> 1028.3698 | AB87: =AA87 -> 1028.3698 | AC87: =AB87 -> 1028.3698 | AD87: =AC87 -> 1028.3698 | ... BV87: =BU87 -> 1028.3698
A88: Operation Center | C88: =Formulas!E5 -> 0 | D88: =Formulas!F5 -> 0 | E88: =Formulas!G5 -> 0 | F88: =Formulas!H5 -> 0 | G88: =Formulas!I5 -> 0 | H88: =Formulas!J5 -> 0 | I88: 0 | J88: =Formulas!L5 -> 825 | K88: =Formulas!M5 -> 7249.5 | L88: =Formulas!N5 -> 7332 | M88: =Formulas!O5 -> 7365.75 | N88: =Formulas!P5 -> 8140.5 | O88: =Formulas!Q5 -> 8704.5 | P88: =Formulas!R5 -> 15311.25 | Q88: =Formulas!S5 -> 20472.75 | ... BV88: =Formulas!BX5 -> 104916.75
A89: Finantial Team - CFO | B89: 0.004 | C89: =C$53*$B89 -> 0 | D89: =D$53*$B89 -> 0 | E89: =E$53*$B89 -> 0 | F89: =F$53*$B89 -> 0 | G89: =G$53*$B89 -> 0 | H89: =H$53*$B89 -> 0 | I89: 0 | J89: =J$53*$B89 -> 118.93074 | K89: =K$53*$B89 -> 824.95086 | L89: =L$53*$B89 -> 840.75694 | M89: =M$53*$B89 -> 844.34594 | N89: =N$53*$B89 -> 916.88988 | O89: =O$53*$B89 -> 967.92522 | P89: =P$53*$B89 -> 1637.6001 | Q89: =P89 -> 1637.6001 | R89: =Q89 -> 1637.6001 | S89: =R89 -> 1637.6001 | T89: =S89 -> 1637.6001 | U89: =T89 -> 1637.6001 | V89: =U89 -> 1637.6001 | W89: =V89 -> 1637.6001 | X89: =W89 -> 1637.6001 | ... BV89: =BU89 -> 1637.6001
A90: Accounting 1 | B90: 0.002 | C90: =C$53*$B90 -> 0 | D90: =D$53*$B90 -> 0 | E90: =E$53*$B90 -> 0 | F90: =F$53*$B90 -> 0 | G90: =G$53*$B90 -> 0 | H90: =H$53*$B90 -> 0 | I90: 0 | J90: =J$53*$B90 -> 59.46537 | K90: =K$53*$B90 -> 412.47543 | L90: =L$53*$B90 -> 420.37847 | M90: =M$53*$B90 -> 422.17297 | N90: =N$53*$B90 -> 458.44494 | O90: =O$53*$B90 -> 483.96261 | P90: =P$53*$B90 -> 818.80006 | Q90: =Q$53*$B90 -> 1062.7361 | R90: =R$53*$B90 -> 1356.0609 | S90: =R90 -> 1356.0609 | T90: =S90 -> 1356.0609 | U90: =T90 -> 1356.0609 | V90: =U90 -> 1356.0609 | W90: =V90 -> 1356.0609 | X90: =W90 -> 1356.0609 | Y90: =X90 -> 1356.0609 | Z90: =Y90 -> 1356.0609 | ... BV90: =BU90 -> 1356.0609
A91: Accounting 2 | B91: 0.002 | C91: =C$53*$B91 -> 0 | D91: =D$53*$B91 -> 0 | E91: =E$53*$B91 -> 0 | F91: =F$53*$B91 -> 0 | G91: =G$53*$B91 -> 0 | H91: =H$53*$B91 -> 0 | I91: 0 | J91: =J$53*$B91 -> 59.46537 | K91: =K$53*$B91 -> 412.47543 | L91: =L$53*$B91 -> 420.37847 | M91: =M$53*$B91 -> 422.17297 | N91: =N$53*$B91 -> 458.44494 | O91: =O$53*$B91 -> 483.96261 | P91: =P$53*$B91 -> 818.80006 | Q91: =Q$53*$B91 -> 1062.7361 | R91: =R$53*$B91 -> 1356.0609 | S91: =R91 -> 1356.0609 | T91: =S91 -> 1356.0609 | U91: =T91 -> 1356.0609 | V91: =U91 -> 1356.0609 | W91: =V91 -> 1356.0609 | X91: =W91 -> 1356.0609 | Y91: =X91 -> 1356.0609 | Z91: =Y91 -> 1356.0609 | ... BV91: =BU91 -> 1356.0609
A92: Accounting 3 | B92: 0.002 | C92: =C$53*$B92 -> 0 | D92: =D$53*$B92 -> 0 | E92: =E$53*$B92 -> 0 | F92: =F$53*$B92 -> 0 | G92: =G$53*$B92 -> 0 | H92: =H$53*$B92 -> 0 | I92: 0 | J92: =J$53*$B92 -> 59.46537 | K92: =K$53*$B92 -> 412.47543 | L92: =L$53*$B92 -> 420.37847 | M92: =M$53*$B92 -> 422.17297 | N92: =N$53*$B92 -> 458.44494 | O92: =O$53*$B92 -> 483.96261 | P92: =P$53*$B92 -> 818.80006 | Q92: =Q$53*$B92 -> 1062.7361 | R92: =R$53*$B92 -> 1356.0609 | S92: =R92 -> 1356.0609 | T92: =S92 -> 1356.0609 | U92: =T92 -> 1356.0609 | V92: =U92 -> 1356.0609 | W92: =V92 -> 1356.0609 | X92: =W92 -> 1356.0609 | Y92: =X92 -> 1356.0609 | Z92: =Y92 -> 1356.0609 | ... BV92: =BU92 -> 1356.0609
A93: Accounting 4 | B93: 0.002 | C93: =C$53*$B93 -> 0 | D93: =D$53*$B93 -> 0 | E93: =E$53*$B93 -> 0 | F93: =F$53*$B93 -> 0 | G93: =G$53*$B93 -> 0 | H93: =H$53*$B93 -> 0 | I93: 0 | J93: =J$53*$B93 -> 59.46537 | K93: =K$53*$B93 -> 412.47543 | L93: =L$53*$B93 -> 420.37847 | M93: =M$53*$B93 -> 422.17297 | N93: =N$53*$B93 -> 458.44494 | O93: =O$53*$B93 -> 483.96261 | P93: =P$53*$B93 -> 818.80006 | Q93: =Q$53*$B93 -> 1062.7361 | R93: =R$53*$B93 -> 1356.0609 | S93: =R93 -> 1356.0609 | T93: =S93 -> 1356.0609 | U93: =T93 -> 1356.0609 | V93: =U93 -> 1356.0609 | W93: =V93 -> 1356.0609 | X93: =W93 -> 1356.0609 | Y93: =X93 -> 1356.0609 | Z93: =Y93 -> 1356.0609 | ... BV93: =BU93 -> 1356.0609
A94: Felipe Botero - CTO | B94: 0.003 | C94: =C$53*$B94 -> 0 | D94: =D$53*$B94 -> 0 | E94: =E$53*$B94 -> 0 | F94: =F$53*$B94 -> 0 | G94: =G$53*$B94 -> 0 | H94: =H$53*$B94 -> 0 | I94: 0 | J94: =J$53*$B94 -> 89.198055 | K94: =K$53*$B94 -> 618.71315 | L94: =L$53*$B94 -> 630.56771 | M94: =M$53*$B94 -> 633.25946 | N94: =N$53*$B94 -> 687.66741 | O94: =O$53*$B94 -> 725.94391 | P94: =P$53*$B94 -> 1228.2001 | Q94: =Q$53*$B94 -> 1594.1042 | ... T94: =T$53*$B94 -> 4867.1332 | U94: =T94 -> 4867.1332 | V94: =U94 -> 4867.1332 | W94: =V94 -> 4867.1332 | X94: =W94 -> 4867.1332 | Y94: =X94 -> 4867.1332 | Z94: =Y94 -> 4867.1332 | AA94: =Z94 -> 4867.1332 | AB94: =AA94 -> 4867.1332 | ... BV94: =BU94 -> 4867.1332
A95: Development 1 | B95: 0.002 | C95: =C$53*$B95 -> 0 | D95: =D$53*$B95 -> 0 | E95: =E$53*$B95 -> 0 | F95: =F$53*$B95 -> 0 | G95: =G$53*$B95 -> 0 | H95: =H$53*$B95 -> 0 | I95: 0 | J95: =J$53*$B95 -> 59.46537 | K95: =K$53*$B95 -> 412.47543 | L95: =L$53*$B95 -> 420.37847 | M95: =M$53*$B95 -> 422.17297 | N95: =N$53*$B95 -> 458.44494 | O95: =O$53*$B95 -> 483.96261 | P95: =P$53*$B95 -> 818.80006 | Q95: =Q$53*$B95 -> 1062.7361 | ... U95: =U$53*$B95 -> 3250.7856 | V95: =U95 -> 3250.7856 | W95: =V95 -> 3250.7856 | X95: =W95 -> 3250.7856 | Y95: =X95 -> 3250.7856 | Z95: =Y95 -> 3250.7856 | AA95: =Z95 -> 3250.7856 | AB95: =AA95 -> 3250.7856 | AC95: =AB95 -> 3250.7856 | ... BV95: =BU95 -> 3250.7856
A96: Development 2 | B96: 0.002 | C96: =C$53*$B96 -> 0 | D96: =D$53*$B96 -> 0 | E96: =E$53*$B96 -> 0 | F96: =F$53*$B96 -> 0 | G96: =G$53*$B96 -> 0 | H96: =H$53*$B96 -> 0 | I96: 0 | J96: =J$53*$B96 -> 59.46537 | K96: =K$53*$B96 -> 412.47543 | L96: =L$53*$B96 -> 420.37847 | M96: =M$53*$B96 -> 422.17297 | N96: =N$53*$B96 -> 458.44494 | O96: =O$53*$B96 -> 483.96261 | P96: =P$53*$B96 -> 818.80006 | Q96: =Q$53*$B96 -> 1062.7361 | ... U96: =U$53*$B96 -> 3250.7856 | V96: =U96 -> 3250.7856 | W96: =V96 -> 3250.7856 | X96: =W96 -> 3250.7856 | Y96: =X96 -> 3250.7856 | Z96: =Y96 -> 3250.7856 | AA96: =Z96 -> 3250.7856 | AB96: =AA96 -> 3250.7856 | AC96: =AB96 -> 3250.7856 | ... BV96: =BU96 -> 3250.7856
A97: Development 3 | B97: 0.002 | C97: =C$53*$B97 -> 0 | D97: =D$53*$B97 -> 0 | E97: =E$53*$B97 -> 0 | F97: =F$53*$B97 -> 0 | G97: =G$53*$B97 -> 0 | H97: =H$53*$B97 -> 0 | I97: 0 | J97: =J$53*$B97 -> 59.46537 | K97: =K$53*$B97 -> 412.47543 | L97: =L$53*$B97 -> 420.37847 | M97: =M$53*$B97 -> 422.17297 | N97: =N$53*$B97 -> 458.44494 | O97: =O$53*$B97 -> 483.96261 | P97: =P$53*$B97 -> 818.80006 | Q97: =Q$53*$B97 -> 1062.7361 | ... T97: =T$53*$B97 -> 3244.7555 | U97: =T97 -> 3244.7555 | V97: =U97 -> 3244.7555 | W97: =V97 -> 3244.7555 | X97: =W97 -> 3244.7555 | Y97: =X97 -> 3244.7555 | Z97: =Y97 -> 3244.7555 | AA97: =Z97 -> 3244.7555 | AB97: =AA97 -> 3244.7555 | ... BV97: =BU97 -> 3244.7555
A98: Development 4 | B98: 0.002 | C98: =C$53*$B98 -> 0 | D98: =D$53*$B98 -> 0 | E98: =E$53*$B98 -> 0 | F98: =F$53*$B98 -> 0 | G98: =G$53*$B98 -> 0 | H98: =H$53*$B98 -> 0 | I98: 0 | J98: =J$53*$B98 -> 59.46537 | K98: =K$53*$B98 -> 412.47543 | L98: =L$53*$B98 -> 420.37847 | M98: =M$53*$B98 -> 422.17297 | N98: =N$53*$B98 -> 458.44494 | O98: =O$53*$B98 -> 483.96261 | P98: =P$53*$B98 -> 818.80006 | Q98: =Q$53*$B98 -> 1062.7361 | ... T98: =T$53*$B98 -> 3244.7555 | U98: =T98 -> 3244.7555 | V98: =U98 -> 3244.7555 | W98: =V98 -> 3244.7555 | X98: =W98 -> 3244.7555 | Y98: =X98 -> 3244.7555 | Z98: =Y98 -> 3244.7555 | AA98: =Z98 -> 3244.7555 | AB98: =AA98 -> 3244.7555 | ... BV98: =BU98 -> 3244.7555
A99: Aux. Adm | B99: 0.001 | C99: =C$53*$B99 -> 0 | D99: =D$53*$B99 -> 0 | E99: =E$53*$B99 -> 0 | F99: =F$53*$B99 -> 0 | G99: =G$53*$B99 -> 0 | H99: =H$53*$B99 -> 0 | I99: 0 | J99: =J$53*$B99 -> 29.732685 | K99: =K$53*$B99 -> 206.23772 | L99: =L$53*$B99 -> 210.18923 | M99: =M$53*$B99 -> 211.08649 | N99: =N$53*$B99 -> 229.22247 | O99: =O$53*$B99 -> 241.9813 | P99: =P$53*$B99 -> 409.40003 | Q99: =Q$53*$B99 -> 531.36806 | ... V99: =V$53*$B99 -> 2056.7396 | W99: =V99 -> 2056.7396 | X99: =W99 -> 2056.7396 | Y99: =X99 -> 2056.7396 | Z99: =Y99 -> 2056.7396 | AA99: =Z99 -> 2056.7396 | AB99: =AA99 -> 2056.7396 | AC99: =AB99 -> 2056.7396 | AD99: =AC99 -> 2056.7396 | ... BV99: =BU99 -> 2056.7396
A100: Suppliers Team 1 | B100: 0.003 | C100: =C$53*$B100 -> 0 | D100: =D$53*$B100 -> 0 | E100: =E$53*$B100 -> 0 | F100: =F$53*$B100 -> 0 | G100: =G$53*$B100 -> 0 | H100: =H$53*$B100 -> 0 | I100: 0 | J100: =J$53*$B100 -> 89.198055 | K100: =K$53*$B100 -> 618.71315 | L100: =L$53*$B100 -> 630.56771 | M100: =M$53*$B100 -> 633.25946 | N100: =N$53*$B100 -> 687.66741 | O100: =O$53*$B100 -> 725.94391 | P100: =P$53*$B100 -> 1228.2001 | Q100: =P100 -> 1228.2001 | R100: =Q100 -> 1228.2001 | S100: =R100 -> 1228.2001 | T100: =S100 -> 1228.2001 | U100: =T100 -> 1228.2001 | V100: =U100 -> 1228.2001 | W100: =V100 -> 1228.2001 | X100: =W100 -> 1228.2001 | ... BV100: =BU100 -> 1228.2001
A101: Suppliers Team 2 | B101: 0.002 | C101: =C$53*$B101 -> 0 | D101: =D$53*$B101 -> 0 | E101: =E$53*$B101 -> 0 | F101: =F$53*$B101 -> 0 | G101: =G$53*$B101 -> 0 | H101: =H$53*$B101 -> 0 | I101: 0 | J101: =J$53*$B101 -> 59.46537 | K101: =K$53*$B101 -> 412.47543 | L101: =L$53*$B101 -> 420.37847 | M101: =M$53*$B101 -> 422.17297 | N101: =N$53*$B101 -> 458.44494 | O101: =O$53*$B101 -> 483.96261 | P101: =P$53*$B101 -> 818.80006 | Q101: =Q$53*$B101 -> 1062.7361 | ... S101: =S$53*$B101 -> 1360.0617 | T101: =S101 -> 1360.0617 | U101: =T101 -> 1360.0617 | V101: =U101 -> 1360.0617 | W101: =V101 -> 1360.0617 | X101: =W101 -> 1360.0617 | Y101: =X101 -> 1360.0617 | Z101: =Y101 -> 1360.0617 | AA101: =Z101 -> 1360.0617 | ... BV101: =BU101 -> 1360.0617
A102: Suppliers Team 3 | B102: 0.001 | C102: =C$53*$B102 -> 0 | D102: =D$53*$B102 -> 0 | E102: =E$53*$B102 -> 0 | F102: =F$53*$B102 -> 0 | G102: =G$53*$B102 -> 0 | H102: =H$53*$B102 -> 0 | I102: 0 | J102: =J$53*$B102 -> 29.732685 | K102: =K$53*$B102 -> 206.23772 | L102: =L$53*$B102 -> 210.18923 | M102: =M$53*$B102 -> 211.08649 | N102: =N$53*$B102 -> 229.22247 | O102: =O$53*$B102 -> 241.9813 | P102: =P$53*$B102 -> 409.40003 | Q102: =Q$53*$B102 -> 531.36806 | ... T102: =T$53*$B102 -> 1622.3777 | U102: =T102 -> 1622.3777 | V102: =U102 -> 1622.3777 | W102: =V102 -> 1622.3777 | X102: =W102 -> 1622.3777 | Y102: =X102 -> 1622.3777 | Z102: =Y102 -> 1622.3777 | AA102: =Z102 -> 1622.3777 | AB102: =AA102 -> 1622.3777 | ... BV102: =BU102 -> 1622.3777
A103: Human Resouces | B103: 0.003 | C103: =C$53*$B103 -> 0 | D103: =D$53*$B103 -> 0 | E103: =E$53*$B103 -> 0 | F103: =F$53*$B103 -> 0 | G103: =G$53*$B103 -> 0 | H103: =H$53*$B103 -> 0 | I103: 0 | J103: =J$53*$B103 -> 89.198055 | K103: =K$53*$B103 -> 618.71315 | L103: =L$53*$B103 -> 630.56771 | M103: =M$53*$B103 -> 633.25946 | N103: =N$53*$B103 -> 687.66741 | O103: =O$53*$B103 -> 725.94391 | P103: =P$53*$B103 -> 1228.2001 | Q103: =P103 -> 1228.2001 | R103: =Q103 -> 1228.2001 | S103: =R103 -> 1228.2001 | T103: =S103 -> 1228.2001 | U103: =T103 -> 1228.2001 | V103: =U103 -> 1228.2001 | W103: =V103 -> 1228.2001 | X103: =W103 -> 1228.2001 | ... BV103: =BU103 -> 1228.2001
A104: Strategy & Investment | B104: 0.002 | C104: =C$53*$B104 -> 0 | D104: =D$53*$B104 -> 0 | E104: =E$53*$B104 -> 0 | F104: =F$53*$B104 -> 0 | G104: =G$53*$B104 -> 0 | H104: =H$53*$B104 -> 0 | I104: 0 | J104: =J$53*$B104 -> 59.46537 | K104: =K$53*$B104 -> 412.47543 | L104: =L$53*$B104 -> 420.37847 | M104: =M$53*$B104 -> 422.17297 | N104: =N$53*$B104 -> 458.44494 | O104: =O$53*$B104 -> 483.96261 | P104: =P$53*$B104 -> 818.80006 | Q104: =P104 -> 818.80006 | R104: =Q104 -> 818.80006 | S104: =R104 -> 818.80006 | T104: =S104 -> 818.80006 | U104: =T104 -> 818.80006 | V104: =U104 -> 818.80006 | W104: =V104 -> 818.80006 | X104: =W104 -> 818.80006 | ... BV104: =BU104 -> 818.80006
A105: Martin Pinto - CCO | B105: 0.008 | C105: =C$53*$B105 -> 0 | D105: =D$53*$B105 -> 0 | E105: =E$53*$B105 -> 0 | F105: =F$53*$B105 -> 0 | G105: =G$53*$B105 -> 0 | H105: =H$53*$B105 -> 0 | I105: 0 | J105: =J$53*$B105 -> 237.86148 | K105: =K$53*$B105 -> 1649.9017 | L105: =L$53*$B105 -> 1681.5139 | M105: =M$53*$B105 -> 1688.6919 | N105: =N$53*$B105 -> 1833.7798 | O105: =O$53*$B105 -> 1935.8504 | P105: =P$53*$B105 -> 3275.2002 | Q105: =P105 -> 3275.2002 | R105: =Q105 -> 3275.2002 | S105: =R105 -> 3275.2002 | T105: =S105 -> 3275.2002 | U105: =T105 -> 3275.2002 | V105: =U105 -> 3275.2002 | W105: =V105 -> 3275.2002 | X105: 14000 | Y105: =X105 -> 14000 | Z105: =Y105 -> 14000 | AA105: =Z105 -> 14000 | AB105: =AA105 -> 14000 | AC105: =AB105 -> 14000 | AD105: =AC105 -> 14000 | AE105: =AD105 -> 14000 | AF105: =AE105 -> 14000 | ... BV105: =BU105 -> 14000
A106: Commercial Team 2 | B106: 0.003 | C106: =C$53*$B106 -> 0 | D106: =D$53*$B106 -> 0 | E106: =E$53*$B106 -> 0 | F106: =F$53*$B106 -> 0 | G106: =G$53*$B106 -> 0 | H106: =H$53*$B106 -> 0 | I106: 0 | J106: =J$53*$B106 -> 89.198055 | K106: =K$53*$B106 -> 618.71315 | L106: =L$53*$B106 -> 630.56771 | M106: =M$53*$B106 -> 633.25946 | N106: =N$53*$B106 -> 687.66741 | O106: =O$53*$B106 -> 725.94391 | P106: =P$53*$B106 -> 1228.2001 | Q106: =P106 -> 1228.2001 | R106: =Q106 -> 1228.2001 | S106: =R106 -> 1228.2001 | T106: =S106 -> 1228.2001 | U106: =T106 -> 1228.2001 | V106: =U106 -> 1228.2001 | W106: =V106 -> 1228.2001 | X106: =W106 -> 1228.2001 | ... BV106: =BU106 -> 1228.2001
A107: Commercial Team 3 | B107: 0.003 | C107: =C$53*$B107 -> 0 | D107: =D$53*$B107 -> 0 | E107: =E$53*$B107 -> 0 | F107: =F$53*$B107 -> 0 | G107: =G$53*$B107 -> 0 | H107: =H$53*$B107 -> 0 | I107: 0 | J107: =J$53*$B107 -> 89.198055 | K107: =K$53*$B107 -> 618.71315 | L107: =L$53*$B107 -> 630.56771 | M107: =M$53*$B107 -> 633.25946 | N107: =N$53*$B107 -> 687.66741 | O107: =O$53*$B107 -> 725.94391 | P107: =P$53*$B107 -> 1228.2001 | Q107: =P107 -> 1228.2001 | R107: =Q107 -> 1228.2001 | S107: =R107 -> 1228.2001 | T107: =S107 -> 1228.2001 | U107: =T107 -> 1228.2001 | V107: =U107 -> 1228.2001 | W107: =V107 -> 1228.2001 | X107: =W107 -> 1228.2001 | ... BV107: =BU107 -> 1228.2001
...

Sheet Formulas
A1: Call Center 20% | C1: TOTAL SERVICES | E1: 0 | F1: 0 | G1: 0 | H1: 0 | I1: 0 | J1: 0 | K1: 150 | L1: 1100 | M1: 9666 | N1: 9776 | O1: 9821 | P1: 10854 | Q1: 11606 | R1: 20415 | S1: 27297 | T1: 39496 | U1: 39614 | V1: 87668 | W1: 87839 | X1: 104910 | Y1: 105143 | Z1: 105371 | AA1: 105610 | AB1: 105849 | AC1: 122084 | AD1: 122340 | AE1: 125593 | AF1: 125876 | AG1: 126164 | AH1: 126445 | AI1: 126732 | AJ1: 127022 | AK1: 127313 | AL1: 127602 | AM1: 127894 | AN1: 128192 | AO1: 128483 | AP1: 128783 | AQ1: 129083 | AR1: 129380 | AS1: 129685 | AT1: 129988 | AU1: 130291 | AV1: 130600 | AW1: 130905 | AX1: 131218 | AY1: 131530 | AZ1: 131839 | BA1: 132155 | BB1: 132474 | BC1: 132788 | BD1: 133108 | BE1: 133430 | BF1: 133754 | BG1: 134080 | BH1: 134406 | BI1: 134734 | BJ1: 135066 | BK1: 135398 | BL1: 135734 | BM1: 136066 | BN1: 136403 | BO1: 136743 | BP1: 137087 | BQ1: 137429 | BR1: 137775 | BS1: 138122 | BT1: 138473 | BU1: 138823 | BV1: 139176 | BW1: 139532 | BX1: 139889
B2: Unitary Cost | C2: % Ai free HR Assist
B3: 900 | C3: 0.2 | D3: 20% Services | E3: =E1*$C$3 -> 0 | F3: =F1*$C$3 -> 0 | G3: =G1*$C$3 -> 0 | H3: =H1*$C$3 -> 0 | I3: =I1*$C$3 -> 0 | J3: =J1*$C$3 -> 0 | K3: =K1*$C$3 -> 30 | L3: =L1*$C$3 -> 220 | ... BX3: =BX1*$C$3 -> 27977.8
C4: Cases per HR | D4: # HR Neccesary | E4: =E3/$C$5 -> 0 | F4: =F3/$C$5 -> 0 | G4: =G3/$C$5 -> 0 | H4: =H3/$C$5 -> 0 | I4: =I3/$C$5 -> 0 | J4: =J3/$C$5 -> 0 | K4: =K3/$C$5 -> 0.125 | L4: =L3/$C$5 -> 0.91666667 | ... BX4: =BX3/$C$5 -> 116.57417
C5: 240 | D5: Cost | E5: =E4*$B$3 -> 0 | F5: =F4*$B$3 -> 0 | G5: =G4*$B$3 -> 0 | H5: =H4*$B$3 -> 0 | I5: =I4*$B$3 -> 0 | J5: =J4*$B$3 -> 0 | K5: =K4*$B$3 -> 112.5 | L5: =L4*$B$3 -> 825 | ... BX5: =BX4*$B$3 -> 104916.75
A8: Call Center Office | C8: Cost per Position | D8: 100 | E8: =$D$8*E4 -> 0 | F8: =$D$8*F4 -> 0 | G8: =$D$8*G4 -> 0 | H8: =$D$8*H4 -> 0 | I8: =$D$8*I4 -> 0 | J8: =$D$8*J4 -> 0 | K8: =$D$8*K4 -> 12.5 | L8: =$D$8*L4 -> 91.666667 | ... BX8: =$D$8*BX4 -> 11657.417
A11: Costo de IA por llamada | B11: 📞 Twilio Incoming | C11: Transporte de la llamada telefónica | D11: 0.0945
B12: 🗣️ ElevenLabs Voice | C12: Escuchar al usuario y generar la voz de la IA | D12: 0.08
B13: 🧠 Qwen 3.5 | C13: El modelo que procesa la conversación y decide qué responder | D13: 0.028 | E13: Total Llamadas
B14: Record | C14: Grabacion de la llamada | D14: 0.0025 | E14: 1.5 | F14: Factor
B15: TOTAL / MIN | D15: =SUM(D11:D14) -> 0.205 | E15: =$E$14*E1 -> 0 | F15: =$E$14*F1 -> 0 | G15: =$E$14*G1 -> 0 | H15: =$E$14*H1 -> 0 | I15: =$E$14*I1 -> 0 | J15: =$E$14*J1 -> 0 | K15: =$E$14*K1 -> 225 | L15: =$E$14*L1 -> 1650 | ... BX15: =$E$14*BX1 -> 209833.5
B16: TMO / Minutos | C16: 7 | D16: =D15*C16 -> 1.435 | E16: =$D$16*E15 -> 0 | F16: =$D$16*F15 -> 0 | G16: =$D$16*G15 -> 0 | H16: =$D$16*H15 -> 0 | I16: =$D$16*I15 -> 0 | J16: =$D$16*J15 -> 0 | K16: =$D$16*K15 -> 322.875 | L16: =$D$16*L15 -> 2367.75 | ... BX16: =$D$16*BX15 -> 301111.07

Sheet Resumen
A1: Resumen general - Fee for Service
A3: Actor | B3: País | C3: Categoría | D3: Servicio | E3: Casos | F3: Revenue Total ($) | G3: Revenue Weso ($) | H3: Costos Proveedor ($) | I3: Ticket Prom. ($) | J3: Fee Prom. % | K3: Churn Acum.
A4: SEGUROS MONTERREY 🇲🇽 | B4: México | C4: Salud y cuidado | D4: Asistencia Médica Telefónica | E4: 105476 | F4: 4219054 | G4: 1393716 | H4: 2953338 | I4: 40 | J4: 30 | K4: 62203
A5: SEGUROS MONTERREY 🇲🇽 - Hogar | B5: México | C5: Hogar y Propiedades | E5: 33417 | F5: 1670870 | G5: 501261 | H5: 1169609 | I5: 50 | J5: 30 | K5: 11580
A6: CHUBB | B6: Estados Unidos | C6: Veterinario | E6: 494985 | F6: 54448342 | G6: 11017668 | H6: 43558673 | I6: 110 | J6: 20 | K6: 283498
A7: CHUBB - Hogar Singapur | B7: Singapur | C7: Hogar y Propiedades | E7: 20770 | F7: 1453867 | G7: 436160 | H7: 1017707 | I7: 70 | J7: 30 | K7: 10215
A8: CHUBB · Hogar Perú | B8: Perú | C8: Hogar y Propiedades | E8: 10555 | F8: 474977 | G8: 142493 | H8: 332484 | I8: 45 | J8: 30 | K8: 4154
A9: CHUBB · Salud Chile | B9: Chile | C9: Salud y cuidado | E9: 27240 | F9: 1498174 | G9: 449452 | H9: 1048722 | I9: 55 | J9: 30 | K9: 8036
A10: CHUBB - Salud Singapur | B10: Singapur | C10: Salud y cuidado | E10: 6212 | F10: 496998 | G10: 149099 | H10: 347898 | I10: 80 | J10: 30 | K10: 4578
A11: Kanguro Insurance | B11: Estados Unidos | C11: Veterinario | E11: 20019 | F11: 2202054 | G11: 570411 | H11: 1761643 | I11: 110 | J11: 20 | K11: 11742
A12: Kanguro Insurance - Hogar | B12: Estados Unidos | C12: Hogar y Propiedades | E12: 6695 | F12: 1004179 | G12: 301254 | H12: 702925 | I12: 150 | J12: 30 | K12: 5607
A13: METLIFE | B13: Chile | C13: Salud y cuidado | E13: 31154 | F13: 2180800 | G13: 784240 | H13: 1526560 | I13: 70 | J13: 30 | K13: 12258
A14: METLIFE - Salud | B14: Colombia | C14: Salud y cuidado | E14: 38504 | F14: 1925220 | G14: 577566 | H14: 1347654 | I14: 50 | J14: 30 | K14: 13354
A15: Seguros Mundial 🇨🇴 | B15: Colombia | C15: Asistencia en Ruta - Livianos | E15: 27008 | F15: 1620464 | G15: 604139 | H15: 1134325 | I15: 60 | J15: 30 | K15: 13255
A16: Seguros Mundial 🇨🇴 - Hogar | B16: Colombia | C16: Hogar y Propiedades | E16: 4217 | F16: 168675 | G16: 50602 | H16: 118072 | I16: 40 | J16: 30 | K16: 2418
... A35: Liberty Mutual - Hogar | B35: Estados Unidos | C35: Hogar y Propiedades | E35: 570590 | F35: 85588466 | G35: 17117693 | H35: 68470773 | I35: 150 | J35: 20 | K35: 479617
A36: TOTAL | E36: 7219860 | F36: 655824602 | G36: 146138466 | H36: 511216136 | I36: 90.84 | J36: 22.28 | K36: 4220222

Sheet Por Categoría
A1: Categoría | B1: Casos | C1: Revenue Total ($) | D1: Revenue Weso ($)
A2: Salud y cuidado | B2: 249106 | C2: 12951444 | D2: 4265433
A3: Hogar y Propiedades | B3: 1463404 | C3: 144311473 | D3: 32194139
A4: Veterinario | B4: 1176805 | C4: 103311731 | D4: 22479458
A5: Asistencia en Ruta - Livianos | B5: 4330545 | C5: 395249954 | D5: 87199436

Sheet 1_SEGUROS MONTERREY 🇲🇽
A1: SEGUROS MONTERREY 🇲🇽
A2: Categoría: Salud y cuidado · Servicio: Asistencia Médica Telefónica · País: México
A3: Crecimiento: 0.9% · Churn: 0.6%
A5: Métrica | B5: M1 | C5: M2 | D5: M3 | E5: M4 | F5: M5 | G5: M6 | H5: M7 | I5: M8 | J5: M9 | K5: M10 | L5: M11 | M5: M12 | N5: M13 | O5: M14 | P5: M15 | Q5: M16 | R5: M17 | S5: M18 | T5: M19 | U5: M20 | V5: M21 | W5: M22 | X5: M23 | Y5: M24 | Z5: M25 | AA5: M26 | AB5: M27 | AC5: M28 | AD5: M29 | AE5: M30 | AF5: M31 | AG5: M32 | AH5: M33 | AI5: M34 | AJ5: M35 | AK5: M36 | AL5: M37 | AM5: M38 | AN5: M39 | AO5: M40 | AP5: M41 | AQ5: M42 | AR5: M43 | AS5: M44 | AT5: M45 | AU5: M46 | AV5: M47 | AW5: M48 | AX5: M49 | AY5: M50 | AZ5: M51 | BA5: M52 | BB5: M53 | BC5: M54 | BD5: M55 | BE5: M56 | BF5: M57 | BG5: M58 | BH5: M59 | BI5: M60 | BJ5: M61 | BK5: M62 | BL5: M63 | BM5: M64 | BN5: M65 | BO5: M66 | BP5: M67 | BQ5: M68 | BR5: M69 | BS5: M70 | BT5: M71 | BU5: M72 | BV5: TOTAL
A6: Clientes | B6: 0 | C6: 0 | D6: 0 | E6: 0 | F6: 0 | G6: 0 | H6: 0 | I6: 0 | J6: 150000 | K6: 150442 | L6: 150885 | M6: 151330 | N6: 151775 | O6: 152223 | P6: 152671 | Q6: 153121 | R6: 153572 | S6: 154024 | T6: 154478 | U6: 154933 | V6: 155390 | W6: 155847 | X6: 156306 | Y6: 156767 | Z6: 157229 | AA6: 157692 | AB6: 158157 | AC6: 158622 | AD6: 159090 | AE6: 159558 | AF6: 160029 | AG6: 160500 | AH6: 160973 | AI6: 161447 | AJ6: 161923 | AK6: 162400 | AL6: 162878 | AM6: 163358 | AN6: 163839 | AO6: 164322 | AP6: 164806 | AQ6: 165291 | AR6: 165778 | AS6: 166267 | AT6: 166757 | AU6: 167248 | AV6: 167741 | AW6: 168235 | AX6: 168730 | AY6: 169227 | AZ6: 169726 | BA6: 170226 | BB6: 170728 | BC6: 171230 | BD6: 171735 | BE6: 172241 | BF6: 172748 | BG6: 173257 | BH6: 173768 | BI6: 174280 | BJ6: 174793 | BK6: 175308 | BL6: 175824 | BM6: 176342 | BN6: 176862 | BO6: 177383 | BP6: 177905 | BQ6: 178430 | BR6: 178955 | BS6: 179482 | BT6: 180011 | BU6: 180541
A7: Clientes Perdidos (Churn) | B7: 0 | C7: 0 | D7: 0 | E7: 0 | F7: 0 | G7: 0 | H7: 0 | I7: 0 | J7: 0 | K7: 900 | L7: 903 | M7: 905 | N7: 908 | O7: 911 | P7: 913 | Q7: 916 | R7: 919 | S7: 921 | T7: 924 | U7: 927 | V7: 930 | W7: 932 | X7: 935 | Y7: 938 | Z7: 941 | AA7: 943 | AB7: 946 | AC7: 949 | AD7: 952 | AE7: 955 | AF7: 957 | AG7: 960 | AH7: 963 | AI7: 966 | AJ7: 969 | AK7: 972 | AL7: 974 | AM7: 977 | AN7: 980 | AO7: 983 | AP7: 986 | AQ7: 989 | AR7: 992 | AS7: 995 | AT7: 998 | AU7: 1001 | AV7: 1003 | AW7: 1006 | AX7: 1009 | AY7: 1012 | AZ7: 1015 | BA7: 1018 | BB7: 1021 | BC7: 1024 | BD7: 1027 | BE7: 1030 | BF7: 1033 | BG7: 1036 | BH7: 1040 | BI7: 1043 | BJ7: 1046 | BK7: 1049 | BL7: 1052 | BM7: 1055 | BN7: 1058 | BO7: 1061 | BP7: 1064 | BQ7: 1067 | BR7: 1071 | BS7: 1074 | BT7: 1077 | BU7: 1080 | BV7: 62203
A8: Tasa Uso % | B8: 1 | C8: 1 | D8: 1 | E8: 1 | F8: 1 | G8: 1 | H8: 1 | I8: 1 | J8: 1 | K8: 1 | L8: 1 | M8: 1 | N8: 1 | O8: 1 | P8: 1 | Q8: 1 | R8: 1 | S8: 1 | T8: 1 | U8: 1 | V8: 1 | W8: 1 | X8: 1 | Y8: 1 | Z8: 1 | AA8: 1 | AB8: 1 | AC8: 1 | AD8: 1 | AE8: 1 | AF8: 1 | AG8: 1 | AH8: 1 | AI8: 1 | AJ8: 1 | AK8: 1 | AL8: 1 | AM8: 1 | AN8: 1 | AO8: 1 | AP8: 1 | AQ8: 1 | AR8: 1 | AS8: 1 | AT8: 1 | AU8: 1 | AV8: 1 | AW8: 1 | AX8: 1 | AY8: 1 | AZ8: 1 | BA8: 1 | BB8: 1 | BC8: 1 | BD8: 1 | BE8: 1 | BF8: 1 | BG8: 1 | BH8: 1 | BI8: 1 | BJ8: 1 | BK8: 1 | BL8: 1 | BM8: 1 | BN8: 1 | BO8: 1 | BP8: 1 | BQ8: 1 | BR8: 1 | BS8: 1 | BT8: 1 | BU8: 1
A9: Ticket ($) | B9: 40 | C9: 40 | D9: 40 | E9: 40 | F9: 40 | G9: 40 | H9: 40 | I9: 40 | J9: 40 | K9: 40 | L9: 40 | M9: 40 | N9: 40 | O9: 40 | P9: 40 | Q9: 40 | R9: 40 | S9: 40 | T9: 40 | U9: 40 | V9: 40 | W9: 40 | X9: 40 | Y9: 40 | Z9: 40 | AA9: 40 | AB9: 40 | AC9: 40 | AD9: 40 | AE9: 40 | AF9: 40 | AG9: 40 | AH9: 40 | AI9: 40 | AJ9: 40 | AK9: 40 | AL9: 40 | AM9: 40 | AN9: 40 | AO9: 40 | AP9: 40 | AQ9: 40 | AR9: 40 | AS9: 40 | AT9: 40 | AU9: 40 | AV9: 40 | AW9: 40 | AX9: 40 | AY9: 40 | AZ9: 40 | BA9: 40 | BB9: 40 | BC9: 40 | BD9: 40 | BE9: 40 | BF9: 40 | BG9: 40 | BH9: 40 | BI9: 40 | BJ9: 40 | BK9: 40 | BL9: 40 | BM9: 40 | BN9: 40 | BO9: 40 | BP9: 40 | BQ9: 40 | BR9: 40 | BS9: 40 | BT9: 40 | BU9: 40 | BV9: 40.00
A10: Fee Weso % | B10: 30 | C10: 30 | D10: 30 | E10: 30 | F10: 30 | G10: 30 | H10: 30 | I10: 30 | J10: 30 | K10: 30 | L10: 30 | M10: 30 | N10: 30 | O10: 30 | P10: 30 | Q10: 30 | R10: 30 | S10: 30 | T10: 30 | U10: 30 | V10: 30 | W10: 30 | X10: 30 | Y10: 30 | Z10: 30 | AA10: 30 | AB10: 30 | AC10: 30 | AD10: 30 | AE10: 30 | AF10: 30 | AG10: 30 | AH10: 30 | AI10: 30 | AJ10: 30 | AK10: 30 | AL10: 30 | AM10: 30 | AN10: 30 | AO10: 30 | AP10: 30 | AQ10: 30 | AR10: 30 | AS10: 30 | AT10: 30 | AU10: 30 | AV10: 30 | AW10: 30 | AX10: 30 | AY10: 30 | AZ10: 30 | BA10: 30 | BB10: 30 | BC10: 30 | BD10: 30 | BE10: 30 | BF10: 30 | BG10: 30 | BH10: 30 | BI10: 30 | BJ10: 30 | BK10: 30 | BL10: 30 | BM10: 30 | BN10: 30 | BO10: 30 | BP10: 30 | BQ10: 30 | BR10: 30 | BS10: 30 | BT10: 30 | BU10: 30 | BV10: 30.00
A11: Casos | B11: 0 | C11: 0 | D11: 0 | E11: 0 | F11: 0 | G11: 0 | H11: 0 | I11: 0 | J11: 1500 | K11: 1504 | L11: 1509 | M11: 1513 | N11: 1518 | O11: 1522 | P11: 1527 | Q11: 1531 | R11: 1536 | S11: 1540 | T11: 1545 | U11: 1549 | V11: 1554 | W11: 1558 | X11: 1563 | Y11: 1568 | Z11: 1572 | AA11: 1577 | AB11: 1582 | AC11: 1586 | AD11: 1591 | AE11: 1596 | AF11: 1600 | AG11: 1605 | AH11: 1610 | AI11: 1614 | AJ11: 1619 | AK11: 1624 | AL11: 1629 | AM11: 1634 | AN11: 1638 | AO11: 1643 | AP11: 1648 | AQ11: 1653 | AR11: 1658 | AS11: 1663 | AT11: 1668 | AU11: 1672 | AV11: 1677 | AW11: 1682 | AX11: 1687 | AY11: 1692 | AZ11: 1697 | BA11: 1702 | BB11: 1707 | BC11: 1712 | BD11: 1717 | BE11: 1722 | BF11: 1727 | BG11: 1733 | BH11: 1738 | BI11: 1743 | BJ11: 1748 | BK11: 1753 | BL11: 1758 | BM11: 1763 | BN11: 1769 | BO11: 1774 | BP11: 1779 | BQ11: 1784 | BR11: 1790 | BS11: 1795 | BT11: 1800 | BU11: 1805 | BV11: 105476
A12: Revenue Total ($) | B12: 0 | C12: 0 | D12: 0 | E12: 0 | F12: 0 | G12: 0 | H12: 0 | I12: 0 | J12: 60000 | K12: 60177 | L12: 60354 | M12: 60532 | N12: 60710 | O12: 60889 | P12: 61068 | Q12: 61248 | R12: 61429 | S12: 61610 | T12: 61791 | U12: 61973 | V12: 62156 | W12: 62339 | X12: 62523 | Y12: 62707 | Z12: 62892 | AA12: 63077 | AB12: 63263 | AC12: 63449 | AD12: 63636 | AE12: 63823 | AF12: 64011 | AG12: 64200 | AH12: 64389 | AI12: 64579 | AJ12: 64769 | AK12: 64960 | AL12: 65151 | AM12: 65343 | AN12: 65536 | AO12: 65729 | AP12: 65922 | AQ12: 66117 | AR12: 66311 | AS12: 66507 | AT12: 66703 | AU12: 66899 | AV12: 67096 | AW12: 67294 | AX12: 67492 | AY12: 67691 | AZ12: 67890 | BA12: 68090 | BB12: 68291 | BC12: 68492 | BD12: 68694 | BE12: 68896 | BF12: 69099 | BG12: 69303 | BH12: 69507 | BI12: 69712 | BJ12: 69917 | BK12: 70123 | BL12: 70330 | BM12: 70537 | BN12: 70745 | BO12: 70953 | BP12: 71162 | BQ12: 71372 | BR12: 71582 | BS12: 71793 | BT12: 72004 | BU12: 72217 | BV12: 4219054
A13: Fee Variable Weso ($) | B13: 0 | C13: 0 | D13: 0 | E13: 0 | F13: 0 | G13: 0 | H13: 0 | I13: 0 | J13: 18000 | K13: 18053 | L13: 18106 | M13: 18160 | N13: 18213 | O13: 18267 | P13: 18321 | Q13: 18374 | R13: 18429 | S13: 18483 | T13: 18537 | U13: 18592 | V13: 18647 | W13: 18702 | X13: 18757 | Y13: 18812 | Z13: 18867 | AA13: 18923 | AB13: 18979 | AC13: 19035 | AD13: 19091 | AE13: 19147 | AF13: 19203 | AG13: 19260 | AH13: 19317 | AI13: 19374 | AJ13: 19431 | AK13: 19488 | AL13: 19545 | AM13: 19603 | AN13: 19661 | AO13: 19719 | AP13: 19777 | AQ13: 19835 | AR13: 19893 | AS13: 19952 | AT13: 20011 | AU13: 20070 | AV13: 20129 | AW13: 20188 | AX13: 20248 | AY13: 20307 | AZ13: 20367 | BA13: 20427 | BB13: 20487 | BC13: 20548 | BD13: 20608 | BE13: 20669 | BF13: 20730 | BG13: 20791 | BH13: 20852 | BI13: 20914 | BJ13: 20975 | BK13: 21037 | BL13: 21099 | BM13: 21161 | BN13: 21223 | BO13: 21286 | BP13: 21349 | BQ13: 21412 | BR13: 21475 | BS13: 21538 | BT13: 21601 | BU13: 21665 | BV13: 1265716
A14: Licencia Weso ($) | B14: 0 | C14: 0 | D14: 0 | E14: 0 | F14: 0 | G14: 0 | H14: 0 | I14: 0 | J14: 2000 | K14: 2000 | L14: 2000 | M14: 2000 | N14: 2000 | O14: 2000 | P14: 2000 | Q14: 2000 | R14: 2000 | S14: 2000 | T14: 2000 | U14: 2000 | V14: 2000 | W14: 2000 | X14: 2000 | Y14: 2000 | Z14: 2000 | AA14: 2000 | AB14: 2000 | AC14: 2000 | AD14: 2000 | AE14: 2000 | AF14: 2000 | AG14: 2000 | AH14: 2000 | AI14: 2000 | AJ14: 2000 | AK14: 2000 | AL14: 2000 | AM14: 2000 | AN14: 2000 | AO14: 2000 | AP14: 2000 | AQ14: 2000 | AR14: 2000 | AS14: 2000 | AT14: 2000 | AU14: 2000 | AV14: 2000 | AW14: 2000 | AX14: 2000 | AY14: 2000 | AZ14: 2000 | BA14: 2000 | BB14: 2000 | BC14: 2000 | BD14: 2000 | BE14: 2000 | BF14: 2000 | BG14: 2000 | BH14: 2000 | BI14: 2000 | BJ14: 2000 | BK14: 2000 | BL14: 2000 | BM14: 2000 | BN14: 2000 | BO14: 2000 | BP14: 2000 | BQ14: 2000 | BR14: 2000 | BS14: 2000 | BT14: 2000 | BU14: 2000 | BV14: 128000
A15: Revenue Weso ($) | B15: 0 | C15: 0 | D15: 0 | E15: 0 | F15: 0 | G15: 0 | H15: 0 | I15: 0 | J15: 20000 | K15: 20053 | L15: 20106 | M15: 20160 | N15: 20213 | O15: 20267 | P15: 20321 | Q15: 20374 | R15: 20429 | S15: 20483 | T15: 20537 | U15: 20592 | V15: 20647 | W15: 20702 | X15: 20757 | Y15: 20812 | Z15: 20867 | AA15: 20923 | AB15: 20979 | AC15: 21035 | AD15: 21091 | AE15: 21147 | AF15: 21203 | AG15: 21260 | AH15: 21317 | AI15: 21374 | AJ15: 21431 | AK15: 21488 | AL15: 21545 | AM15: 21603 | AN15: 21661 | AO15: 21719 | AP15: 21777 | AQ15: 21835 | AR15: 21893 | AS15: 21952 | AT15: 22011 | AU15: 22070 | AV15: 22129 | AW15: 22188 | AX15: 22248 | AY15: 22307 | AZ15: 22367 | BA15: 22427 | BB15: 22487 | BC15: 22548 | BD15: 22608 | BE15: 22669 | BF15: 22730 | BG15: 22791 | BH15: 22852 | BI15: 22914 | BJ15: 22975 | BK15: 23037 | BL15: 23099 | BM15: 23161 | BN15: 23223 | BO15: 23286 | BP15: 23349 | BQ15: 23412 | BR15: 23475 | BS15: 23538 | BT15: 23601 | BU15: 23665 | BV15: 1393716
A16: Costos Proveedor ($) | B16: 0 | C16: 0 | D16: 0 | E16: 0 | F16: 0 | G16: 0 | H16: 0 | I16: 0 | J16: 42000 | K16: 42124 | L16: 42248 | M16: 42372 | N16: 42497 | O16: 42622 | P16: 42748 | Q16: 42874 | R16: 43000 | S16: 43127 | T16: 43254 | U16: 43381 | V16: 43509 | W16: 43637 | X16: 43766 | Y16: 43895 | Z16: 44024 | AA16: 44154 | AB16: 44284 | AC16: 44414 | AD16: 44545 | AE16: 44676 | AF16: 44808 | AG16: 44940 | AH16: 45072 | AI16: 45205 | AJ16: 45338 | AK16: 45472 | AL16: 45606 | AM16: 45740 | AN16: 45875 | AO16: 46010 | AP16: 46146 | AQ16: 46282 | AR16: 46418 | AS16: 46555 | AT16: 46692 | AU16: 46829 | AV16: 46967 | AW16: 47106 | AX16: 47245 | AY16: 47384 | AZ16: 47523 | BA16: 47663 | BB16: 47804 | BC16: 47945 | BD16: 48086 | BE16: 48227 | BF16: 48370 | BG16: 48512 | BH16: 48655 | BI16: 48798 | BJ16: 48942 | BK16: 49086 | BL16: 49231 | BM16: 49376 | BN16: 49521 | BO16: 49667 | BP16: 49814 | BQ16: 49960 | BR16: 50107 | BS16: 50255 | BT16: 50403 | BU16: 50552 | BV16: 2953338

Sheet 2_SEGUROS MONTERREY 🇲🇽 - Hog
A1: SEGUROS MONTERREY 🇲🇽 - Hogar
A2: Categoría: Hogar y Propiedades · Servicio: · País: México
A3: Crecimiento: 0.9% · Churn: 0.6%
A5: Métrica | B5: M1 | C5: M2 | D5: M3 | E5: M4 | F5: M5 | G5: M6 | H5: M7 | I5: M8 | J5: M9 | K5: M10 | L5: M11 | M5: M12 | N5: M13 | O5: M14 | P5: M15 | Q5: M16 | R5: M17 | S5: M18 | T5: M19 | U5: M20 | V5: M21 | W5: M22 | X5: M23 | Y5: M24 | Z5: M25 | AA5: M26 | AB5: M27 | AC5: M28 | AD5: M29 | AE5: M30 | AF5: M31 | AG5: M32 | AH5: M33 | AI5: M34 | AJ5: M35 | AK5: M36 | AL5: M37 | AM5: M38 | AN5: M39 | AO5: M40 | AP5: M41 | AQ5: M42 | AR5: M43 | AS5: M44 | AT5: M45 | AU5: M46 | AV5: M47 | AW5: M48 | AX5: M49 | AY5: M50 | AZ5: M51 | BA5: M52 | BB5: M53 | BC5: M54 | BD5: M55 | BE5: M56 | BF5: M57 | BG5: M58 | BH5: M59 | BI5: M60 | BJ5: M61 | BK5: M62 | BL5: M63 | BM5: M64 | BN5: M65 | BO5: M66 | BP5: M67 | BQ5: M68 | BR5: M69 | BS5: M70 | BT5: M71 | BU5: M72 | BV5: TOTAL
A6: Clientes | B6: 0 | C6: 0 | D6: 0 | E6: 0 | F6: 0 | G6: 0 | H6: 0 | I6: 0 | J6: 0 | K6: 0 | L6: 0 | M6: 0 | N6: 30000 | O6: 30088 | P6: 30177 | Q6: 30266 | R6: 30355 | S6: 30445 | T6: 30534 | U6: 30624 | V6: 30714 | W6: 30805 | X6: 30896 | Y6: 30987 | Z6: 31078 | AA6: 31169 | AB6: 31261 | AC6: 31353 | AD6: 31446 | AE6: 31538 | AF6: 31631 | AG6: 31724 | AH6: 31818 | AI6: 31912 | AJ6: 32006 | AK6: 32100 | AL6: 32195 | AM6: 32289 | AN6: 32385 | AO6: 32480 | AP6: 32576 | AQ6: 32672 | AR6: 32768 | AS6: 32864 | AT6: 32961 | AU6: 33058 | AV6: 33156 | AW6: 33253 | AX6: 33351 | AY6: 33450 | AZ6: 33548 | BA6: 33647 | BB6: 33746 | BC6: 33845 | BD6: 33945 | BE6: 34045 | BF6: 34146 | BG6: 34246 | BH6: 34347 | BI6: 34448 | BJ6: 34550 | BK6: 34651 | BL6: 34754 | BM6: 34856 | BN6: 34959 | BO6: 35062 | BP6: 35165 | BQ6: 35268 | BR6: 35372 | BS6: 35477 | BT6: 35581 | BU6: 35686
A7: Clientes Perdidos (Churn) | B7: 0 | C7: 0 | D7: 0 | E7: 0 | F7: 0 | G7: 0 | H7: 0 | I7: 0 | J7: 0 | K7: 0 | L7: 0 | M7: 0 | N7: 0 | O7: 180 | P7: 181 | Q7: 181 | R7: 182 | S7: 182 | T7: 183 | U7: 183 | V7: 184 | W7: 184 | X7: 185 | Y7: 185 | Z7: 186 | AA7: 186 | AB7: 187 | AC7: 188 | AD7: 188 | AE7: 189 | AF7: 189 | AG7: 190 | AH7: 190 | AI7: 191 | AJ7: 191 | AK7: 192 | AL7: 193 | AM7: 193 | AN7: 194 | AO7: 194 | AP7: 195 | AQ7: 195 | AR7: 196 | AS7: 197 | AT7: 197 | AU7: 198 | AV7: 198 | AW7: 199 | AX7: 200 | AY7: 200 | AZ7: 201 | BA7: 201 | BB7: 202 | BC7: 202 | BD7: 203 | BE7: 204 | BF7: 204 | BG7: 205 | BH7: 205 | BI7: 206 | BJ7: 207 | BK7: 207 | BL7: 208 | BM7: 209 | BN7: 209 | BO7: 210 | BP7: 210 | BQ7: 211 | BR7: 212 | BS7: 212 | BT7: 213 | BU7: 213 | BV7: 11580
A8: Tasa Uso % | B8: 1.7 | C8: 1.7 | D8: 1.7 | E8: 1.7 | F8: 1.7 | G8: 1.7 | H8: 1.7 | I8: 1.7 | J8: 1.7 | K8: 1.7 | L8: 1.7 | M8: 1.7 | N8: 1.7 | O8: 1.7 | P8: 1.7 | Q8: 1.7 | R8: 1.7 | S8: 1.7 | T8: 1.7 | U8: 1.7 | V8: 1.7 | W8: 1.7 | X8: 1.7 | Y8: 1.7 | Z8: 1.7 | AA8: 1.7 | AB8: 1.7 | AC8: 1.7 | AD8: 1.7 | AE8: 1.7 | AF8: 1.7 | AG8: 1.7 | AH8: 1.7 | AI8: 1.7 | AJ8: 1.7 | AK8: 1.7 | AL8: 1.7 | AM8: 1.7 | AN8: 1.7 | AO8: 1.7 | AP8: 1.7 | AQ8: 1.7 | AR8: 1.7 | AS8: 1.7 | AT8: 1.7 | AU8: 1.7 | AV8: 1.7 | AW8: 1.7 | AX8: 1.7 | AY8: 1.7 | AZ8: 1.7 | BA8: 1.7 | BB8: 1.7 | BC8: 1.7 | BD8: 1.7 | BE8: 1.7 | BF8: 1.7 | BG8: 1.7 | BH8: 1.7 | BI8: 1.7 | BJ8: 1.7 | BK8: 1.7 | BL8: 1.7 | BM8: 1.7 | BN8: 1.7 | BO8: 1.7 | BP8: 1.7 | BQ8: 1.7 | BR8: 1.7 | BS8: 1.7 | BT8: 1.7 | BU8: 1.7
A9: Ticket ($) | B9: 50 | C9: 50 | D9: 50 | E9: 50 | F9: 50 | G9: 50 | H9: 50 | I9: 50 | J9: 50 | K9: 50 | L9: 50 | M9: 50 | N9: 50 | O9: 50 | P9: 50 | Q9: 50 | R9: 50 | S9: 50 | T9: 50 | U9: 50 | V9: 50 | W9: 50 | X9: 50 | Y9: 50 | Z9: 50 | AA9: 50 | AB9: 50 | AC9: 50 | AD9: 50 | AE9: 50 | AF9: 50 | AG9: 50 | AH9: 50 | AI9: 50 | AJ9: 50 | AK9: 50 | AL9: 50 | AM9: 50 | AN9: 50 | AO9: 50 | AP9: 50 | AQ9: 50 | AR9: 50 | AS9: 50 | AT9: 50 | AU9: 50 | AV9: 50 | AW9: 50 | AX9: 50 | AY9: 50 | AZ9: 50 | BA9: 50 | BB9: 50 | BC9: 50 | BD9: 50 | BE9: 50 | BF9: 50 | BG9: 50 | BH9: 50 | BI9: 50 | BJ9: 50 | BK9: 50 | BL9: 50 | BM9: 50 | BN9: 50 | BO9: 50 | BP9: 50 | BQ9: 50 | BR9: 50 | BS9: 50 | BT9: 50 | BU9: 50 | BV9: 50.00
A10: Fee Weso % | B10: 30 | C10: 30 | D10: 30 | E10: 30 | F10: 30 | G10: 30 | H10: 30 | I10: 30 | J10: 30 | K10: 30 | L10: 30 | M10: 30 | N10: 30 | O10: 30 | P10: 30 | Q10: 30 | R10: 30 | S10: 30 | T10: 30 | U10: 30 | V10: 30 | W10: 30 | X10: 30 | Y10: 30 | Z10: 30 | AA10: 30 | AB10: 30 | AC10: 30 | AD10: 30 | AE10: 30 | AF10: 30 | AG10: 30 | AH10: 30 | AI10: 30 | AJ10: 30 | AK10: 30 | AL10: 30 | AM10: 30 | AN10: 30 | AO10: 30 | AP10: 30 | AQ10: 30 | AR10: 30 | AS10: 30 | AT10: 30 | AU10: 30 | AV10: 30 | AW10: 30 | AX10: 30 | AY10: 30 | AZ10: 30 | BA10: 30 | BB10: 30 | BC10: 30 | BD10: 30 | BE10: 30 | BF10: 30 | BG10: 30 | BH10: 30 | BI10: 30 | BJ10: 30 | BK10: 30 | BL10: 30 | BM10: 30 | BN10: 30 | BO10: 30 | BP10: 30 | BQ10: 30 | BR10: 30 | BS10: 30 | BT10: 30 | BU10: 30 | BV10: 30.00
A11: Casos | B11: 0 | C11: 0 | D11: 0 | E11: 0 | F11: 0 | G11: 0 | H11: 0 | I11: 0 | J11: 0 | K11: 0 | L11: 0 | M11: 0 | N11: 510 | O11: 512 | P11: 513 | Q11: 515 | R11: 516 | S11: 518 | T11: 519 | U11: 521 | V11: 522 | W11: 524 | X11: 525 | Y11: 527 | Z11: 528 | AA11: 530 | AB11: 531 | AC11: 533 | AD11: 535 | AE11: 536 | AF11: 538 | AG11: 539 | AH11: 541 | AI11: 542 | AJ11: 544 | AK11: 546 | AL11: 547 | AM11: 549 | AN11: 551 | AO11: 552 | AP11: 554 | AQ11: 555 | AR11: 557 | AS11: 559 | AT11: 560 | AU11: 562 | AV11: 564 | AW11: 565 | AX11: 567 | AY11: 569 | AZ11: 570 | BA11: 572 | BB11: 574 | BC11: 575 | BD11: 577 | BE11: 579 | BF11: 580 | BG11: 582 | BH11: 584 | BI11: 586 | BJ11: 587 | BK11: 589 | BL11: 591 | BM11: 593 | BN11: 594 | BO11: 596 | BP11: 598 | BQ11: 600 | BR11: 601 | BS11: 603 | BT11: 605 | BU11: 607 | BV11: 33417
A12: Revenue Total ($) | B12: 0 | C12: 0 | D12: 0 | E12: 0 | F12: 0 | G12: 0 | H12: 0 | I12: 0 | J12: 0 | K12: 0 | L12: 0 | M12: 0 | N12: 25500 | O12: 25575 | P12: 25650 | Q12: 25726 | R12: 25802 | S12: 25878 | T12: 25954 | U12: 26031 | V12: 26107 | W12: 26184 | X12: 26261 | Y12: 26339 | Z12: 26416 | AA12: 26494 | AB12: 26572 | AC12: 26650 | AD12: 26729 | AE12: 26808 | AF12: 26887 | AG12: 26966 | AH12: 27045 | AI12: 27125 | AJ12: 27205 | AK12: 27285 | AL12: 27365 | AM12: 27446 | AN12: 27527 | AO12: 27608 | AP12: 27689 | AQ12: 27771 | AR12: 27853 | AS12: 27935 | AT12: 28017 | AU12: 28100 | AV12: 28182 | AW12: 28265 | AX12: 28349 | AY12: 28432 | AZ12: 28516 | BA12: 28600 | BB12: 28684 | BC12: 28769 | BD12: 28853 | BE12: 28938 | BF12: 29024 | BG12: 29109 | BH12: 29195 | BI12: 29281 | BJ12: 29367 | BK12: 29454 | BL12: 29540 | BM12: 29628 | BN12: 29715 | BO12: 29802 | BP12: 29890 | BQ12: 29978 | BR12: 30067 | BS12: 30155 | BT12: 30244 | BU12: 30333 | BV12: 1670870
A13: Fee Variable Weso ($) | B13: 0 | C13: 0 | D13: 0 | E13: 0 | F13: 0 | G13: 0 | H13: 0 | I13: 0 | J13: 0 | K13: 0 | L13: 0 | M13: 0 | N13: 7650 | O13: 7673 | P13: 7695 | Q13: 7718 | R13: 7741 | S13: 7763 | T13: 7786 | U13: 7809 | V13: 7832 | W13: 7855 | X13: 7878 | Y13: 7902 | Z13: 7925 | AA13: 7948 | AB13: 7972 | AC13: 7995 | AD13: 8019 | AE13: 8042 | AF13: 8066 | AG13: 8090 | AH13: 8114 | AI13: 8137 | AJ13: 8161 | AK13: 8185 | AL13: 8210 | AM13: 8234 | AN13: 8258 | AO13: 8282 | AP13: 8307 | AQ13: 8331 | AR13: 8356 | AS13: 8380 | AT13: 8405 | AU13: 8430 | AV13: 8455 | AW13: 8480 | AX13: 8505 | AY13: 8530 | AZ13: 8555 | BA13: 8580 | BB13: 8605 | BC13: 8631 | BD13: 8656 | BE13: 8682 | BF13: 8707 | BG13: 8733 | BH13: 8758 | BI13: 8784 | BJ13: 8810 | BK13: 8836 | BL13: 8862 | BM13: 8888 | BN13: 8914 | BO13: 8941 | BP13: 8967 | BQ13: 8993 | BR13: 9020 | BS13: 9047 | BT13: 9073 | BU13: 9100 | BV13: 501261
A14: Licencia Weso ($) | B14: 0 | C14: 0 | D14: 0 | E14: 0 | F14: 0 | G14: 0 | H14: 0 | I14: 0 | J14: 0 | K14: 0 | L14: 0 | M14: 0 | N14: 0 | O14: 0 | P14: 0 | Q14: 0 | R14: 0 | S14: 0 | T14: 0 | U14: 0 | V14: 0 | W14: 0 | X14: 0 | Y14: 0 | Z14: 0 | AA14: 0 | AB14: 0 | AC14: 0 | AD14: 0 | AE14: 0 | AF14: 0 | AG14: 0 | AH14: 0 | AI14: 0 | AJ14: 0 | AK14: 0 | AL14: 0 | AM14: 0 | AN14: 0 | AO14: 0 | AP14: 0 | AQ14: 0 | AR14: 0 | AS14: 0 | AT14: 0 | AU14: 0 | AV14: 0 | AW14: 0 | AX14: 0 | AY14: 0 | AZ14: 0 | BA14: 0 | BB14: 0 | BC14: 0 | BD14: 0 | BE14: 0 | BF14: 0 | BG14: 0 | BH14: 0 | BI14: 0 | BJ14: 0 | BK14: 0 | BL14: 0 | BM14: 0 | BN14: 0 | BO14: 0 | BP14: 0 | BQ14: 0 | BR14: 0 | BS14: 0 | BT14: 0 | BU14: 0 | BV14: 0
A15: Revenue Weso ($) | B15: 0 | C15: 0 | D15: 0 | E15: 0 | F15: 0 | G15: 0 | H15: 0 | I15: 0 | J15: 0 | K15: 0 | L15: 0 | M15: 0 | N15: 7650 | O15: 7673 | P15: 7695 | Q15: 7718 | R15: 7741 | S15: 7763 | T15: 7786 | U15: 7809 | V15: 7832 | W15: 7855 | X15: 7878 | Y15: 7902 | Z15: 7925 | AA15: 7948 | AB15: 7972 | AC15: 7995 | AD15: 8019 | AE15: 8042 | AF15: 8066 | AG15: 8090 | AH15: 8114 | AI15: 8137 | AJ15: 8161 | AK15: 8185 | AL15: 8210 | AM15: 8234 | AN15: 8258 | AO15: 8282 | AP15: 8307 | AQ15: 8331 | AR15: 8356 | AS15: 8380 | AT15: 8405 | AU15: 8430 | AV15: 8455 | AW15: 8480 | AX15: 8505 | AY15: 8530 | AZ15: 8555 | BA15: 8580 | BB15: 8605 | BC15: 8631 | BD15: 8656 | BE15: 8682 | BF15: 8707 | BG15: 8733 | BH15: 8758 | BI15: 8784 | BJ15: 8810 | BK15: 8836 | BL15: 8862 | BM15: 8888 | BN15: 8914 | BO15: 8941 | BP15: 8967 | BQ15: 8993 | BR15: 9020 | BS15: 9047 | BT15: 9073 | BU15: 9100 | BV15: 501261
A16: Costos Proveedor ($) | B16: 0 | C16: 0 | D16: 0 | E16: 0 | F16: 0 | G16: 0 | H16: 0 | I16: 0 | J16: 0 | K16: 0 | L16: 0 | M16: 0 | N16: 17850 | O16: 17903 | P16: 17955 | Q16: 18008 | R16: 18061 | S16: 18114 | T16: 18168 | U16: 18221 | V16: 18275 | W16: 18329 | X16: 18383 | Y16: 18437 | Z16: 18491 | AA16: 18546 | AB16: 18600 | AC16: 18655 | AD16: 18710 | AE16: 18765 | AF16: 18821 | AG16: 18876 | AH16: 18932 | AI16: 18987 | AJ16: 19043 | AK16: 19099 | AL16: 19156 | AM16: 19212 | AN16: 19269 | AO16: 19326 | AP16: 19382 | AQ16: 19440 | AR16: 19497 | AS16: 19554 | AT16: 19612 | AU16: 19670 | AV16: 19728 | AW16: 19786 | AX16: 19844 | AY16: 19902 | AZ16: 19961 | BA16: 20020 | BB16: 20079 | BC16: 20138 | BD16: 20197 | BE16: 20257 | BF16: 20317 | BG16: 20376 | BH16: 20436 | BI16: 20497 | BJ16: 20557 | BK16: 20618 | BL16: 20678 | BM16: 20739 | BN16: 20800 | BO16: 20862 | BP16: 20923 | BQ16: 20985 | BR16: 21047 | BS16: 21109 | BT16: 21171 | BU16: 21233 | BV16: 1169609

Sheet 3_CHUBB
A1: CHUBB
A2: Categoría: Veterinario · Servicio: · País: Estados Unidos
A3: Crecimiento: 1.2% · Churn: 0.7%
A5: Métrica | B5: M1 | C5: M2 | D5: M3 | E5: M4 | F5: M5 | G5: M6 | H5: M7 | I5: M8 | J5: M9 | K5: M10 | L5: M11 | M5: M12 | N5: M13 | O5: M14 | P5: M15 | Q5: M16 | R5: M17 | S5: M18 | T5: M19 | U5: M20 | V5: M21 | W5: M22 | X5: M23 | Y5: M24 | Z5: M25 | AA5: M26 | AB5: M27 | AC5: M28 | AD5: M29 | AE5: M30 | AF5: M31 | AG5: M32 | AH5: M33 | AI5: M34 | AJ5: M35 | AK5: M36 | AL5: M37 | AM5: M38 | AN5: M39 | AO5: M40 | AP5: M41 | AQ5: M42 | AR5: M43 | AS5: M44 | AT5: M45 | AU5: M46 | AV5: M47 | AW5: M48 | AX5: M49 | AY5: M50 | AZ5: M51 | BA5: M52 | BB5: M53 | BC5: M54 | BD5: M55 | BE5: M56 | BF5: M57 | BG5: M58 | BH5: M59 | BI5: M60 | BJ5: M61 | BK5: M62 | BL5: M63 | BM5: M64 | BN5: M65 | BO5: M66 | BP5: M67 | BQ5: M68 | BR5: M69 | BS5: M70 | BT5: M71 | BU5: M72 | BV5: TOTAL
A6: Clientes | B6: 0 | C6: 0 | D6: 0 | E6: 0 | F6: 0 | G6: 0 | H6: 0 | I6: 0 | J6: 550000 | K6: 552704 | L6: 555421 | M6: 558151 | N6: 560895 | O6: 563653 | P6: 566423 | Q6: 569208 | R6: 572006 | S6: 574818 | T6: 577644 | U6: 580484 | V6: 583337 | W6: 586205 | X6: 589087 | Y6: 591983 | Z6: 594893 | AA6: 597818 | AB6: 600756 | AC6: 603710 | AD6: 606678 | AE6: 609660 | AF6: 612657 | AG6: 615669 | AH6: 618695 | AI6: 621737 | AJ6: 624793 | AK6: 627865 | AL6: 630952 | AM6: 634053 | AN6: 637170 | AO6: 640303 | AP6: 643450 | AQ6: 646614 | AR6: 649792 | AS6: 652987 | AT6: 656197 | AU6: 659423 | AV6: 662664 | AW6: 665922 | AX6: 669196 | AY6: 672485 | AZ6: 675791 | BA6: 679114 | BB6: 682452 | BC6: 685807 | BD6: 689178 | BE6: 692566 | BF6: 695971 | BG6: 699393 | BH6: 702831 | BI6: 706286 | BJ6: 709758 | BK6: 713247 | BL6: 716753 | BM6: 720277 | BN6: 723818 | BO6: 727376 | BP6: 730952 | BQ6: 734545 | BR6: 738156 | BS6: 741785 | BT6: 745432 | BU6: 749096
A7: Clientes Perdidos (Churn) | B7: 0 | C7: 0 | D7: 0 | E7: 0 | F7: 0 | G7: 0 | H7: 0 | I7: 0 | J7: 0 | K7: 3850 | L7: 3869 | M7: 3888 | N7: 3907 | O7: 3926 | P7: 3946 | Q7: 3965 | R7: 3984 | S7: 4004 | T7: 4024 | U7: 4044 | V7: 4063 | W7: 4083 | X7: 4103 | Y7: 4124 | Z7: 4144 | AA7: 4164 | AB7: 4185 | AC7: 4205 | AD7: 4226 | AE7: 4247 | AF7: 4268 | AG7: 4289 | AH7: 4310 | AI7: 4331 | AJ7: 4352 | AK7: 4374 | AL7: 4395 | AM7: 4417 | AN7: 4438 | AO7: 4460 | AP7: 4482 | AQ7: 4504 | AR7: 4526 | AS7: 4549 | AT7: 4571 | AU7: 4593 | AV7: 4616 | AW7: 4639 | AX7: 4661 | AY7: 4684 | AZ7: 4707 | BA7: 4731 | BB7: 4754 | BC7: 4777 | BD7: 4801 | BE7: 4824 | BF7: 4848 | BG7: 4872 | BH7: 4896 | BI7: 4920 | BJ7: 4944 | BK7: 4968 | BL7: 4993 | BM7: 5017 | BN7: 5042 | BO7: 5067 | BP7: 5092 | BQ7: 5117 | BR7: 5142 | BS7: 5167 | BT7: 5192 | BU7: 5218 | BV7: 283498
A8: Tasa Uso % | B8: 1.2 | C8: 1.2 | D8: 1.2 | E8: 1.2 | F8: 1.2 | G8: 1.2 | H8: 1.2 | I8: 1.2 | J8: 1.2 | K8: 1.2 | L8: 1.2 | M8: 1.2 | N8: 1.2 | O8: 1.2 | P8: 1.2 | Q8: 1.2 | R8: 1.2 | S8: 1.2 | T8: 1.2 | U8: 1.2 | V8: 1.2 | W8: 1.2 | X8: 1.2 | Y8: 1.2 | Z8: 1.2 | AA8: 1.2 | AB8: 1.2 | AC8: 1.2 | AD8: 1.2 | AE8: 1.2 | AF8: 1.2 | AG8: 1.2 | AH8: 1.2 | AI8: 1.2 | AJ8: 1.2 | AK8: 1.2 | AL8: 1.2 | AM8: 1.2 | AN8: 1.2 | AO8: 1.2 | AP8: 1.2 | AQ8: 1.2 | AR8: 1.2 | AS8: 1.2 | AT8: 1.2 | AU8: 1.2 | AV8: 1.2 | AW8: 1.2 | AX8: 1.2 | AY8: 1.2 | AZ8: 1.2 | BA8: 1.2 | BB8: 1.2 | BC8: 1.2 | BD8: 1.2 | BE8: 1.2 | BF8: 1.2 | BG8: 1.2 | BH8: 1.2 | BI8: 1.2 | BJ8: 1.2 | BK8: 1.2 | BL8: 1.2 | BM8: 1.2 | BN8: 1.2 | BO8: 1.2 | BP8: 1.2 | BQ8: 1.2 | BR8: 1.2 | BS8: 1.2 | BT8: 1.2 | BU8: 1.2
A9: Ticket ($) | B9: 110 | C9: 110 | D9: 110 | E9: 110 | F9: 110 | G9: 110 | H9: 110 | I9: 110 | J9: 110 | K9: 110 | L9: 110 | M9: 110 | N9: 110 | O9: 110 | P9: 110 | Q9: 110 | R9: 110 | S9: 110 | T9: 110 | U9: 110 | V9: 110 | W9: 110 | X9: 110 | Y9: 110 | Z9: 110 | AA9: 110 | AB9: 110 | AC9: 110 | AD9: 110 | AE9: 110 | AF9: 110 | AG9: 110 | AH9: 110 | AI9: 110 | AJ9: 110 | AK9: 110 | AL9: 110 | AM9: 110 | AN9: 110 | AO9: 110 | AP9: 110 | AQ9: 110 | AR9: 110 | AS9: 110 | AT9: 110 | AU9: 110 | AV9: 110 | AW9: 110 | AX9: 110 | AY9: 110 | AZ9: 110 | BA9: 110 | BB9: 110 | BC9: 110 | BD9: 110 | BE9: 110 | BF9: 110 | BG9: 110 | BH9: 110 | BI9: 110 | BJ9: 110 | BK9: 110 | BL9: 110 | BM9: 110 | BN9: 110 | BO9: 110 | BP9: 110 | BQ9: 110 | BR9: 110 | BS9: 110 | BT9: 110 | BU9: 110 | BV9: 110.00
A10: Fee Weso % | B10: 20 | C10: 20 | D10: 20 | E10: 20 | F10: 20 | G10: 20 | H10: 20 | I10: 20 | J10: 20 | K10: 20 | L10: 20 | M10: 20 | N10: 20 | O10: 20 | P10: 20 | Q10: 20 | R10: 20 | S10: 20 | T10: 20 | U10: 20 | V10: 20 | W10: 20 | X10: 20 | Y10: 20 | Z10: 20 | AA10: 20 | AB10: 20 | AC10: 20 | AD10: 20 | AE10: 20 | AF10: 20 | AG10: 20 | AH10: 20 | AI10: 20 | AJ10: 20 | AK10: 20 | AL10: 20 | AM10: 20 | AN10: 20 | AO10: 20 | AP10: 20 | AQ10: 20 | AR10: 20 | AS10: 20 | AT10: 20 | AU10: 20 | AV10: 20 | AW10: 20 | AX10: 20 | AY10: 20 | AZ10: 20 | BA10: 20 | BB10: 20 | BC10: 20 | BD10: 20 | BE10: 20 | BF10: 20 | BG10: 20 | BH10: 20 | BI10: 20 | BJ10: 20 | BK10: 20 | BL10: 20 | BM10: 20 | BN10: 20 | BO10: 20 | BP10: 20 | BQ10: 20 | BR10: 20 | BS10: 20 | BT10: 20 | BU10: 20 | BV10: 20.00
A11: Casos | B11: 0 | C11: 0 | D11: 0 | E11: 0 | F11: 0 | G11: 0 | H11: 0 | I11: 0 | J11: 6600 | K11: 6632 | L11: 6665 | M11: 6698 | N11: 6731 | O11: 6764 | P11: 6797 | Q11: 6830 | R11: 6864 | S11: 6898 | T11: 6932 | U11: 6966 | V11: 7000 | W11: 7034 | X11: 7069 | Y11: 7104 | Z11: 7139 | AA11: 7174 | AB11: 7209 | AC11: 7245 | AD11: 7280 | AE11: 7316 | AF11: 7352 | AG11: 7388 | AH11: 7424 | AI11: 7461 | AJ11: 7498 | AK11: 7534 | AL11: 7571 | AM11: 7609 | AN11: 7646 | AO11: 7684 | AP11: 7721 | AQ11: 7759 | AR11: 7798 | AS11: 7836 | AT11: 7874 | AU11: 7913 | AV11: 7952 | AW11: 7991 | AX11: 8030 | AY11: 8070 | AZ11: 8109 | BA11: 8149 | BB11: 8189 | BC11: 8230 | BD11: 8270 | BE11: 8311 | BF11: 8352 | BG11: 8393 | BH11: 8434 | BI11: 8475 | BJ11: 8517 | BK11: 8559 | BL11: 8601 | BM11: 8643 | BN11: 8686 | BO11: 8729 | BP11: 8771 | BQ11: 8815 | BR11: 8858 | BS11: 8901 | BT11: 8945 | BU11: 8989 | BV11: 494985
A12: Revenue Total ($) | B12: 0 | C12: 0 | D12: 0 | E12: 0 | F12: 0 | G12: 0 | H12: 0 | I12: 0 | J12: 726000 | K12: 729569 | L12: 733156 | M12: 736760 | N12: 740382 | O12: 744021 | P12: 747679 | Q12: 751355 | R12: 755048 | S12: 758760 | T12: 762490 | U12: 766239 | V12: 770005 | W12: 773791 | X12: 777595 | Y12: 781417 | Z12: 785259 | AA12: 789119 | AB12: 792998 | AC12: 796897 | AD12: 800814 | AE12: 804751 | AF12: 808707 | AG12: 812683 | AH12: 816678 | AI12: 820693 | AJ12: 824727 | AK12: 828782 | AL12: 832856 | AM12: 836950 | AN12: 841065 | AO12: 845199 | AP12: 849354 | AQ12: 853530 | AR12: 857726 | AS12: 861942 | AT12: 866180 | AU12: 870438 | AV12: 874717 | AW12: 879017 | AX12: 883338 | AY12: 887681 | AZ12: 892045 | BA12: 896430 | BB12: 900837 | BC12: 905265 | BD12: 909716 | BE12: 914188 | BF12: 918682 | BG12: 923198 | BH12: 927737 | BI12: 932297 | BJ12: 936880 | BK12: 941486 | BL12: 946115 | BM12: 950766 | BN12: 955440 | BO12: 960137 | BP12: 964857 | BQ12: 969600 | BR12: 974366 | BS12: 979156 | BT12: 983970 | BU12: 988807 | BV12: 54448342
A13: Fee Variable Weso ($) | B13: 0 | C13: 0 | D13: 0 | E13: 0 | F13: 0 | G13: 0 | H13: 0 | I13: 0 | J13: 145200 | K13: 145914 | L13: 146631 | M13: 147352 | N13: 148076 | O13: 148804 | P13: 149536 | Q13: 150271 | R13: 151010 | S13: 151752 | T13: 152498 | U13: 153248 | V13: 154001 | W13: 154758 | X13: 155519 | Y13: 156283 | Z13: 157052 | AA13: 157824 | AB13: 158600 | AC13: 159379 | AD13: 160163 | AE13: 160950 | AF13: 161741 | AG13: 162537 | AH13: 163336 | AI13: 164139 | AJ13: 164945 | AK13: 165756 | AL13: 166571 | AM13: 167390 | AN13: 168213 | AO13: 169040 | AP13: 169871 | AQ13: 170706 | AR13: 171545 | AS13: 172388 | AT13: 173236 | AU13: 174088 | AV13: 174943 | AW13: 175803 | AX13: 176668 | AY13: 177536 | AZ13: 178409 | BA13: 179286 | BB13: 180167 | BC13: 181053 | BD13: 181943 | BE13: 182838 | BF13: 183736 | BG13: 184640 | BH13: 185547 | BI13: 186459 | BJ13: 187376 | BK13: 188297 | BL13: 189223 | BM13: 190153 | BN13: 191088 | BO13: 192027 | BP13: 192971 | BQ13: 193920 | BR13: 194873 | BS13: 195831 | BT13: 196794 | BU13: 197761 | BV13: 10889668
A14: Licencia Weso ($) | B14: 0 | C14: 0 | D14: 0 | E14: 0 | F14: 0 | G14: 0 | H14: 0 | I14: 0 | J14: 2000 | K14: 2000 | L14: 2000 | M14: 2000 | N14: 2000 | O14: 2000 | P14: 2000 | Q14: 2000 | R14: 2000 | S14: 2000 | T14: 2000 | U14: 2000 | V14: 2000 | W14: 2000 | X14: 2000 | Y14: 2000 | Z14: 2000 | AA14: 2000 | AB14: 2000 | AC14: 2000 | AD14: 2000 | AE14: 2000 | AF14: 2000 | AG14: 2000 | AH14: 2000 | AI14: 2000 | AJ14: 2000 | AK14: 2000 | AL14: 2000 | AM14: 2000 | AN14: 2000 | AO14: 2000 | AP14: 2000 | AQ14: 2000 | AR14: 2000 | AS14: 2000 | AT14: 2000 | AU14: 2000 | AV14: 2000 | AW14: 2000 | AX14: 2000 | AY14: 2000 | AZ14: 2000 | BA14: 2000 | BB14: 2000 | BC14: 2000 | BD14: 2000 | BE14: 2000 | BF14: 2000 | BG14: 2000 | BH14: 2000 | BI14: 2000 | BJ14: 2000 | BK14: 2000 | BL14: 2000 | BM14: 2000 | BN14: 2000 | BO14: 2000 | BP14: 2000 | BQ14: 2000 | BR14: 2000 | BS14: 2000 | BT14: 2000 | BU14: 2000 | BV14: 128000
A15: Revenue Weso ($) | B15: 0 | C15: 0 | D15: 0 | E15: 0 | F15: 0 | G15: 0 | H15: 0 | I15: 0 | J15: 147200 | K15: 147914 | L15: 148631 | M15: 149352 | N15: 150076 | O15: 150804 | P15: 151536 | Q15: 152271 | R15: 153010 | S15: 153752 | T15: 154498 | U15: 155248 | V15: 156001 | W15: 156758 | X15: 157519 | Y15: 158283 | Z15: 159052 | AA15: 159824 | AB15: 160600 | AC15: 161379 | AD15: 162163 | AE15: 162950 | AF15: 163741 | AG15: 164537 | AH15: 165336 | AI15: 166139 | AJ15: 166945 | AK15: 167756 | AL15: 168571 | AM15: 169390 | AN15: 170213 | AO15: 171040 | AP15: 171871 | AQ15: 172706 | AR15: 173545 | AS15: 174388 | AT15: 175236 | AU15: 176088 | AV15: 176943 | AW15: 177803 | AX15: 178668 | AY15: 179536 | AZ15: 180409 | BA15: 181286 | BB15: 182167 | BC15: 183053 | BD15: 183943 | BE15: 184838 | BF15: 185736 | BG15: 186640 | BH15: 187547 | BI15: 188459 | BJ15: 189376 | BK15: 190297 | BL15: 191223 | BM15: 192153 | BN15: 193088 | BO15: 194027 | BP15: 194971 | BQ15: 195920 | BR15: 196873 | BS15: 197831 | BT15: 198794 | BU15: 199761 | BV15: 11017668
A16: Costos Proveedor ($) | B16: 0 | C16: 0 | D16: 0 | E16: 0 | F16: 0 | G16: 0 | H16: 0 | I16: 0 | J16: 580800 | K16: 583655 | L16: 586524 | M16: 589408 | N16: 592305 | O16: 595217 | P16: 598143 | Q16: 601084 | R16: 604039 | S16: 607008 | T16: 609992 | U16: 612991 | V16: 616004 | W16: 619033 | X16: 622076 | Y16: 625134 | Z16: 628207 | AA16: 631295 | AB16: 634399 | AC16: 637517 | AD16: 640651 | AE16: 643801 | AF16: 646966 | AG16: 650146 | AH16: 653342 | AI16: 656554 | AJ16: 659782 | AK16: 663025 | AL16: 666285 | AM16: 669560 | AN16: 672852 | AO16: 676160 | AP16: 679484 | AQ16: 682824 | AR16: 686181 | AS16: 689554 | AT16: 692944 | AU16: 696350 | AV16: 699774 | AW16: 703214 | AX16: 706671 | AY16: 710145 | AZ16: 713636 | BA16: 717144 | BB16: 720669 | BC16: 724212 | BD16: 727772 | BE16: 731350 | BF16: 734946 | BG16: 738558 | BH16: 742189 | BI16: 745838 | BJ16: 749504 | BK16: 753189 | BL16: 756892 | BM16: 760613 | BN16: 764352 | BO16: 768109 | BP16: 771885 | BQ16: 775680 | BR16: 779493 | BS16: 783325 | BT16: 787176 | BU16: 791046 | BV16: 43558673

Sheet 4_CHUBB - Hogar Singapur
A1: CHUBB - Hogar Singapur
A2: Categoría: Hogar y Propiedades · Servicio: · País: Singapur
A3: Crecimiento: 0.8% · Churn: 0.6%
A5: Métrica | B5: M1 | C5: M2 | D5: M3 | E5: M4 | F5: M5 | G5: M6 | H5: M7 | I5: M8 | J5: M9 | K5: M10 | L5: M11 | M5: M12 | N5: M13 | O5: M14 | P5: M15 | Q5: M16 | R5: M17 | S5: M18 | T5: M19 | U5: M20 | V5: M21 | W5: M22 | X5: M23 | Y5: M24 | Z5: M25 | AA5: M26 | AB5: M27 | AC5: M28 | AD5: M29 | AE5: M30 | AF5: M31 | AG5: M32 | AH5: M33 | AI5: M34 | AJ5: M35 | AK5: M36 | AL5: M37 | AM5: M38 | AN5: M39 | AO5: M40 | AP5: M41 | AQ5: M42 | AR5: M43 | AS5: M44 | AT5: M45 | AU5: M46 | AV5: M47 | AW5: M48 | AX5: M49 | AY5: M50 | AZ5: M51 | BA5: M52 | BB5: M53 | BC5: M54 | BD5: M55 | BE5: M56 | BF5: M57 | BG5: M58 | BH5: M59 | BI5: M60 | BJ5: M61 | BK5: M62 | BL5: M63 | BM5: M64 | BN5: M65 | BO5: M66 | BP5: M67 | BQ5: M68 | BR5: M69 | BS5: M70 | BT5: M71 | BU5: M72 | BV5: TOTAL
A6: Clientes | B6: 0 | C6: 0 | D6: 0 | E6: 0 | F6: 0 | G6: 0 | H6: 0 | I6: 25000 | J6: 25049 | K6: 25098 | L6: 25147 | M6: 25196 | N6: 25245 | O6: 25294 | P6: 25344 | Q6: 25393 | R6: 25443 | S6: 25492 | T6: 25542 | U6: 25592 | V6: 25642 | W6: 25692 | X6: 25742 | Y6: 25792 | Z6: 25843 | AA6: 25893 | AB6: 25944 | AC6: 25994 | AD6: 26045 | AE6: 26096 | AF6: 26147 | AG6: 26198 | AH6: 26249 | AI6: 26300 | AJ6: 26352 | AK6: 26403 | AL6: 26455 | AM6: 26506 | AN6: 26558 | AO6: 26610 | AP6: 26662 | AQ6: 26714 | AR6: 26766 | AS6: 26818 | AT6: 26871 | AU6: 26923 | AV6: 26976 | AW6: 27028 | AX6: 27081 | AY6: 27134 | AZ6: 27187 | BA6: 27240 | BB6: 27293 | BC6: 27346 | BD6: 27400 | BE6: 27453 | BF6: 27507 | BG6: 27560 | BH6: 27614 | BI6: 27668 | BJ6: 27722 | BK6: 27776 | BL6: 27830 | BM6: 27885 | BN6: 27939 | BO6: 27994 | BP6: 28048 | BQ6: 28103 | BR6: 28158 | BS6: 28213 | BT6: 28268 | BU6: 28323
A7: Clientes Perdidos (Churn) | B7: 0 | C7: 0 | D7: 0 | E7: 0 | F7: 0 | G7: 0 | H7: 0 | I7: 0 | J7: 150 | K7: 150 | L7: 151 | M7: 151 | N7: 151 | O7: 151 | P7: 152 | Q7: 152 | R7: 152 | S7: 153 | T7: 153 | U7: 153 | V7: 154 | W7: 154 | X7: 154 | Y7: 154 | Z7: 155 | AA7: 155 | AB7: 155 | AC7: 156 | AD7: 156 | AE7: 156 | AF7: 157 | AG7: 157 | AH7: 157 | AI7: 157 | AJ7: 158 | AK7: 158 | AL7: 158 | AM7: 159 | AN7: 159 | AO7: 159 | AP7: 160 | AQ7: 160 | AR7: 160 | AS7: 161 | AT7: 161 | AU7: 161 | AV7: 162 | AW7: 162 | AX7: 162 | AY7: 162 | AZ7: 163 | BA7: 163 | BB7: 163 | BC7: 164 | BD7: 164 | BE7: 164 | BF7: 165 | BG7: 165 | BH7: 165 | BI7: 166 | BJ7: 166 | BK7: 166 | BL7: 167 | BM7: 167 | BN7: 167 | BO7: 168 | BP7: 168 | BQ7: 168 | BR7: 169 | BS7: 169 | BT7: 169 | BU7: 170 | BV7: 10215
A8: Tasa Uso % | B8: 1.2 | C8: 1.2 | D8: 1.2 | E8: 1.2 | F8: 1.2 | G8: 1.2 | H8: 1.2 | I8: 1.2 | J8: 1.2 | K8: 1.2 | L8: 1.2 | M8: 1.2 | N8: 1.2 | O8: 1.2 | P8: 1.2 | Q8: 1.2 | R8: 1.2 | S8: 1.2 | T8: 1.2 | U8: 1.2 | V8: 1.2 | W8: 1.2 | X8: 1.2 | Y8: 1.2 | Z8: 1.2 | AA8: 1.2 | AB8: 1.2 | AC8: 1.2 | AD8: 1.2 | AE8: 1.2 | AF8: 1.2 | AG8: 1.2 | AH8: 1.2 | AI8: 1.2 | AJ8: 1.2 | AK8: 1.2 | AL8: 1.2 | AM8: 1.2 | AN8: 1.2 | AO8: 1.2 | AP8: 1.2 | AQ8: 1.2 | AR8: 1.2 | AS8: 1.2 | AT8: 1.2 | AU8: 1.2 | AV8: 1.2 | AW8: 1.2 | AX8: 1.2 | AY8: 1.2 | AZ8: 1.2 | BA8: 1.2 | BB8: 1.2 | BC8: 1.2 | BD8: 1.2 | BE8: 1.2 | BF8: 1.2 | BG8: 1.2 | BH8: 1.2 | BI8: 1.2 | BJ8: 1.2 | BK8: 1.2 | BL8: 1.2 | BM8: 1.2 | BN8: 1.2 | BO8: 1.2 | BP8: 1.2 | BQ8: 1.2 | BR8: 1.2 | BS8: 1.2 | BT8: 1.2 | BU8: 1.2
A9: Ticket ($) | B9: 70 | C9: 70 | D9: 70 | E9: 70 | F9: 70 | G9: 70 | H9: 70 | I9: 70 | J9: 70 | K9: 70 | L9: 70 | M9: 70 | N9: 70 | O9: 70 | P9: 70 | Q9: 70 | R9: 70 | S9: 70 | T9: 70 | U9: 70 | V9: 70 | W9: 70 | X9: 70 | Y9: 70 | Z9: 70 | AA9: 70 | AB9: 70 | AC9: 70 | AD9: 70 | AE9: 70 | AF9: 70 | AG9: 70 | AH9: 70 | AI9: 70 | AJ9: 70 | AK9: 70 | AL9: 70 | AM9: 70 | AN9: 70 | AO9: 70 | AP9: 70 | AQ9: 70 | AR9: 70 | AS9: 70 | AT9: 70 | AU9: 70 | AV9: 70 | AW9: 70 | AX9: 70 | AY9: 70 | AZ9: 70 | BA9: 70 | BB9: 70 | BC9: 70 | BD9: 70 | BE9: 70 | BF9: 70 | BG9: 70 | BH9: 70 | BI9: 70 | BJ9: 70 | BK9: 70 | BL9: 70 | BM9: 70 | BN9: 70 | BO9: 70 | BP9: 70 | BQ9: 70 | BR9: 70 | BS9: 70 | BT9: 70 | BU9: 70 | BV9: 70.00
A10: Fee Weso % | B10: 30 | C10: 30 | D10: 30 | E10: 30 | F10: 30 | G10: 30 | H10: 30 | I10: 30 | J10: 30 | K10: 30 | L10: 30 | M10: 30 | N10: 30 | O10: 30 | P10: 30 | Q10: 30 | R10: 30 | S10: 30 | T10: 30 | U10: 30 | V10: 30 | W10: 30 | X10: 30 | Y10: 30 | Z10: 30 | AA10: 30 | AB10: 30 | AC10: 30 | AD10: 30 | AE10: 30 | AF10: 30 | AG10: 30 | AH10: 30 | AI10: 30 | AJ10: 30 | AK10: 30 | AL10: 30 | AM10: 30 | AN10: 30 | AO10: 30 | AP10: 30 | AQ10: 30 | AR10: 30 | AS10: 30 | AT10: 30 | AU10: 30 | AV10: 30 | AW10: 30 | AX10: 30 | AY10: 30 | AZ10: 30 | BA10: 30 | BB10: 30 | BC10: 30 | BD10: 30 | BE10: 30 | BF10: 30 | BG10: 30 | BH10: 30 | BI10: 30 | BJ10: 30 | BK10: 30 | BL10: 30 | BM10: 30 | BN10: 30 | BO10: 30 | BP10: 30 | BQ10: 30 | BR10: 30 | BS10: 30 | BT10: 30 | BU10: 30 | BV10: 30.00
A11: Casos | B11: 0 | C11: 0 | D11: 0 | E11: 0 | F11: 0 | G11: 0 | H11: 0 | I11: 300 | J11: 301 | K11: 301 | L11: 302 | M11: 302 | N11: 303 | O11: 304 | P11: 304 | Q11: 305 | R11: 305 | S11: 306 | T11: 307 | U11: 307 | V11: 308 | W11: 308 | X11: 309 | Y11: 310 | Z11: 310 | AA11: 311 | AB11: 311 | AC11: 312 | AD11: 313 | AE11: 313 | AF11: 314 | AG11: 314 | AH11: 315 | AI11: 316 | AJ11: 316 | AK11: 317 | AL11: 317 | AM11: 318 | AN11: 319 | AO11: 319 | AP11: 320 | AQ11: 321 | AR11: 321 | AS11: 322 | AT11: 322 | AU11: 323 | AV11: 324 | AW11: 324 | AX11: 325 | AY11: 326 | AZ11: 326 | BA11: 327 | BB11: 328 | BC11: 328 | BD11: 329 | BE11: 329 | BF11: 330 | BG11: 331 | BH11: 331 | BI11: 332 | BJ11: 333 | BK11: 333 | BL11: 334 | BM11: 335 | BN11: 335 | BO11: 336 | BP11: 337 | BQ11: 337 | BR11: 338 | BS11: 339 | BT11: 339 | BU11: 340 | BV11: 20770
A12: Revenue Total ($) | B12: 0 | C12: 0 | D12: 0 | E12: 0 | F12: 0 | G12: 0 | H12: 0 | I12: 21000 | J12: 21041 | K12: 21082 | L12: 21123 | M12: 21164 | N12: 21206 | O12: 21247 | P12: 21289 | Q12: 21330 | R12: 21372 | S12: 21414 | T12: 21455 | U12: 21497 | V12: 21539 | W12: 21581 | X12: 21623 | Y12: 21666 | Z12: 21708 | AA12: 21750 | AB12: 21793 | AC12: 21835 | AD12: 21878 | AE12: 21921 | AF12: 21963 | AG12: 22006 | AH12: 22049 | AI12: 22092 | AJ12: 22135 | AK12: 22179 | AL12: 22222 | AM12: 22265 | AN12: 22309 | AO12: 22352 | AP12: 22396 | AQ12: 22440 | AR12: 22483 | AS12: 22527 | AT12: 22571 | AU12: 22615 | AV12: 22659 | AW12: 22704 | AX12: 22748 | AY12: 22792 | AZ12: 22837 | BA12: 22881 | BB12: 22926 | BC12: 22971 | BD12: 23016 | BE12: 23061 | BF12: 23106 | BG12: 23151 | BH12: 23196 | BI12: 23241 | BJ12: 23287 | BK12: 23332 | BL12: 23378 | BM12: 23423 | BN12: 23469 | BO12: 23515 | BP12: 23561 | BQ12: 23607 | BR12: 23653 | BS12: 23699 | BT12: 23745 | BU12: 23792 | BV12: 1453867
A13: Fee Variable Weso ($) | B13: 0 | C13: 0 | D13: 0 | E13: 0 | F13: 0 | G13: 0 | H13: 0 | I13: 6300 | J13: 6312 | K13: 6325 | L13: 6337 | M13: 6349 | N13: 6362 | O13: 6374 | P13: 6387 | Q13: 6399 | R13: 6412 | S13: 6424 | T13: 6437 | U13: 6449 | V13: 6462 | W13: 6474 | X13: 6487 | Y13: 6500 | Z13: 6512 | AA13: 6525 | AB13: 6538 | AC13: 6551 | AD13: 6563 | AE13: 6576 | AF13: 6589 | AG13: 6602 | AH13: 6615 | AI13: 6628 | AJ13: 6641 | AK13: 6654 | AL13: 6667 | AM13: 6680 | AN13: 6693 | AO13: 6706 | AP13: 6719 | AQ13: 6732 | AR13: 6745 | AS13: 6758 | AT13: 6771 | AU13: 6785 | AV13: 6798 | AW13: 6811 | AX13: 6824 | AY13: 6838 | AZ13: 6851 | BA13: 6864 | BB13: 6878 | BC13: 6891 | BD13: 6905 | BE13: 6918 | BF13: 6932 | BG13: 6945 | BH13: 6959 | BI13: 6972 | BJ13: 6986 | BK13: 7000 | BL13: 7013 | BM13: 7027 | BN13: 7041 | BO13: 7054 | BP13: 7068 | BQ13: 7082 | BR13: 7096 | BS13: 7110 | BT13: 7124 | BU13: 7137 | BV13: 436160
A14: Licencia Weso ($) | B14: 0 | C14: 0 | D14: 0 | E14: 0 | F14: 0 | G14: 0 | H14: 0 | I14: 0 | J14: 0 | K14: 0 | L14: 0 | M14: 0 | N14: 0 | O14: 0 | P14: 0 | Q14: 0 | R14: 0 | S14: 0 | T14: 0 | U14: 0 | V14: 0 | W14: 0 | X14: 0 | Y14: 0 | Z14: 0 | AA14: 0 | AB14: 0 | AC14: 0 | AD14: 0 | AE14: 0 | AF14: 0 | AG14: 0 | AH14: 0 | AI14: 0 | AJ14: 0 | AK14: 0 | AL14: 0 | AM14: 0 | AN14: 0 | AO14: 0 | AP14: 0 | AQ14: 0 | AR14: 0 | AS14: 0 | AT14: 0 | AU14: 0 | AV14: 0 | AW14: 0 | AX14: 0 | AY14: 0 | AZ14: 0 | BA14: 0 | BB14: 0 | BC14: 0 | BD14: 0 | BE14: 0 | BF14: 0 | BG14: 0 | BH14: 0 | BI14: 0 | BJ14: 0 | BK14: 0 | BL14: 0 | BM14: 0 | BN14: 0 | BO14: 0 | BP14: 0 | BQ14: 0 | BR14: 0 | BS14: 0 | BT14: 0 | BU14: 0 | BV14: 0
A15: Revenue Weso ($) | B15: 0 | C15: 0 | D15: 0 | E15: 0 | F15: 0 | G15: 0 | H15: 0 | I15: 6300 | J15: 6312 | K15: 6325 | L15: 6337 | M15: 6349 | N15: 6362 | O15: 6374 | P15: 6387 | Q15: 6399 | R15: 6412 | S15: 6424 | T15: 6437 | U15: 6449 | V15: 6462 | W15: 6474 | X15: 6487 | Y15: 6500 | Z15: 6512 | AA15: 6525 | AB15: 6538 | AC15: 6551 | AD15: 6563 | AE15: 6576 | AF15: 6589 | AG15: 6602 | AH15: 6615 | AI15: 6628 | AJ15: 6641 | AK15: 6654 | AL15: 6667 | AM15: 6680 | AN15: 6693 | AO15: 6706 | AP15: 6719 | AQ15: 6732 | AR15: 6745 | AS15: 6758 | AT15: 6771 | AU15: 6785 | AV15: 6798 | AW15: 6811 | AX15: 6824 | AY15: 6838 | AZ15: 6851 | BA15: 6864 | BB15: 6878 | BC15: 6891 | BD15: 6905 | BE15: 6918 | BF15: 6932 | BG15: 6945 | BH15: 6959 | BI15: 6972 | BJ15: 6986 | BK15: 7000 | BL15: 7013 | BM15: 7027 | BN15: 7041 | BO15: 7054 | BP15: 7068 | BQ15: 7082 | BR15: 7096 | BS15: 7110 | BT15: 7124 | BU15: 7137 | BV15: 436160
A16: Costos Proveedor ($) | B16: 0 | C16: 0 | D16: 0 | E16: 0 | F16: 0 | G16: 0 | H16: 0 | I16: 14700 | J16: 14729 | K16: 14757 | L16: 14786 | M16: 14815 | N16: 14844 | O16: 14873 | P16: 14902 | Q16: 14931 | R16: 14960 | S16: 14989 | T16: 15019 | U16: 15048 | V16: 15077 | W16: 15107 | X16: 15136 | Y16: 15166 | Z16: 15195 | AA16: 15225 | AB16: 15255 | AC16: 15285 | AD16: 15314 | AE16: 15344 | AF16: 15374 | AG16: 15404 | AH16: 15434 | AI16: 15465 | AJ16: 15495 | AK16: 15525 | AL16: 15555 | AM16: 15586 | AN16: 15616 | AO16: 15647 | AP16: 15677 | AQ16: 15708 | AR16: 15738 | AS16: 15769 | AT16: 15800 | AU16: 15831 | AV16: 15862 | AW16: 15893 | AX16: 15924 | AY16: 15955 | AZ16: 15986 | BA16: 16017 | BB16: 16048 | BC16: 16080 | BD16: 16111 | BE16: 16142 | BF16: 16174 | BG16: 16206 | BH16: 16237 | BI16: 16269 | BJ16: 16301 | BK16: 16332 | BL16: 16364 | BM16: 16396 | BN16: 16428 | BO16: 16460 | BP16: 16492 | BQ16: 16525 | BR16: 16557 | BS16: 16589 | BT16: 16622 | BU16: 16654 | BV16: 1017707

Sheet 5_CHUBB · Hogar Perú
A1: Actor: CHUBB · Hogar Perú
A2: Categoría: Hogar y Propiedades · Servicio: · País: Perú
A3: Crecimiento: 0.8% · Churn: 0.6%
A5: Métrica | B5: M1 | C5: M2 | D5: M3 | E5: M4 | F5: M5 | G5: M6 | H5: M7 | I5: M8 | J5: M9 | K5: M10 | L5: M11 | M5: M12 | N5: M13 | O5: M14 | P5: M15 | Q5: M16 | R5: M17 | S5: M18 | T5: M19 | U5: M20 | V5: M21 | W5: M22 | X5: M23 | Y5: M24 | Z5: M25 | AA5: M26 | AB5: M27 | AC5: M28 | AD5: M29 | AE5: M30 | AF5: M31 | AG5: M32 | AH5: M33 | AI5: M34 | AJ5: M35 | AK5: M36 | AL5: M37 | AM5: M38 | AN5: M39 | AO5: M40 | AP5: M41 | AQ5: M42 | AR5: M43 | AS5: M44 | AT5: M45 | AU5: M46 | AV5: M47 | AW5: M48 | AX5: M49 | AY5: M50 | AZ5: M51 | BA5: M52 | BB5: M53 | BC5: M54 | BD5: M55 | BE5: M56 | BF5: M57 | BG5: M58 | BH5: M59 | BI5: M60 | BJ5: M61 | BK5: M62 | BL5: M63 | BM5: M64 | BN5: M65 | BO5: M66 | BP5: M67 | BQ5: M68 | BR5: M69 | BS5: M70 | BT5: M71 | BU5: M72 | BV5: TOTAL
A6: Clientes | B6: 0 | C6: 0 | D6: 0 | E6: 0 | F6: 0 | G6: 0 | H6: 10000 | I6: 10020 | J6: 10039 | K6: 10059 | L6: 10078 | M6: 10098 | N6: 10118 | O6: 10137 | P6: 10157 | Q6: 10177 | R6: 10197 | S6: 10217 | T6: 10237 | U6: 10257 | V6: 10277 | W6: 10297 | X6: 10317 | Y6: 10337 | Z6: 10357 | AA6: 10377 | AB6: 10398 | AC6: 10418 | AD6: 10438 | AE6: 10459 | AF6: 10479 | AG6: 10500 | AH6: 10520 | AI6: 10541 | AJ6: 10561 | AK6: 10582 | AL6: 10602 | AM6: 10623 | AN6: 10644 | AO6: 10665 | AP6: 10686 | AQ6: 10706 | AR6: 10727 | AS6: 10748 | AT6: 10769 | AU6: 10790 | AV6: 10811 | AW6: 10832 | AX6: 10854 | AY6: 10875 | AZ6: 10896 | BA6: 10917 | BB6: 10939 | BC6: 10960 | BD6: 10981 | BE6: 11003 | BF6: 11024 | BG6: 11046 | BH6: 11067 | BI6: 11089 | BJ6: 11110 | BK6: 11132 | BL6: 11154 | BM6: 11176 | BN6: 11198 | BO6: 11219 | BP6: 11241 | BQ6: 11263 | BR6: 11285 | BS6: 11307 | BT6: 11329 | BU6: 11351
A7: Clientes Perdidos (Churn) | B7: 0 | C7: 0 | D7: 0 | E7: 0 | F7: 0 | G7: 0 | H7: 0 | I7: 60 | J7: 60 | K7: 60 | L7: 60 | M7: 60 | N7: 61 | O7: 61 | P7: 61 | Q7: 61 | R7: 61 | S7: 61 | T7: 61 | U7: 61 | V7: 62 | W7: 62 | X7: 62 | Y7: 62 | Z7: 62 | AA7: 62 | AB7: 62 | AC7: 62 | AD7: 63 | AE7: 63 | AF7: 63 | AG7: 63 | AH7: 63 | AI7: 63 | AJ7: 63 | AK7: 63 | AL7: 63 | AM7: 64 | AN7: 64 | AO7: 64 | AP7: 64 | AQ7: 64 | AR7: 64 | AS7: 64 | AT7: 64 | AU7: 65 | AV7: 65 | AW7: 65 | AX7: 65 | AY7: 65 | AZ7: 65 | BA7: 65 | BB7: 66 | BC7: 66 | BD7: 66 | BE7: 66 | BF7: 66 | BG7: 66 | BH7: 66 | BI7: 66 | BJ7: 67 | BK7: 67 | BL7: 67 | BM7: 67 | BN7: 67 | BO7: 67 | BP7: 67 | BQ7: 67 | BR7: 68 | BS7: 68 | BT7: 68 | BU7: 68 | BV7: 4154
A8: Tasa Uso % | B8: 1.5 | C8: 1.5 | D8: 1.5 | E8: 1.5 | F8: 1.5 | G8: 1.5 | H8: 1.5 | I8: 1.5 | J8: 1.5 | K8: 1.5 | L8: 1.5 | M8: 1.5 | N8: 1.5 | O8: 1.5 | P8: 1.5 | Q8: 1.5 | R8: 1.5 | S8: 1.5 | T8: 1.5 | U8: 1.5 | V8: 1.5 | W8: 1.5 | X8: 1.5 | Y8: 1.5 | Z8: 1.5 | AA8: 1.5 | AB8: 1.5 | AC8: 1.5 | AD8: 1.5 | AE8: 1.5 | AF8: 1.5 | AG8: 1.5 | AH8: 1.5 | AI8: 1.5 | AJ8: 1.5 | AK8: 1.5 | AL8: 1.5 | AM8: 1.5 | AN8: 1.5 | AO8: 1.5 | AP8: 1.5 | AQ8: 1.5 | AR8: 1.5 | AS8: 1.5 | AT8: 1.5 | AU8: 1.5 | AV8: 1.5 | AW8: 1.5 | AX8: 1.5 | AY8: 1.5 | AZ8: 1.5 | BA8: 1.5 | BB8: 1.5 | BC8: 1.5 | BD8: 1.5 | BE8: 1.5 | BF8: 1.5 | BG8: 1.5 | BH8: 1.5 | BI8: 1.5 | BJ8: 1.5 | BK8: 1.5 | BL8: 1.5 | BM8: 1.5 | BN8: 1.5 | BO8: 1.5 | BP8: 1.5 | BQ8: 1.5 | BR8: 1.5 | BS8: 1.5 | BT8: 1.5 | BU8: 1.5
A9: Ticket ($) | B9: 45 | C9: 45 | D9: 45 | E9: 45 | F9: 45 | G9: 45 | H9: 45 | I9: 45 | J9: 45 | K9: 45 | L9: 45 | M9: 45 | N9: 45 | O9: 45 | P9: 45 | Q9: 45 | R9: 45 | S9: 45 | T9: 45 | U9: 45 | V9: 45 | W9: 45 | X9: 45 | Y9: 45 | Z9: 45 | AA9: 45 | AB9: 45 | AC9: 45 | AD9: 45 | AE9: 45 | AF9: 45 | AG9: 45 | AH9: 45 | AI9: 45 | AJ9: 45 | AK9: 45 | AL9: 45 | AM9: 45 | AN9: 45 | AO9: 45 | AP9: 45 | AQ9: 45 | AR9: 45 | AS9: 45 | AT9: 45 | AU9: 45 | AV9: 45 | AW9: 45 | AX9: 45 | AY9: 45 | AZ9: 45 | BA9: 45 | BB9: 45 | BC9: 45 | BD9: 45 | BE9: 45 | BF9: 45 | BG9: 45 | BH9: 45 | BI9: 45 | BJ9: 45 | BK9: 45 | BL9: 45 | BM9: 45 | BN9: 45 | BO9: 45 | BP9: 45 | BQ9: 45 | BR9: 45 | BS9: 45 | BT9: 45 | BU9: 45 | BV9: 45.00
A10: Fee Weso % | B10: 30 | C10: 30 | D10: 30 | E10: 30 | F10: 30 | G10: 30 | H10: 30 | I10: 30 | J10: 30 | K10: 30 | L10: 30 | M10: 30 | N10: 30 | O10: 30 | P10: 30 | Q10: 30 | R10: 30 | S10: 30 | T10: 30 | U10: 30 | V10: 30 | W10: 30 | X10: 30 | Y10: 30 | Z10: 30 | AA10: 30 | AB10: 30 | AC10: 30 | AD10: 30 | AE10: 30 | AF10: 30 | AG10: 30 | AH10: 30 | AI10: 30 | AJ10: 30 | AK10: 30 | AL10: 30 | AM10: 30 | AN10: 30 | AO10: 30 | AP10: 30 | AQ10: 30 | AR10: 30 | AS10: 30 | AT10: 30 | AU10: 30 | AV10: 30 | AW10: 30 | AX10: 30 | AY10: 30 | AZ10: 30 | BA10: 30 | BB10: 30 | BC10: 30 | BD10: 30 | BE10: 30 | BF10: 30 | BG10: 30 | BH10: 30 | BI10: 30 | BJ10: 30 | BK10: 30 | BL10: 30 | BM10: 30 | BN10: 30 | BO10: 30 | BP10: 30 | BQ10: 30 | BR10: 30 | BS10: 30 | BT10: 30 | BU10: 30 | BV10: 30.00
A11: Casos | B11: 0 | C11: 0 | D11: 0 | E11: 0 | F11: 0 | G11: 0 | H11: 150 | I11: 150 | J11: 151 | K11: 151 | L11: 151 | M11: 151 | N11: 152 | O11: 152 | P11: 152 | Q11: 153 | R11: 153 | S11: 153 | T11: 154 | U11: 154 | V11: 154 | W11: 154 | X11: 155 | Y11: 155 | Z11: 155 | AA11: 156 | AB11: 156 | AC11: 156 | AD11: 157 | AE11: 157 | AF11: 157 | AG11: 157 | AH11: 158 | AI11: 158 | AJ11: 158 | AK11: 159 | AL11: 159 | AM11: 159 | AN11: 160 | AO11: 160 | AP11: 160 | AQ11: 161 | AR11: 161 | AS11: 161 | AT11: 162 | AU11: 162 | AV11: 162 | AW11: 162 | AX11: 163 | AY11: 163 | AZ11: 163 | BA11: 164 | BB11: 164 | BC11: 164 | BD11: 165 | BE11: 165 | BF11: 165 | BG11: 166 | BH11: 166 | BI11: 166 | BJ11: 167 | BK11: 167 | BL11: 167 | BM11: 168 | BN11: 168 | BO11: 168 | BP11: 169 | BQ11: 169 | BR11: 169 | BS11: 170 | BT11: 170 | BU11: 170 | BV11: 10555
A12: Revenue Total ($) | B12: 0 | C12: 0 | D12: 0 | E12: 0 | F12: 0 | G12: 0 | H12: 6750 | I12: 6763 | J12: 6776 | K12: 6790 | L12: 6803 | M12: 6816 | N12: 6829 | O12: 6843 | P12: 6856 | Q12: 6870 | R12: 6883 | S12: 6896 | T12: 6910 | U12: 6923 | V12: 6937 | W12: 6950 | X12: 6964 | Y12: 6978 | Z12: 6991 | AA12: 7005 | AB12: 7018 | AC12: 7032 | AD12: 7046 | AE12: 7060 | AF12: 7073 | AG12: 7087 | AH12: 7101 | AI12: 7115 | AJ12: 7129 | AK12: 7143 | AL12: 7157 | AM12: 7171 | AN12: 7185 | AO12: 7199 | AP12: 7213 | AQ12: 7227 | AR12: 7241 | AS12: 7255 | AT12: 7269 | AU12: 7283 | AV12: 7298 | AW12: 7312 | AX12: 7326 | AY12: 7340 | AZ12: 7355 | BA12: 7369 | BB12: 7383 | BC12: 7398 | BD12: 7412 | BE12: 7427 | BF12: 7441 | BG12: 7456 | BH12: 7470 | BI12: 7485 | BJ12: 7500 | BK12: 7514 | BL12: 7529 | BM12: 7544 | BN12: 7558 | BO12: 7573 | BP12: 7588 | BQ12: 7603 | BR12: 7618 | BS12: 7632 | BT12: 7647 | BU12: 7662 | BV12: 474977
A13: Fee Variable Weso ($) | B13: 0 | C13: 0 | D13: 0 | E13: 0 | F13: 0 | G13: 0 | H13: 2025 | I13: 2029 | J13: 2033 | K13: 2037 | L13: 2041 | M13: 2045 | N13: 2049 | O13: 2053 | P13: 2057 | Q13: 2061 | R13: 2065 | S13: 2069 | T13: 2073 | U13: 2077 | V13: 2081 | W13: 2085 | X13: 2089 | Y13: 2093 | Z13: 2097 | AA13: 2101 | AB13: 2106 | AC13: 2110 | AD13: 2114 | AE13: 2118 | AF13: 2122 | AG13: 2126 | AH13: 2130 | AI13: 2134 | AJ13: 2139 | AK13: 2143 | AL13: 2147 | AM13: 2151 | AN13: 2155 | AO13: 2160 | AP13: 2164 | AQ13: 2168 | AR13: 2172 | AS13: 2177 | AT13: 2181 | AU13: 2185 | AV13: 2189 | AW13: 2194 | AX13: 2198 | AY13: 2202 | AZ13: 2206 | BA13: 2211 | BB13: 2215 | BC13: 2219 | BD13: 2224 | BE13: 2228 | BF13: 2232 | BG13: 2237 | BH13: 2241 | BI13: 2245 | BJ13: 2250 | BK13: 2254 | BL13: 2259 | BM13: 2263 | BN13: 2267 | BO13: 2272 | BP13: 2276 | BQ13: 2281 | BR13: 2285 | BS13: 2290 | BT13: 2294 | BU13: 2299 | BV13: 142493
A14: Licencia Weso ($) | B14: 0 | C14: 0 | D14: 0 | E14: 0 | F14: 0 | G14: 0 | H14: 0 | I14: 0 | J14: 0 | K14: 0 | L14: 0 | M14: 0 | N14: 0 | O14: 0 | P14: 0 | Q14: 0 | R14: 0 | S14: 0 | T14: 0 | U14: 0 | V14: 0 | W14: 0 | X14: 0 | Y14: 0 | Z14: 0 | AA14: 0 | AB14: 0 | AC14: 0 | AD14: 0 | AE14: 0 | AF14: 0 | AG14: 0 | AH14: 0 | AI14: 0 | AJ14: 0 | AK14: 0 | AL14: 0 | AM14: 0 | AN14: 0 | AO14: 0 | AP14: 0 | AQ14: 0 | AR14: 0 | AS14: 0 | AT14: 0 | AU14: 0 | AV14: 0 | AW14: 0 | AX14: 0 | AY14: 0 | AZ14: 0 | BA14: 0 | BB14: 0 | BC14: 0 | BD14: 0 | BE14: 0 | BF14: 0 | BG14: 0 | BH14: 0 | BI14: 0 | BJ14: 0 | BK14: 0 | BL14: 0 | BM14: 0 | BN14: 0 | BO14: 0 | BP14: 0 | BQ14: 0 | BR14: 0 | BS14: 0 | BT14: 0 | BU14: 0 | BV14: 0
A15: Revenue Weso ($) | B15: 0 | C15: 0 | D15: 0 | E15: 0 | F15: 0 | G15: 0 | H15: 2025 | I15: 2029 | J15: 2033 | K15: 2037 | L15: 2041 | M15: 2045 | N15: 2049 | O15: 2053 | P15: 2057 | Q15: 2061 | R15: 2065 | S15: 2069 | T15: 2073 | U15: 2077 | V15: 2081 | W15: 2085 | X15: 2089 | Y15: 2093 | Z15: 2097 | AA15: 2101 | AB15: 2106 | AC15: 2110 | AD15: 2114 | AE15: 2118 | AF15: 2122 | AG15: 2126 | AH15: 2130 | AI15: 2134 | AJ15: 2139 | AK15: 2143 | AL15: 2147 | AM15: 2151 | AN15: 2155 | AO15: 2160 | AP15: 2164 | AQ15: 2168 | AR15: 2172 | AS15: 2177 | AT15: 2181 | AU15: 2185 | AV15: 2189 | AW15: 2194 | AX15: 2198 | AY15: 2202 | AZ15: 2206 | BA15: 2211 | BB15: 2215 | BC15: 2219 | BD15: 2224 | BE15: 2228 | BF15: 2232 | BG15: 2237 | BH15: 2241 | BI15: 2245 | BJ15: 2250 | BK15: 2254 | BL15: 2259 | BM15: 2263 | BN15: 2267 | BO15: 2272 | BP15: 2276 | BQ15: 2281 | BR15: 2285 | BS15: 2290 | BT15: 2294 | BU15: 2299 | BV15: 142493
A16: Costos Proveedor ($) | B16: 0 | C16: 0 | D16: 0 | E16: 0 | F16: 0 | G16: 0 | H16: 4725 | I16: 4734 | J16: 4743 | K16: 4753 | L16: 4762 | M16: 4771 | N16: 4781 | O16: 4790 | P16: 4799 | Q16: 4809 | R16: 4818 | S16: 4827 | T16: 4837 | U16: 4846 | V16: 4856 | W16: 4865 | X16: 4875 | Y16: 4884 | Z16: 4894 | AA16: 4903 | AB16: 4913 | AC16: 4923 | AD16: 4932 | AE16: 4942 | AF16: 4951 | AG16: 4961 | AH16: 4971 | AI16: 4980 | AJ16: 4990 | AK16: 5000 | AL16: 5010 | AM16: 5019 | AN16: 5029 | AO16: 5039 | AP16: 5049 | AQ16: 5059 | AR16: 5069 | AS16: 5079 | AT16: 5088 | AU16: 5098 | AV16: 5108 | AW16: 5118 | AX16: 5128 | AY16: 5138 | AZ16: 5148 | BA16: 5158 | BB16: 5168 | BC16: 5179 | BD16: 5189 | BE16: 5199 | BF16: 5209 | BG16: 5219 | BH16: 5229 | BI16: 5239 | BJ16: 5250 | BK16: 5260 | BL16: 5270 | BM16: 5281 | BN16: 5291 | BO16: 5301 | BP16: 5311 | BQ16: 5322 | BR16: 5332 | BS16: 5343 | BT16: 5353 | BU16: 5364 | BV16: 332484

Sheet 6_CHUBB · Salud Chile
A1: Actor: CHUBB · Salud Chile
A2: Categoría: Salud y cuidado · Servicio: · País: Chile
A3: Crecimiento: 0.8% · Churn: 0.6%
A5: Métrica | B5: M1 | C5: M2 | D5: M3 | E5: M4 | F5: M5 | G5: M6 | H5: M7 | I5: M8 | J5: M9 | K5: M10 | L5: M11 | M5: M12 | N5: M13 | O5: M14 | P5: M15 | Q5: M16 | R5: M17 | S5: M18 | T5: M19 | U5: M20 | V5: M21 | W5: M22 | X5: M23 | Y5: M24 | Z5: M25 | AA5: M26 | AB5: M27 | AC5: M28 | AD5: M29 | AE5: M30 | AF5: M31 | AG5: M32 | AH5: M33 | AI5: M34 | AJ5: M35 | AK5: M36 | AL5: M37 | AM5: M38 | AN5: M39 | AO5: M40 | AP5: M41 | AQ5: M42 | AR5: M43 | AS5: M44 | AT5: M45 | AU5: M46 | AV5: M47 | AW5: M48 | AX5: M49 | AY5: M50 | AZ5: M51 | BA5: M52 | BB5: M53 | BC5: M54 | BD5: M55 | BE5: M56 | BF5: M57 | BG5: M58 | BH5: M59 | BI5: M60 | BJ5: M61 | BK5: M62 | BL5: M63 | BM5: M64 | BN5: M65 | BO5: M66 | BP5: M67 | BQ5: M68 | BR5: M69 | BS5: M70 | BT5: M71 | BU5: M72 | BV5: TOTAL
A6: Clientes | B6: 0 | C6: 0 | D6: 0 | E6: 0 | F6: 0 | G6: 0 | H6: 0 | I6: 0 | J6: 20000 | K6: 20039 | L6: 20078 | M6: 20117 | N6: 20157 | O6: 20196 | P6: 20235 | Q6: 20275 | R6: 20314 | S6: 20354 | T6: 20394 | U6: 20434 | V6: 20474 | W6: 20514 | X6: 20554 | Y6: 20594 | Z6: 20634 | AA6: 20674 | AB6: 20715 | AC6: 20755 | AD6: 20795 | AE6: 20836 | AF6: 20877 | AG6: 20917 | AH6: 20958 | AI6: 20999 | AJ6: 21040 | AK6: 21081 | AL6: 21122 | AM6: 21164 | AN6: 21205 | AO6: 21246 | AP6: 21288 | AQ6: 21329 | AR6: 21371 | AS6: 21413 | AT6: 21455 | AU6: 21496 | AV6: 21538 | AW6: 21580 | AX6: 21623 | AY6: 21665 | AZ6: 21707 | BA6: 21749 | BB6: 21792 | BC6: 21834 | BD6: 21877 | BE6: 21920 | BF6: 21963 | BG6: 22005 | BH6: 22048 | BI6: 22091 | BJ6: 22134 | BK6: 22178 | BL6: 22221 | BM6: 22264 | BN6: 22308 | BO6: 22351 | BP6: 22395 | BQ6: 22439 | BR6: 22483 | BS6: 22526 | BT6: 22570 | BU6: 22614
A7: Clientes Perdidos (Churn) | B7: 0 | C7: 0 | D7: 0 | E7: 0 | F7: 0 | G7: 0 | H7: 0 | I7: 0 | J7: 0 | K7: 120 | L7: 120 | M7: 120 | N7: 121 | O7: 121 | P7: 121 | Q7: 121 | R7: 122 | S7: 122 | T7: 122 | U7: 122 | V7: 123 | W7: 123 | X7: 123 | Y7: 123 | Z7: 124 | AA7: 124 | AB7: 124 | AC7: 124 | AD7: 125 | AE7: 125 | AF7: 125 | AG7: 125 | AH7: 126 | AI7: 126 | AJ7: 126 | AK7: 126 | AL7: 126 | AM7: 127 | AN7: 127 | AO7: 127 | AP7: 127 | AQ7: 128 | AR7: 128 | AS7: 128 | AT7: 128 | AU7: 129 | AV7: 129 | AW7: 129 | AX7: 129 | AY7: 130 | AZ7: 130 | BA7: 130 | BB7: 130 | BC7: 131 | BD7: 131 | BE7: 131 | BF7: 132 | BG7: 132 | BH7: 132 | BI7: 132 | BJ7: 133 | BK7: 133 | BL7: 133 | BM7: 133 | BN7: 134 | BO7: 134 | BP7: 134 | BQ7: 134 | BR7: 135 | BS7: 135 | BT7: 135 | BU7: 135 | BV7: 8036
A8: Tasa Uso % | B8: 2 | C8: 2 | D8: 2 | E8: 2 | F8: 2 | G8: 2 | H8: 2 | I8: 2 | J8: 2 | K8: 2 | L8: 2 | M8: 2 | N8: 2 | O8: 2 | P8: 2 | Q8: 2 | R8: 2 | S8: 2 | T8: 2 | U8: 2 | V8: 2 | W8: 2 | X8: 2 | Y8: 2 | Z8: 2 | AA8: 2 | AB8: 2 | AC8: 2 | AD8: 2 | AE8: 2 | AF8: 2 | AG8: 2 | AH8: 2 | AI8: 2 | AJ8: 2 | AK8: 2 | AL8: 2 | AM8: 2 | AN8: 2 | AO8: 2 | AP8: 2 | AQ8: 2 | AR8: 2 | AS8: 2 | AT8: 2 | AU8: 2 | AV8: 2 | AW8: 2 | AX8: 2 | AY8: 2 | AZ8: 2 | BA8: 2 | BB8: 2 | BC8: 2 | BD8: 2 | BE8: 2 | BF8: 2 | BG8: 2 | BH8: 2 | BI8: 2 | BJ8: 2 | BK8: 2 | BL8: 2 | BM8: 2 | BN8: 2 | BO8: 2 | BP8: 2 | BQ8: 2 | BR8: 2 | BS8: 2 | BT8: 2 | BU8: 2
A9: Ticket ($) | B9: 55 | C9: 55 | D9: 55 | E9: 55 | F9: 55 | G9: 55 | H9: 55 | I9: 55 | J9: 55 | K9: 55 | L9: 55 | M9: 55 | N9: 55 | O9: 55 | P9: 55 | Q9: 55 | R9: 55 | S9: 55 | T9: 55 | U9: 55 | V9: 55 | W9: 55 | X9: 55 | Y9: 55 | Z9: 55 | AA9: 55 | AB9: 55 | AC9: 55 | AD9: 55 | AE9: 55 | AF9: 55 | AG9: 55 | AH9: 55 | AI9: 55 | AJ9: 55 | AK9: 55 | AL9: 55 | AM9: 55 | AN9: 55 | AO9: 55 | AP9: 55 | AQ9: 55 | AR9: 55 | AS9: 55 | AT9: 55 | AU9: 55 | AV9: 55 | AW9: 55 | AX9: 55 | AY9: 55 | AZ9: 55 | BA9: 55 | BB9: 55 | BC9: 55 | BD9: 55 | BE9: 55 | BF9: 55 | BG9: 55 | BH9: 55 | BI9: 55 | BJ9: 55 | BK9: 55 | BL9: 55 | BM9: 55 | BN9: 55 | BO9: 55 | BP9: 55 | BQ9: 55 | BR9: 55 | BS9: 55 | BT9: 55 | BU9: 55 | BV9: 55.00
A10: Fee Weso % | B10: 30 | C10: 30 | D10: 30 | E10: 30 | F10: 30 | G10: 30 | H10: 30 | I10: 30 | J10: 30 | K10: 30 | L10: 30 | M10: 30 | N10: 30 | O10: 30 | P10: 30 | Q10: 30 | R10: 30 | S10: 30 | T10: 30 | U10: 30 | V10: 30 | W10: 30 | X10: 30 | Y10: 30 | Z10: 30 | AA10: 30 | AB10: 30 | AC10: 30 | AD10: 30 | AE10: 30 | AF10: 30 | AG10: 30 | AH10: 30 | AI10: 30 | AJ10: 30 | AK10: 30 | AL10: 30 | AM10: 30 | AN10: 30 | AO10: 30 | AP10: 30 | AQ10: 30 | AR10: 30 | AS10: 30 | AT10: 30 | AU10: 30 | AV10: 30 | AW10: 30 | AX10: 30 | AY10: 30 | AZ10: 30 | BA10: 30 | BB10: 30 | BC10: 30 | BD10: 30 | BE10: 30 | BF10: 30 | BG10: 30 | BH10: 30 | BI10: 30 | BJ10: 30 | BK10: 30 | BL10: 30 | BM10: 30 | BN10: 30 | BO10: 30 | BP10: 30 | BQ10: 30 | BR10: 30 | BS10: 30 | BT10: 30 | BU10: 30 | BV10: 30.00
A11: Casos | B11: 0 | C11: 0 | D11: 0 | E11: 0 | F11: 0 | G11: 0 | H11: 0 | I11: 0 | J11: 400 | K11: 401 | L11: 402 | M11: 402 | N11: 403 | O11: 404 | P11: 405 | Q11: 405 | R11: 406 | S11: 407 | T11: 408 | U11: 409 | V11: 409 | W11: 410 | X11: 411 | Y11: 412 | Z11: 413 | AA11: 413 | AB11: 414 | AC11: 415 | AD11: 416 | AE11: 417 | AF11: 418 | AG11: 418 | AH11: 419 | AI11: 420 | AJ11: 421 | AK11: 422 | AL11: 422 | AM11: 423 | AN11: 424 | AO11: 425 | AP11: 426 | AQ11: 427 | AR11: 427 | AS11: 428 | AT11: 429 | AU11: 430 | AV11: 431 | AW11: 432 | AX11: 432 | AY11: 433 | AZ11: 434 | BA11: 435 | BB11: 436 | BC11: 437 | BD11: 438 | BE11: 438 | BF11: 439 | BG11: 440 | BH11: 441 | BI11: 442 | BJ11: 443 | BK11: 444 | BL11: 444 | BM11: 445 | BN11: 446 | BO11: 447 | BP11: 448 | BQ11: 449 | BR11: 450 | BS11: 451 | BT11: 451 | BU11: 452 | BV11: 27240
A12: Revenue Total ($) | B12: 0 | C12: 0 | D12: 0 | E12: 0 | F12: 0 | G12: 0 | H12: 0 | I12: 0 | J12: 22000 | K12: 22043 | L12: 22086 | M12: 22129 | N12: 22172 | O12: 22216 | P12: 22259 | Q12: 22302 | R12: 22346 | S12: 22390 | T12: 22433 | U12: 22477 | V12: 22521 | W12: 22565 | X12: 22609 | Y12: 22653 | Z12: 22697 | AA12: 22742 | AB12: 22786 | AC12: 22830 | AD12: 22875 | AE12: 22920 | AF12: 22964 | AG12: 23009 | AH12: 23054 | AI12: 23099 | AJ12: 23144 | AK12: 23189 | AL12: 23235 | AM12: 23280 | AN12: 23325 | AO12: 23371 | AP12: 23417 | AQ12: 23462 | AR12: 23508 | AS12: 23554 | AT12: 23600 | AU12: 23646 | AV12: 23692 | AW12: 23738 | AX12: 23785 | AY12: 23831 | AZ12: 23878 | BA12: 23924 | BB12: 23971 | BC12: 24018 | BD12: 24065 | BE12: 24112 | BF12: 24159 | BG12: 24206 | BH12: 24253 | BI12: 24301 | BJ12: 24348 | BK12: 24395 | BL12: 24443 | BM12: 24491 | BN12: 24539 | BO12: 24587 | BP12: 24635 | BQ12: 24683 | BR12: 24731 | BS12: 24779 | BT12: 24827 | BU12: 24876 | BV12: 1498174
A13: Fee Variable Weso ($) | B13: 0 | C13: 0 | D13: 0 | E13: 0 | F13: 0 | G13: 0 | H13: 0 | I13: 0 | J13: 6600 | K13: 6613 | L13: 6626 | M13: 6639 | N13: 6652 | O13: 6665 | P13: 6678 | Q13: 6691 | R13: 6704 | S13: 6717 | T13: 6730 | U13: 6743 | V13: 6756 | W13: 6769 | X13: 6783 | Y13: 6796 | Z13: 6809 | AA13: 6822 | AB13: 6836 | AC13: 6849 | AD13: 6862 | AE13: 6876 | AF13: 6889 | AG13: 6903 | AH13: 6916 | AI13: 6930 | AJ13: 6943 | AK13: 6957 | AL13: 6970 | AM13: 6984 | AN13: 6998 | AO13: 7011 | AP13: 7025 | AQ13: 7039 | AR13: 7052 | AS13: 7066 | AT13: 7080 | AU13: 7094 | AV13: 7108 | AW13: 7122 | AX13: 7135 | AY13: 7149 | AZ13: 7163 | BA13: 7177 | BB13: 7191 | BC13: 7205 | BD13: 7219 | BE13: 7234 | BF13: 7248 | BG13: 7262 | BH13: 7276 | BI13: 7290 | BJ13: 7304 | BK13: 7319 | BL13: 7333 | BM13: 7347 | BN13: 7362 | BO13: 7376 | BP13: 7390 | BQ13: 7405 | BR13: 7419 | BS13: 7434 | BT13: 7448 | BU13: 7463 | BV13: 449452
A14: Licencia Weso ($) | B14: 0 | C14: 0 | D14: 0 | E14: 0 | F14: 0 | G14: 0 | H14: 0 | I14: 0 | J14: 0 | K14: 0 | L14: 0 | M14: 0 | N14: 0 | O14: 0 | P14: 0 | Q14: 0 | R14: 0 | S14: 0 | T14: 0 | U14: 0 | V14: 0 | W14: 0 | X14: 0 | Y14: 0 | Z14: 0 | AA14: 0 | AB14: 0 | AC14: 0 | AD14: 0 | AE14: 0 | AF14: 0 | AG14: 0 | AH14: 0 | AI14: 0 | AJ14: 0 | AK14: 0 | AL14: 0 | AM14: 0 | AN14: 0 | AO14: 0 | AP14: 0 | AQ14: 0 | AR14: 0 | AS14: 0 | AT14: 0 | AU14: 0 | AV14: 0 | AW14: 0 | AX14: 0 | AY14: 0 | AZ14: 0 | BA14: 0 | BB14: 0 | BC14: 0 | BD14: 0 | BE14: 0 | BF14: 0 | BG14: 0 | BH14: 0 | BI14: 0 | BJ14: 0 | BK14: 0 | BL14: 0 | BM14: 0 | BN14: 0 | BO14: 0 | BP14: 0 | BQ14: 0 | BR14: 0 | BS14: 0 | BT14: 0 | BU14: 0 | BV14: 0
A15: Revenue Weso ($) | B15: 0 | C15: 0 | D15: 0 | E15: 0 | F15: 0 | G15: 0 | H15: 0 | I15: 0 | J15: 6600 | K15: 6613 | L15: 6626 | M15: 6639 | N15: 6652 | O15: 6665 | P15: 6678 | Q15: 6691 | R15: 6704 | S15: 6717 | T15: 6730 | U15: 6743 | V15: 6756 | W15: 6769 | X15: 6783 | Y15: 6796 | Z15: 6809 | AA15: 6822 | AB15: 6836 | AC15: 6849 | AD15: 6862 | AE15: 6876 | AF15: 6889 | AG15: 6903 | AH15: 6916 | AI15: 6930 | AJ15: 6943 | AK15: 6957 | AL15: 6970 | AM15: 6984 | AN15: 6998 | AO15: 7011 | AP15: 7025 | AQ15: 7039 | AR15: 7052 | AS15: 7066 | AT15: 7080 | AU15: 7094 | AV15: 7108 | AW15: 7122 | AX15: 7135 | AY15: 7149 | AZ15: 7163 | BA15: 7177 | BB15: 7191 | BC15: 7205 | BD15: 7219 | BE15: 7234 | BF15: 7248 | BG15: 7262 | BH15: 7276 | BI15: 7290 | BJ15: 7304 | BK15: 7319 | BL15: 7333 | BM15: 7347 | BN15: 7362 | BO15: 7376 | BP15: 7390 | BQ15: 7405 | BR15: 7419 | BS15: 7434 | BT15: 7448 | BU15: 7463 | BV15: 449452
A16: Costos Proveedor ($) | B16: 0 | C16: 0 | D16: 0 | E16: 0 | F16: 0 | G16: 0 | H16: 0 | I16: 0 | J16: 15400 | K16: 15430 | L16: 15460 | M16: 15490 | N16: 15521 | O16: 15551 | P16: 15581 | Q16: 15612 | R16: 15642 | S16: 15673 | T16: 15703 | U16: 15734 | V16: 15765 | W16: 15795 | X16: 15826 | Y16: 15857 | Z16: 15888 | AA16: 15919 | AB16: 15950 | AC16: 15981 | AD16: 16012 | AE16: 16044 | AF16: 16075 | AG16: 16106 | AH16: 16138 | AI16: 16169 | AJ16: 16201 | AK16: 16233 | AL16: 16264 | AM16: 16296 | AN16: 16328 | AO16: 16360 | AP16: 16392 | AQ16: 16424 | AR16: 16456 | AS16: 16488 | AT16: 16520 | AU16: 16552 | AV16: 16585 | AW16: 16617 | AX16: 16649 | AY16: 16682 | AZ16: 16714 | BA16: 16747 | BB16: 16780 | BC16: 16812 | BD16: 16845 | BE16: 16878 | BF16: 16911 | BG16: 16944 | BH16: 16977 | BI16: 17010 | BJ16: 17044 | BK16: 17077 | BL16: 17110 | BM16: 17144 | BN16: 17177 | BO16: 17211 | BP16: 17244 | BQ16: 17278 | BR16: 17312 | BS16: 17345 | BT16: 17379 | BU16: 17413 | BV16: 1048722

Sheet 7_CHUBB - Salud Singapur
A1: Actor: CHUBB - Salud Singapur
A2: Categoría: Salud y cuidado · Servicio: · País: Singapur
A3: Crecimiento: 0.8% · Churn: 0.6%
A5: Métrica | B5: M1 | C5: M2 | D5: M3 | E5: M4 | F5: M5 | G5: M6 | H5: M7 | I5: M8 | J5: M9 | K5: M10 | L5: M11 | M5: M12 | N5: M13 | O5: M14 | P5: M15 | Q5: M16 | R5: M17 | S5: M18 | T5: M19 | U5: M20 | V5: M21 | W5: M22 | X5: M23 | Y5: M24 | Z5: M25 | AA5: M26 | AB5: M27 | AC5: M28 | AD5: M29 | AE5: M30 | AF5: M31 | AG5: M32 | AH5: M33 | AI5: M34 | AJ5: M35 | AK5: M36 | AL5: M37 | AM5: M38 | AN5: M39 | AO5: M40 | AP5: M41 | AQ5: M42 | AR5: M43 | AS5: M44 | AT5: M45 | AU5: M46 | AV5: M47 | AW5: M48 | AX5: M49 | AY5: M50 | AZ5: M51 | BA5: M52 | BB5: M53 | BC5: M54 | BD5: M55 | BE5: M56 | BF5: M57 | BG5: M58 | BH5: M59 | BI5: M60 | BJ5: M61 | BK5: M62 | BL5: M63 | BM5: M64 | BN5: M65 | BO5: M66 | BP5: M67 | BQ5: M68 | BR5: M69 | BS5: M70 | BT5: M71 | BU5: M72 | BV5: TOTAL
A6: Clientes | B6: 0 | C6: 0 | D6: 0 | E6: 0 | F6: 0 | G6: 0 | H6: 0 | I6: 0 | J6: 0 | K6: 0 | L6: 0 | M6: 12000 | N6: 12023 | O6: 12047 | P6: 12070 | Q6: 12094 | R6: 12118 | S6: 12141 | T6: 12165 | U6: 12189 | V6: 12212 | W6: 12236 | X6: 12260 | Y6: 12284 | Z6: 12308 | AA6: 12332 | AB6: 12356 | AC6: 12380 | AD6: 12404 | AE6: 12429 | AF6: 12453 | AG6: 12477 | AH6: 12502 | AI6: 12526 | AJ6: 12550 | AK6: 12575 | AL6: 12600 | AM6: 12624 | AN6: 12649 | AO6: 12673 | AP6: 12698 | AQ6: 12723 | AR6: 12748 | AS6: 12773 | AT6: 12798 | AU6: 12823 | AV6: 12848 | AW6: 12873 | AX6: 12898 | AY6: 12923 | AZ6: 12948 | BA6: 12974 | BB6: 12999 | BC6: 13024 | BD6: 13050 | BE6: 13075 | BF6: 13101 | BG6: 13126 | BH6: 13152 | BI6: 13178 | BJ6: 13203 | BK6: 13229 | BL6: 13255 | BM6: 13281 | BN6: 13307 | BO6: 13333 | BP6: 13359 | BQ6: 13385 | BR6: 13411 | BS6: 13437 | BT6: 13463 | BU6: 13490
A7: Clientes Perdidos (Churn) | B7: 0 | C7: 0 | D7: 0 | E7: 0 | F7: 0 | G7: 0 | H7: 0 | I7: 0 | J7: 0 | K7: 0 | L7: 0 | M7: 0 | N7: 72 | O7: 72 | P7: 72 | Q7: 72 | R7: 73 | S7: 73 | T7: 73 | U7: 73 | V7: 73 | W7: 73 | X7: 73 | Y7: 74 | Z7: 74 | AA7: 74 | AB7: 74 | AC7: 74 | AD7: 74 | AE7: 74 | AF7: 75 | AG7: 75 | AH7: 75 | AI7: 75 | AJ7: 75 | AK7: 75 | AL7: 75 | AM7: 76 | AN7: 76 | AO7: 76 | AP7: 76 | AQ7: 76 | AR7: 76 | AS7: 76 | AT7: 77 | AU7: 77 | AV7: 77 | AW7: 77 | AX7: 77 | AY7: 77 | AZ7: 78 | BA7: 78 | BB7: 78 | BC7: 78 | BD7: 78 | BE7: 78 | BF7: 78 | BG7: 79 | BH7: 79 | BI7: 79 | BJ7: 79 | BK7: 79 | BL7: 79 | BM7: 80 | BN7: 80 | BO7: 80 | BP7: 80 | BQ7: 80 | BR7: 80 | BS7: 80 | BT7: 81 | BU7: 81 | BV7: 4578
A8: Tasa Uso % | B8: 0.8 | C8: 0.8 | D8: 0.8 | E8: 0.8 | F8: 0.8 | G8: 0.8 | H8: 0.8 | I8: 0.8 | J8: 0.8 | K8: 0.8 | L8: 0.8 | M8: 0.8 | N8: 0.8 | O8: 0.8 | P8: 0.8 | Q8: 0.8 | R8: 0.8 | S8: 0.8 | T8: 0.8 | U8: 0.8 | V8: 0.8 | W8: 0.8 | X8: 0.8 | Y8: 0.8 | Z8: 0.8 | AA8: 0.8 | AB8: 0.8 | AC8: 0.8 | AD8: 0.8 | AE8: 0.8 | AF8: 0.8 | AG8: 0.8 | AH8: 0.8 | AI8: 0.8 | AJ8: 0.8 | AK8: 0.8 | AL8: 0.8 | AM8: 0.8 | AN8: 0.8 | AO8: 0.8 | AP8: 0.8 | AQ8: 0.8 | AR8: 0.8 | AS8: 0.8 | AT8: 0.8 | AU8: 0.8 | AV8: 0.8 | AW8: 0.8 | AX8: 0.8 | AY8: 0.8 | AZ8: 0.8 | BA8: 0.8 | BB8: 0.8 | BC8: 0.8 | BD8: 0.8 | BE8: 0.8 | BF8: 0.8 | BG8: 0.8 | BH8: 0.8 | BI8: 0.8 | BJ8: 0.8 | BK8: 0.8 | BL8: 0.8 | BM8: 0.8 | BN8: 0.8 | BO8: 0.8 | BP8: 0.8 | BQ8: 0.8 | BR8: 0.8 | BS8: 0.8 | BT8: 0.8 | BU8: 0.8
A9: Ticket ($) | B9: 80 | C9: 80 | D9: 80 | E9: 80 | F9: 80 | G9: 80 | H9: 80 | I9: 80 | J9: 80 | K9: 80 | L9: 80 | M9: 80 | N9: 80 | O9: 80 | P9: 80 | Q9: 80 | R9: 80 | S9: 80 | T9: 80 | U9: 80 | V9: 80 | W9: 80 | X9: 80 | Y9: 80 | Z9: 80 | AA9: 80 | AB9: 80 | AC9: 80 | AD9: 80 | AE9: 80 | AF9: 80 | AG9: 80 | AH9: 80 | AI9: 80 | AJ9: 80 | AK9: 80 | AL9: 80 | AM9: 80 | AN9: 80 | AO9: 80 | AP9: 80 | AQ9: 80 | AR9: 80 | AS9: 80 | AT9: 80 | AU9: 80 | AV9: 80 | AW9: 80 | AX9: 80 | AY9: 80 | AZ9: 80 | BA9: 80 | BB9: 80 | BC9: 80 | BD9: 80 | BE9: 80 | BF9: 80 | BG9: 80 | BH9: 80 | BI9: 80 | BJ9: 80 | BK9: 80 | BL9: 80 | BM9: 80 | BN9: 80 | BO9: 80 | BP9: 80 | BQ9: 80 | BR9: 80 | BS9: 80 | BT9: 80 | BU9: 80 | BV9: 80.00
A10: Fee Weso % | B10: 30 | C10: 30 | D10: 30 | E10: 30 | F10: 30 | G10: 30 | H10: 30 | I10: 30 | J10: 30 | K10: 30 | L10: 30 | M10: 30 | N10: 30 | O10: 30 | P10: 30 | Q10: 30 | R10: 30 | S10: 30 | T10: 30 | U10: 30 | V10: 30 | W10: 30 | X10: 30 | Y10: 30 | Z10: 30 | AA10: 30 | AB10: 30 | AC10: 30 | AD10: 30 | AE10: 30 | AF10: 30 | AG10: 30 | AH10: 30 | AI10: 30 | AJ10: 30 | AK10: 30 | AL10: 30 | AM10: 30 | AN10: 30 | AO10: 30 | AP10: 30 | AQ10: 30 | AR10: 30 | AS10: 30 | AT10: 30 | AU10: 30 | AV10: 30 | AW10: 30 | AX10: 30 | AY10: 30 | AZ10: 30 | BA10: 30 | BB10: 30 | BC10: 30 | BD10: 30 | BE10: 30 | BF10: 30 | BG10: 30 | BH10: 30 | BI10: 30 | BJ10: 30 | BK10: 30 | BL10: 30 | BM10: 30 | BN10: 30 | BO10: 30 | BP10: 30 | BQ10: 30 | BR10: 30 | BS10: 30 | BT10: 30 | BU10: 30 | BV10: 30.00
A11: Casos | B11: 0 | C11: 0 | D11: 0 | E11: 0 | F11: 0 | G11: 0 | H11: 0 | I11: 0 | J11: 0 | K11: 0 | L11: 0 | M11: 96 | N11: 96 | O11: 96 | P11: 97 | Q11: 97 | R11: 97 | S11: 97 | T11: 97 | U11: 98 | V11: 98 | W11: 98 | X11: 98 | Y11: 98 | Z11: 98 | AA11: 99 | AB11: 99 | AC11: 99 | AD11: 99 | AE11: 99 | AF11: 100 | AG11: 100 | AH11: 100 | AI11: 100 | AJ11: 100 | AK11: 101 | AL11: 101 | AM11: 101 | AN11: 101 | AO11: 101 | AP11: 102 | AQ11: 102 | AR11: 102 | AS11: 102 | AT11: 102 | AU11: 103 | AV11: 103 | AW11: 103 | AX11: 103 | AY11: 103 | AZ11: 104 | BA11: 104 | BB11: 104 | BC11: 104 | BD11: 104 | BE11: 105 | BF11: 105 | BG11: 105 | BH11: 105 | BI11: 105 | BJ11: 106 | BK11: 106 | BL11: 106 | BM11: 106 | BN11: 106 | BO11: 107 | BP11: 107 | BQ11: 107 | BR11: 107 | BS11: 107 | BT11: 108 | BU11: 108 | BV11: 6212
A12: Revenue Total ($) | B12: 0 | C12: 0 | D12: 0 | E12: 0 | F12: 0 | G12: 0 | H12: 0 | I12: 0 | J12: 0 | K12: 0 | L12: 0 | M12: 7680 | N12: 7695 | O12: 7710 | P12: 7725 | Q12: 7740 | R12: 7755 | S12: 7770 | T12: 7786 | U12: 7801 | V12: 7816 | W12: 7831 | X12: 7847 | Y12: 7862 | Z12: 7877 | AA12: 7893 | AB12: 7908 | AC12: 7923 | AD12: 7939 | AE12: 7954 | AF12: 7970 | AG12: 7985 | AH12: 8001 | AI12: 8017 | AJ12: 8032 | AK12: 8048 | AL12: 8064 | AM12: 8079 | AN12: 8095 | AO12: 8111 | AP12: 8127 | AQ12: 8143 | AR12: 8159 | AS12: 8175 | AT12: 8190 | AU12: 8206 | AV12: 8222 | AW12: 8239 | AX12: 8255 | AY12: 8271 | AZ12: 8287 | BA12: 8303 | BB12: 8319 | BC12: 8336 | BD12: 8352 | BE12: 8368 | BF12: 8384 | BG12: 8401 | BH12: 8417 | BI12: 8434 | BJ12: 8450 | BK12: 8467 | BL12: 8483 | BM12: 8500 | BN12: 8516 | BO12: 8533 | BP12: 8550 | BQ12: 8566 | BR12: 8583 | BS12: 8600 | BT12: 8616 | BU12: 8633 | BV12: 496998
A13: Fee Variable Weso ($) | B13: 0 | C13: 0 | D13: 0 | E13: 0 | F13: 0 | G13: 0 | H13: 0 | I13: 0 | J13: 0 | K13: 0 | L13: 0 | M13: 2304 | N13: 2308 | O13: 2313 | P13: 2318 | Q13: 2322 | R13: 2327 | S13: 2331 | T13: 2336 | U13: 2340 | V13: 2345 | W13: 2349 | X13: 2354 | Y13: 2359 | Z13: 2363 | AA13: 2368 | AB13: 2372 | AC13: 2377 | AD13: 2382 | AE13: 2386 | AF13: 2391 | AG13: 2396 | AH13: 2400 | AI13: 2405 | AJ13: 2410 | AK13: 2414 | AL13: 2419 | AM13: 2424 | AN13: 2429 | AO13: 2433 | AP13: 2438 | AQ13: 2443 | AR13: 2448 | AS13: 2452 | AT13: 2457 | AU13: 2462 | AV13: 2467 | AW13: 2472 | AX13: 2476 | AY13: 2481 | AZ13: 2486 | BA13: 2491 | BB13: 2496 | BC13: 2501 | BD13: 2506 | BE13: 2510 | BF13: 2515 | BG13: 2520 | BH13: 2525 | BI13: 2530 | BJ13: 2535 | BK13: 2540 | BL13: 2545 | BM13: 2550 | BN13: 2555 | BO13: 2560 | BP13: 2565 | BQ13: 2570 | BR13: 2575 | BS13: 2580 | BT13: 2585 | BU13: 2590 | BV13: 149099
A14: Licencia Weso ($) | B14: 0 | C14: 0 | D14: 0 | E14: 0 | F14: 0 | G14: 0 | H14: 0 | I14: 0 | J14: 0 | K14: 0 | L14: 0 | M14: 0 | N14: 0 | O14: 0 | P14: 0 | Q14: 0 | R14: 0 | S14: 0 | T14: 0 | U14: 0 | V14: 0 | W14: 0 | X14: 0 | Y14: 0 | Z14: 0 | AA14: 0 | AB14: 0 | AC14: 0 | AD14: 0 | AE14: 0 | AF14: 0 | AG14: 0 | AH14: 0 | AI14: 0 | AJ14: 0 | AK14: 0 | AL14: 0 | AM14: 0 | AN14: 0 | AO14: 0 | AP14: 0 | AQ14: 0 | AR14: 0 | AS14: 0 | AT14: 0 | AU14: 0 | AV14: 0 | AW14: 0 | AX14: 0 | AY14: 0 | AZ14: 0 | BA14: 0 | BB14: 0 | BC14: 0 | BD14: 0 | BE14: 0 | BF14: 0 | BG14: 0 | BH14: 0 | BI14: 0 | BJ14: 0 | BK14: 0 | BL14: 0 | BM14: 0 | BN14: 0 | BO14: 0 | BP14: 0 | BQ14: 0 | BR14: 0 | BS14: 0 | BT14: 0 | BU14: 0 | BV14: 0
A15: Revenue Weso ($) | B15: 0 | C15: 0 | D15: 0 | E15: 0 | F15: 0 | G15: 0 | H15: 0 | I15: 0 | J15: 0 | K15: 0 | L15: 0 | M15: 2304 | N15: 2308 | O15: 2313 | P15: 2318 | Q15: 2322 | R15: 2327 | S15: 2331 | T15: 2336 | U15: 2340 | V15: 2345 | W15: 2349 | X15: 2354 | Y15: 2359 | Z15: 2363 | AA15: 2368 | AB15: 2372 | AC15: 2377 | AD15: 2382 | AE15: 2386 | AF15: 2391 | AG15: 2396 | AH15: 2400 | AI15: 2405 | AJ15: 2410 | AK15: 2414 | AL15: 2419 | AM15: 2424 | AN15: 2429 | AO15: 2433 | AP15: 2438 | AQ15: 2443 | AR15: 2448 | AS15: 2452 | AT15: 2457 | AU15: 2462 | AV15: 2467 | AW15: 2472 | AX15: 2476 | AY15: 2481 | AZ15: 2486 | BA15: 2491 | BB15: 2496 | BC15: 2501 | BD15: 2506 | BE15: 2510 | BF15: 2515 | BG15: 2520 | BH15: 2525 | BI15: 2530 | BJ15: 2535 | BK15: 2540 | BL15: 2545 | BM15: 2550 | BN15: 2555 | BO15: 2560 | BP15: 2565 | BQ15: 2570 | BR15: 2575 | BS15: 2580 | BT15: 2585 | BU15: 2590 | BV15: 149099
A16: Costos Proveedor ($) | B16: 0 | C16: 0 | D16: 0 | E16: 0 | F16: 0 | G16: 0 | H16: 0 | I16: 0 | J16: 0 | K16: 0 | L16: 0 | M16: 5376 | N16: 5386 | O16: 5397 | P16: 5408 | Q16: 5418 | R16: 5429 | S16: 5439 | T16: 5450 | U16: 5461 | V16: 5471 | W16: 5482 | X16: 5493 | Y16: 5503 | Z16: 5514 | AA16: 5525 | AB16: 5536 | AC16: 5546 | AD16: 5557 | AE16: 5568 | AF16: 5579 | AG16: 5590 | AH16: 5601 | AI16: 5612 | AJ16: 5623 | AK16: 5634 | AL16: 5645 | AM16: 5656 | AN16: 5667 | AO16: 5678 | AP16: 5689 | AQ16: 5700 | AR16: 5711 | AS16: 5722 | AT16: 5733 | AU16: 5745 | AV16: 5756 | AW16: 5767 | AX16: 5778 | AY16: 5790 | AZ16: 5801 | BA16: 5812 | BB16: 5823 | BC16: 5835 | BD16: 5846 | BE16: 5858 | BF16: 5869 | BG16: 5881 | BH16: 5892 | BI16: 5904 | BJ16: 5915 | BK16: 5927 | BL16: 5938 | BM16: 5950 | BN16: 5961 | BO16: 5973 | BP16: 5985 | BQ16: 5996 | BR16: 6008 | BS16: 6020 | BT16: 6032 | BU16: 6043 | BV16: 347898

Sheet 8_Kanguro Insurance
A1: Actor: Kanguro Insurance
A2: Categoría: Veterinario · Servicio: · País: Estados Unidos
A3: Crecimiento: 2.5% · Churn: 1.2%
A5: Métrica | B5: M1 | C5: M2 | D5: M3 | E5: M4 | F5: M5 | G5: M6 | H5: M7 | I5: M8 | J5: M9 | K5: M10 | L5: M11 | M5: M12 | N5: M13 | O5: M14 | P5: M15 | Q5: M16 | R5: M17 | S5: M18 | T5: M19 | U5: M20 | V5: M21 | W5: M22 | X5: M23 | Y5: M24 | Z5: M25 | AA5: M26 | AB5: M27 | AC5: M28 | AD5: M29 | AE5: M30 | AF5: M31 | AG5: M32 | AH5: M33 | AI5: M34 | AJ5: M35 | AK5: M36 | AL5: M37 | AM5: M38 | AN5: M39 | AO5: M40 | AP5: M41 | AQ5: M42 | AR5: M43 | AS5: M44 | AT5: M45 | AU5: M46 | AV5: M47 | AW5: M48 | AX5: M49 | AY5: M50 | AZ5: M51 | BA5: M52 | BB5: M53 | BC5: M54 | BD5: M55 | BE5: M56 | BF5: M57 | BG5: M58 | BH5: M59 | BI5: M60 | BJ5: M61 | BK5: M62 | BL5: M63 | BM5: M64 | BN5: M65 | BO5: M66 | BP5: M67 | BQ5: M68 | BR5: M69 | BS5: M70 | BT5: M71 | BU5: M72 | BV5: TOTAL
A6: Clientes | B6: 0 | C6: 0 | D6: 0 | E6: 0 | F6: 0 | G6: 0 | H6: 0 | I6: 10000 | J6: 10127 | K6: 10256 | L6: 10386 | M6: 10518 | N6: 10651 | O6: 10787 | P6: 10924 | Q6: 11062 | R6: 11203 | S6: 11345 | T6: 11489 | U6: 11635 | V6: 11783 | W6: 11932 | X6: 12084 | Y6: 12238 | Z6: 12393 | AA6: 12550 | AB6: 12710 | AC6: 12871 | AD6: 13035 | AE6: 13200 | AF6: 13368 | AG6: 13538 | AH6: 13709 | AI6: 13884 | AJ6: 14060 | AK6: 14238 | AL6: 14419 | AM6: 14602 | AN6: 14788 | AO6: 14976 | AP6: 15166 | AQ6: 15358 | AR6: 15554 | AS6: 15751 | AT6: 15951 | AU6: 16154 | AV6: 16359 | AW6: 16567 | AX6: 16777 | AY6: 16990 | AZ6: 17206 | BA6: 17424 | BB6: 17646 | BC6: 17870 | BD6: 18097 | BE6: 18326 | BF6: 18559 | BG6: 18795 | BH6: 19034 | BI6: 19275 | BJ6: 19520 | BK6: 19768 | BL6: 20019 | BM6: 20273 | BN6: 20531 | BO6: 20792 | BP6: 21056 | BQ6: 21323 | BR6: 21594 | BS6: 21868 | BT6: 22146 | BU6: 22427
A7: Clientes Perdidos (Churn) | B7: 0 | C7: 0 | D7: 0 | E7: 0 | F7: 0 | G7: 0 | H7: 0 | I7: 0 | J7: 120 | K7: 122 | L7: 123 | M7: 125 | N7: 126 | O7: 128 | P7: 129 | Q7: 131 | R7: 133 | S7: 134 | T7: 136 | U7: 138 | V7: 140 | W7: 141 | X7: 143 | Y7: 145 | Z7: 147 | AA7: 149 | AB7: 151 | AC7: 153 | AD7: 154 | AE7: 156 | AF7: 158 | AG7: 160 | AH7: 162 | AI7: 165 | AJ7: 167 | AK7: 169 | AL7: 171 | AM7: 173 | AN7: 175 | AO7: 177 | AP7: 180 | AQ7: 182 | AR7: 184 | AS7: 187 | AT7: 189 | AU7: 191 | AV7: 194 | AW7: 196 | AX7: 199 | AY7: 201 | AZ7: 204 | BA7: 206 | BB7: 209 | BC7: 212 | BD7: 214 | BE7: 217 | BF7: 220 | BG7: 223 | BH7: 226 | BI7: 228 | BJ7: 231 | BK7: 234 | BL7: 237 | BM7: 240 | BN7: 243 | BO7: 246 | BP7: 249 | BQ7: 253 | BR7: 256 | BS7: 259 | BT7: 262 | BU7: 266 | BV7: 11742
A8: Tasa Uso % | B8: 2 | C8: 2 | D8: 2 | E8: 2 | F8: 2 | G8: 2 | H8: 2 | I8: 2 | J8: 2 | K8: 2 | L8: 2 | M8: 2 | N8: 2 | O8: 2 | P8: 2 | Q8: 2 | R8: 2 | S8: 2 | T8: 2 | U8: 2 | V8: 2 | W8: 2 | X8: 2 | Y8: 2 | Z8: 2 | AA8: 2 | AB8: 2 | AC8: 2 | AD8: 2 | AE8: 2 | AF8: 2 | AG8: 2 | AH8: 2 | AI8: 2 | AJ8: 2 | AK8: 2 | AL8: 2 | AM8: 2 | AN8: 2 | AO8: 2 | AP8: 2 | AQ8: 2 | AR8: 2 | AS8: 2 | AT8: 2 | AU8: 2 | AV8: 2 | AW8: 2 | AX8: 2 | AY8: 2 | AZ8: 2 | BA8: 2 | BB8: 2 | BC8: 2 | BD8: 2 | BE8: 2 | BF8: 2 | BG8: 2 | BH8: 2 | BI8: 2 | BJ8: 2 | BK8: 2 | BL8: 2 | BM8: 2 | BN8: 2 | BO8: 2 | BP8: 2 | BQ8: 2 | BR8: 2 | BS8: 2 | BT8: 2 | BU8: 2
A9: Ticket ($) | B9: 110 | C9: 110 | D9: 110 | E9: 110 | F9: 110 | G9: 110 | H9: 110 | I9: 110 | J9: 110 | K9: 110 | L9: 110 | M9: 110 | N9: 110 | O9: 110 | P9: 110 | Q9: 110 | R9: 110 | S9: 110 | T9: 110 | U9: 110 | V9: 110 | W9: 110 | X9: 110 | Y9: 110 | Z9: 110 | AA9: 110 | AB9: 110 | AC9: 110 | AD9: 110 | AE9: 110 | AF9: 110 | AG9: 110 | AH9: 110 | AI9: 110 | AJ9: 110 | AK9: 110 | AL9: 110 | AM9: 110 | AN9: 110 | AO9: 110 | AP9: 110 | AQ9: 110 | AR9: 110 | AS9: 110 | AT9: 110 | AU9: 110 | AV9: 110 | AW9: 110 | AX9: 110 | AY9: 110 | AZ9: 110 | BA9: 110 | BB9: 110 | BC9: 110 | BD9: 110 | BE9: 110 | BF9: 110 | BG9: 110 | BH9: 110 | BI9: 110 | BJ9: 110 | BK9: 110 | BL9: 110 | BM9: 110 | BN9: 110 | BO9: 110 | BP9: 110 | BQ9: 110 | BR9: 110 | BS9: 110 | BT9: 110 | BU9: 110 | BV9: 110.00
A10: Fee Weso % | B10: 20 | C10: 20 | D10: 20 | E10: 20 | F10: 20 | G10: 20 | H10: 20 | I10: 20 | J10: 20 | K10: 20 | L10: 20 | M10: 20 | N10: 20 | O10: 20 | P10: 20 | Q10: 20 | R10: 20 | S10: 20 | T10: 20 | U10: 20 | V10: 20 | W10: 20 | X10: 20 | Y10: 20 | Z10: 20 | AA10: 20 | AB10: 20 | AC10: 20 | AD10: 20 | AE10: 20 | AF10: 20 | AG10: 20 | AH10: 20 | AI10: 20 | AJ10: 20 | AK10: 20 | AL10: 20 | AM10: 20 | AN10: 20 | AO10: 20 | AP10: 20 | AQ10: 20 | AR10: 20 | AS10: 20 | AT10: 20 | AU10: 20 | AV10: 20 | AW10: 20 | AX10: 20 | AY10: 20 | AZ10: 20 | BA10: 20 | BB10: 20 | BC10: 20 | BD10: 20 | BE10: 20 | BF10: 20 | BG10: 20 | BH10: 20 | BI10: 20 | BJ10: 20 | BK10: 20 | BL10: 20 | BM10: 20 | BN10: 20 | BO10: 20 | BP10: 20 | BQ10: 20 | BR10: 20 | BS10: 20 | BT10: 20 | BU10: 20 | BV10: 20.00
A11: Casos | B11: 0 | C11: 0 | D11: 0 | E11: 0 | F11: 0 | G11: 0 | H11: 0 | I11: 200 | J11: 203 | K11: 205 | L11: 208 | M11: 210 | N11: 213 | O11: 216 | P11: 218 | Q11: 221 | R11: 224 | S11: 227 | T11: 230 | U11: 233 | V11: 236 | W11: 239 | X11: 242 | Y11: 245 | Z11: 248 | AA11: 251 | AB11: 254 | AC11: 257 | AD11: 261 | AE11: 264 | AF11: 267 | AG11: 271 | AH11: 274 | AI11: 278 | AJ11: 281 | AK11: 285 | AL11: 288 | AM11: 292 | AN11: 296 | AO11: 300 | AP11: 303 | AQ11: 307 | AR11: 311 | AS11: 315 | AT11: 319 | AU11: 323 | AV11: 327 | AW11: 331 | AX11: 336 | AY11: 340 | AZ11: 344 | BA11: 348 | BB11: 353 | BC11: 357 | BD11: 362 | BE11: 367 | BF11: 371 | BG11: 376 | BH11: 381 | BI11: 386 | BJ11: 390 | BK11: 395 | BL11: 400 | BM11: 405 | BN11: 411 | BO11: 416 | BP11: 421 | BQ11: 426 | BR11: 432 | BS11: 437 | BT11: 443 | BU11: 449 | BV11: 20019
A12: Revenue Total ($) | B12: 0 | C12: 0 | D12: 0 | E12: 0 | F12: 0 | G12: 0 | H12: 0 | I12: 22000 | J12: 22279 | K12: 22562 | L12: 22849 | M12: 23139 | N12: 23433 | O12: 23731 | P12: 24032 | Q12: 24337 | R12: 24646 | S12: 24959 | T12: 25276 | U12: 25597 | V12: 25922 | W12: 26251 | X12: 26585 | Y12: 26923 | Z12: 27264 | AA12: 27611 | AB12: 27961 | AC12: 28316 | AD12: 28676 | AE12: 29040 | AF12: 29409 | AG12: 29783 | AH12: 30161 | AI12: 30544 | AJ12: 30932 | AK12: 31325 | AL12: 31722 | AM12: 32125 | AN12: 32533 | AO12: 32946 | AP12: 33365 | AQ12: 33789 | AR12: 34218 | AS12: 34652 | AT12: 35092 | AU12: 35538 | AV12: 35989 | AW12: 36446 | AX12: 36909 | AY12: 37378 | AZ12: 37853 | BA12: 38333 | BB12: 38820 | BC12: 39313 | BD12: 39813 | BE12: 40318 | BF12: 40830 | BG12: 41349 | BH12: 41874 | BI12: 42406 | BJ12: 42944 | BK12: 43490 | BL12: 44042 | BM12: 44601 | BN12: 45168 | BO12: 45741 | BP12: 46322 | BQ12: 46911 | BR12: 47506 | BS12: 48110 | BT12: 48721 | BU12: 49339 | BV12: 2202054
A13: Fee Variable Weso ($) | B13: 0 | C13: 0 | D13: 0 | E13: 0 | F13: 0 | G13: 0 | H13: 0 | I13: 4400 | J13: 4456 | K13: 4512 | L13: 4570 | M13: 4628 | N13: 4687 | O13: 4746 | P13: 4806 | Q13: 4867 | R13: 4929 | S13: 4992 | T13: 5055 | U13: 5119 | V13: 5184 | W13: 5250 | X13: 5317 | Y13: 5385 | Z13: 5453 | AA13: 5522 | AB13: 5592 | AC13: 5663 | AD13: 5735 | AE13: 5808 | AF13: 5882 | AG13: 5957 | AH13: 6032 | AI13: 6109 | AJ13: 6186 | AK13: 6265 | AL13: 6344 | AM13: 6425 | AN13: 6507 | AO13: 6589 | AP13: 6673 | AQ13: 6758 | AR13: 6844 | AS13: 6930 | AT13: 7018 | AU13: 7108 | AV13: 7198 | AW13: 7289 | AX13: 7382 | AY13: 7476 | AZ13: 7571 | BA13: 7667 | BB13: 7764 | BC13: 7863 | BD13: 7963 | BE13: 8064 | BF13: 8166 | BG13: 8270 | BH13: 8375 | BI13: 8481 | BJ13: 8589 | BK13: 8698 | BL13: 8808 | BM13: 8920 | BN13: 9034 | BO13: 9148 | BP13: 9264 | BQ13: 9382 | BR13: 9501 | BS13: 9622 | BT13: 9744 | BU13: 9868 | BV13: 440411
A14: Licencia Weso ($) | B14: 0 | C14: 0 | D14: 0 | E14: 0 | F14: 0 | G14: 0 | H14: 0 | I14: 2000 | J14: 2000 | K14: 2000 | L14: 2000 | M14: 2000 | N14: 2000 | O14: 2000 | P14: 2000 | Q14: 2000 | R14: 2000 | S14: 2000 | T14: 2000 | U14: 2000 | V14: 2000 | W14: 2000 | X14: 2000 | Y14: 2000 | Z14: 2000 | AA14: 2000 | AB14: 2000 | AC14: 2000 | AD14: 2000 | AE14: 2000 | AF14: 2000 | AG14: 2000 | AH14: 2000 | AI14: 2000 | AJ14: 2000 | AK14: 2000 | AL14: 2000 | AM14: 2000 | AN14: 2000 | AO14: 2000 | AP14: 2000 | AQ14: 2000 | AR14: 2000 | AS14: 2000 | AT14: 2000 | AU14: 2000 | AV14: 2000 | AW14: 2000 | AX14: 2000 | AY14: 2000 | AZ14: 2000 | BA14: 2000 | BB14: 2000 | BC14: 2000 | BD14: 2000 | BE14: 2000 | BF14: 2000 | BG14: 2000 | BH14: 2000 | BI14: 2000 | BJ14: 2000 | BK14: 2000 | BL14: 2000 | BM14: 2000 | BN14: 2000 | BO14: 2000 | BP14: 2000 | BQ14: 2000 | BR14: 2000 | BS14: 2000 | BT14: 2000 | BU14: 2000 | BV14: 130000
A15: Revenue Weso ($) | B15: 0 | C15: 0 | D15: 0 | E15: 0 | F15: 0 | G15: 0 | H15: 0 | I15: 6400 | J15: 6456 | K15: 6512 | L15: 6570 | M15: 6628 | N15: 6687 | O15: 6746 | P15: 6806 | Q15: 6867 | R15: 6929 | S15: 6992 | T15: 7055 | U15: 7119 | V15: 7184 | W15: 7250 | X15: 7317 | Y15: 7385 | Z15: 7453 | AA15: 7522 | AB15: 7592 | AC15: 7663 | AD15: 7735 | AE15: 7808 | AF15: 7882 | AG15: 7957 | AH15: 8032 | AI15: 8109 | AJ15: 8186 | AK15: 8265 | AL15: 8344 | AM15: 8425 | AN15: 8507 | AO15: 8589 | AP15: 8673 | AQ15: 8758 | AR15: 8844 | AS15: 8930 | AT15: 9018 | AU15: 9108 | AV15: 9198 | AW15: 9289 | AX15: 9382 | AY15: 9476 | AZ15: 9571 | BA15: 9667 | BB15: 9764 | BC15: 9863 | BD15: 9963 | BE15: 10064 | BF15: 10166 | BG15: 10270 | BH15: 10375 | BI15: 10481 | BJ15: 10589 | BK15: 10698 | BL15: 10808 | BM15: 10920 | BN15: 11034 | BO15: 11148 | BP15: 11264 | BQ15: 11382 | BR15: 11501 | BS15: 11622 | BT15: 11744 | BU15: 11868 | BV15: 570411
A16: Costos Proveedor ($) | B16: 0 | C16: 0 | D16: 0 | E16: 0 | F16: 0 | G16: 0 | H16: 0 | I16: 17600 | J16: 17824 | K16: 18050 | L16: 18279 | M16: 18511 | N16: 18746 | O16: 18984 | P16: 19226 | Q16: 19470 | R16: 19717 | S16: 19967 | T16: 20221 | U16: 20478 | V16: 20738 | W16: 21001 | X16: 21268 | Y16: 21538 | Z16: 21812 | AA16: 22089 | AB16: 22369 | AC16: 22653 | AD16: 22941 | AE16: 23232 | AF16: 23527 | AG16: 23826 | AH16: 24129 | AI16: 24435 | AJ16: 24745 | AK16: 25060 | AL16: 25378 | AM16: 25700 | AN16: 26027 | AO16: 26357 | AP16: 26692 | AQ16: 27031 | AR16: 27374 | AS16: 27722 | AT16: 28074 | AU16: 28430 | AV16: 28791 | AW16: 29157 | AX16: 29527 | AY16: 29902 | AZ16: 30282 | BA16: 30667 | BB16: 31056 | BC16: 31451 | BD16: 31850 | BE16: 32255 | BF16: 32664 | BG16: 33079 | BH16: 33499 | BI16: 33925 | BJ16: 34355 | BK16: 34792 | BL16: 35234 | BM16: 35681 | BN16: 36134 | BO16: 36593 | BP16: 37058 | BQ16: 37529 | BR16: 38005 | BS16: 38488 | BT16: 38977 | BU16: 39472 | BV16: 1761643

Sheet 9_Kanguro Insurance - Hogar
A1: Actor: Kanguro Insurance - Hogar
A2: Categoría: Hogar y Propiedades · Servicio: · País: Estados Unidos
A3: Crecimiento: 2.5% · Churn: 1.2%
A5: Métrica | B5: M1 | C5: M2 | D5: M3 | E5: M4 | F5: M5 | G5: M6 | H5: M7 | I5: M8 | J5: M9 | K5: M10 | L5: M11 | M5: M12 | N5: M13 | O5: M14 | P5: M15 | Q5: M16 | R5: M17 | S5: M18 | T5: M19 | U5: M20 | V5: M21 | W5: M22 | X5: M23 | Y5: M24 | Z5: M25 | AA5: M26 | AB5: M27 | AC5: M28 | AD5: M29 | AE5: M30 | AF5: M31 | AG5: M32 | AH5: M33 | AI5: M34 | AJ5: M35 | AK5: M36 | AL5: M37 | AM5: M38 | AN5: M39 | AO5: M40 | AP5: M41 | AQ5: M42 | AR5: M43 | AS5: M44 | AT5: M45 | AU5: M46 | AV5: M47 | AW5: M48 | AX5: M49 | AY5: M50 | AZ5: M51 | BA5: M52 | BB5: M53 | BC5: M54 | BD5: M55 | BE5: M56 | BF5: M57 | BG5: M58 | BH5: M59 | BI5: M60 | BJ5: M61 | BK5: M62 | BL5: M63 | BM5: M64 | BN5: M65 | BO5: M66 | BP5: M67 | BQ5: M68 | BR5: M69 | BS5: M70 | BT5: M71 | BU5: M72 | BV5: TOTAL
A6: Clientes | B6: 0 | C6: 0 | D6: 0 | E6: 0 | F6: 0 | G6: 0 | H6: 0 | I6: 0 | J6: 0 | K6: 5000 | L6: 5064 | M6: 5128 | N6: 5193 | O6: 5259 | P6: 5326 | Q6: 5393 | R6: 5462 | S6: 5531 | T6: 5601 | U6: 5673 | V6: 5745 | W6: 5818 | X6: 5891 | Y6: 5966 | Z6: 6042 | AA6: 6119 | AB6: 6196 | AC6: 6275 | AD6: 6355 | AE6: 6436 | AF6: 6517 | AG6: 6600 | AH6: 6684 | AI6: 6769 | AJ6: 6855 | AK6: 6942 | AL6: 7030 | AM6: 7119 | AN6: 7210 | AO6: 7301 | AP6: 7394 | AQ6: 7488 | AR6: 7583 | AS6: 7679 | AT6: 7777 | AU6: 7876 | AV6: 7976 | AW6: 8077 | AX6: 8179 | AY6: 8283 | AZ6: 8388 | BA6: 8495 | BB6: 8603 | BC6: 8712 | BD6: 8823 | BE6: 8935 | BF6: 9048 | BG6: 9163 | BH6: 9280 | BI6: 9397 | BJ6: 9517 | BK6: 9638 | BL6: 9760 | BM6: 9884 | BN6: 10010 | BO6: 10137 | BP6: 10265 | BQ6: 10396 | BR6: 10528 | BS6: 10662 | BT6: 10797 | BU6: 10934
A7: Clientes Perdidos (Churn) | B7: 0 | C7: 0 | D7: 0 | E7: 0 | F7: 0 | G7: 0 | H7: 0 | I7: 0 | J7: 0 | K7: 0 | L7: 60 | M7: 61 | N7: 62 | O7: 62 | P7: 63 | Q7: 64 | R7: 65 | S7: 66 | T7: 66 | U7: 67 | V7: 68 | W7: 69 | X7: 70 | Y7: 71 | Z7: 72 | AA7: 73 | AB7: 73 | AC7: 74 | AD7: 75 | AE7: 76 | AF7: 77 | AG7: 78 | AH7: 79 | AI7: 80 | AJ7: 81 | AK7: 82 | AL7: 83 | AM7: 84 | AN7: 85 | AO7: 87 | AP7: 88 | AQ7: 89 | AR7: 90 | AS7: 91 | AT7: 92 | AU7: 93 | AV7: 95 | AW7: 96 | AX7: 97 | AY7: 98 | AZ7: 99 | BA7: 101 | BB7: 102 | BC7: 103 | BD7: 105 | BE7: 106 | BF7: 107 | BG7: 109 | BH7: 110 | BI7: 111 | BJ7: 113 | BK7: 114 | BL7: 116 | BM7: 117 | BN7: 119 | BO7: 120 | BP7: 122 | BQ7: 123 | BR7: 125 | BS7: 126 | BT7: 128 | BU7: 130 | BV7: 5607
A8: Tasa Uso % | B8: 1.4 | C8: 1.4 | D8: 1.4 | E8: 1.4 | F8: 1.4 | G8: 1.4 | H8: 1.4 | I8: 1.4 | J8: 1.4 | K8: 1.4 | L8: 1.4 | M8: 1.4 | N8: 1.4 | O8: 1.4 | P8: 1.4 | Q8: 1.4 | R8: 1.4 | S8: 1.4 | T8: 1.4 | U8: 1.4 | V8: 1.4 | W8: 1.4 | X8: 1.4 | Y8: 1.4 | Z8: 1.4 | AA8: 1.4 | AB8: 1.4 | AC8: 1.4 | AD8: 1.4 | AE8: 1.4 | AF8: 1.4 | AG8: 1.4 | AH8: 1.4 | AI8: 1.4 | AJ8: 1.4 | AK8: 1.4 | AL8: 1.4 | AM8: 1.4 | AN8: 1.4 | AO8: 1.4 | AP8: 1.4 | AQ8: 1.4 | AR8: 1.4 | AS8: 1.4 | AT8: 1.4 | AU8: 1.4 | AV8: 1.4 | AW8: 1.4 | AX8: 1.4 | AY8: 1.4 | AZ8: 1.4 | BA8: 1.4 | BB8: 1.4 | BC8: 1.4 | BD8: 1.4 | BE8: 1.4 | BF8: 1.4 | BG8: 1.4 | BH8: 1.4 | BI8: 1.4 | BJ8: 1.4 | BK8: 1.4 | BL8: 1.4 | BM8: 1.4 | BN8: 1.4 | BO8: 1.4 | BP8: 1.4 | BQ8: 1.4 | BR8: 1.4 | BS8: 1.4 | BT8: 1.4 | BU8: 1.4
A9: Ticket ($) | B9: 150 | C9: 150 | D9: 150 | E9: 150 | F9: 150 | G9: 150 | H9: 150 | I9: 150 | J9: 150 | K9: 150 | L9: 150 | M9: 150 | N9: 150 | O9: 150 | P9: 150 | Q9: 150 | R9: 150 | S9: 150 | T9: 150 | U9: 150 | V9: 150 | W9: 150 | X9: 150 | Y9: 150 | Z9: 150 | AA9: 150 | AB9: 150 | AC9: 150 | AD9: 150 | AE9: 150 | AF9: 150 | AG9: 150 | AH9: 150 | AI9: 150 | AJ9: 150 | AK9: 150 | AL9: 150 | AM9: 150 | AN9: 150 | AO9: 150 | AP9: 150 | AQ9: 150 | AR9: 150 | AS9: 150 | AT9: 150 | AU9: 150 | AV9: 150 | AW9: 150 | AX9: 150 | AY9: 150 | AZ9: 150 | BA9: 150 | BB9: 150 | BC9: 150 | BD9: 150 | BE9: 150 | BF9: 150 | BG9: 150 | BH9: 150 | BI9: 150 | BJ9: 150 | BK9: 150 | BL9: 150 | BM9: 150 | BN9: 150 | BO9: 150 | BP9: 150 | BQ9: 150 | BR9: 150 | BS9: 150 | BT9: 150 | BU9: 150 | BV9: 150.00
A10: Fee Weso % | B10: 30 | C10: 30 | D10: 30 | E10: 30 | F10: 30 | G10: 30 | H10: 30 | I10: 30 | J10: 30 | K10: 30 | L10: 30 | M10: 30 | N10: 30 | O10: 30 | P10: 30 | Q10: 30 | R10: 30 | S10: 30 | T10: 30 | U10: 30 | V10: 30 | W10: 30 | X10: 30 | Y10: 30 | Z10: 30 | AA10: 30 | AB10: 30 | AC10: 30 | AD10: 30 | AE10: 30 | AF10: 30 | AG10: 30 | AH10: 30 | AI10: 30 | AJ10: 30 | AK10: 30 | AL10: 30 | AM10: 30 | AN10: 30 | AO10: 30 | AP10: 30 | AQ10: 30 | AR10: 30 | AS10: 30 | AT10: 30 | AU10: 30 | AV10: 30 | AW10: 30 | AX10: 30 | AY10: 30 | AZ10: 30 | BA10: 30 | BB10: 30 | BC10: 30 | BD10: 30 | BE10: 30 | BF10: 30 | BG10: 30 | BH10: 30 | BI10: 30 | BJ10: 30 | BK10: 30 | BL10: 30 | BM10: 30 | BN10: 30 | BO10: 30 | BP10: 30 | BQ10: 30 | BR10: 30 | BS10: 30 | BT10: 30 | BU10: 30 | BV10: 30.00
A11: Casos | B11: 0 | C11: 0 | D11: 0 | E11: 0 | F11: 0 | G11: 0 | H11: 0 | I11: 0 | J11: 0 | K11: 70 | L11: 71 | M11: 72 | N11: 73 | O11: 74 | P11: 75 | Q11: 76 | R11: 76 | S11: 77 | T11: 78 | U11: 79 | V11: 80 | W11: 81 | X11: 82 | Y11: 84 | Z11: 85 | AA11: 86 | AB11: 87 | AC11: 88 | AD11: 89 | AE11: 90 | AF11: 91 | AG11: 92 | AH11: 94 | AI11: 95 | AJ11: 96 | AK11: 97 | AL11: 98 | AM11: 100 | AN11: 101 | AO11: 102 | AP11: 104 | AQ11: 105 | AR11: 106 | AS11: 108 | AT11: 109 | AU11: 110 | AV11: 112 | AW11: 113 | AX11: 115 | AY11: 116 | AZ11: 117 | BA11: 119 | BB11: 120 | BC11: 122 | BD11: 124 | BE11: 125 | BF11: 127 | BG11: 128 | BH11: 130 | BI11: 132 | BJ11: 133 | BK11: 135 | BL11: 137 | BM11: 138 | BN11: 140 | BO11: 142 | BP11: 144 | BQ11: 146 | BR11: 147 | BS11: 149 | BT11: 151 | BU11: 153 | BV11: 6695
A12: Revenue Total ($) | B12: 0 | C12: 0 | D12: 0 | E12: 0 | F12: 0 | G12: 0 | H12: 0 | I12: 0 | J12: 0 | K12: 10500 | L12: 10633 | M12: 10768 | N12: 10905 | O12: 11044 | P12: 11184 | Q12: 11326 | R12: 11470 | S12: 11615 | T12: 11763 | U12: 11912 | V12: 12064 | W12: 12217 | X12: 12372 | Y12: 12529 | Z12: 12688 | AA12: 12849 | AB12: 13013 | AC12: 13178 | AD12: 13345 | AE12: 13515 | AF12: 13686 | AG12: 13860 | AH12: 14036 | AI12: 14214 | AJ12: 14395 | AK12: 14578 | AL12: 14763 | AM12: 14950 | AN12: 15140 | AO12: 15333 | AP12: 15527 | AQ12: 15724 | AR12: 15924 | AS12: 16126 | AT12: 16331 | AU12: 16539 | AV12: 16749 | AW12: 16961 | AX12: 17177 | AY12: 17395 | AZ12: 17616 | BA12: 17840 | BB12: 18066 | BC12: 18296 | BD12: 18528 | BE12: 18763 | BF12: 19001 | BG12: 19243 | BH12: 19487 | BI12: 19735 | BJ12: 19985 | BK12: 20239 | BL12: 20496 | BM12: 20756 | BN12: 21020 | BO12: 21287 | BP12: 21557 | BQ12: 21831 | BR12: 22108 | BS12: 22389 | BT12: 22674 | BU12: 22961 | BV12: 1004179
A13: Fee Variable Weso ($) | B13: 0 | C13: 0 | D13: 0 | E13: 0 | F13: 0 | G13: 0 | H13: 0 | I13: 0 | J13: 0 | K13: 3150 | L13: 3190 | M13: 3231 | N13: 3272 | O13: 3313 | P13: 3355 | Q13: 3398 | R13: 3441 | S13: 3485 | T13: 3529 | U13: 3574 | V13: 3619 | W13: 3665 | X13: 3712 | Y13: 3759 | Z13: 3806 | AA13: 3855 | AB13: 3904 | AC13: 3953 | AD13: 4004 | AE13: 4054 | AF13: 4106 | AG13: 4158 | AH13: 4211 | AI13: 4264 | AJ13: 4318 | AK13: 4373 | AL13: 4429 | AM13: 4485 | AN13: 4542 | AO13: 4600 | AP13: 4658 | AQ13: 4717 | AR13: 4777 | AS13: 4838 | AT13: 4899 | AU13: 4962 | AV13: 5025 | AW13: 5088 | AX13: 5153 | AY13: 5218 | AZ13: 5285 | BA13: 5352 | BB13: 5420 | BC13: 5489 | BD13: 5558 | BE13: 5629 | BF13: 5700 | BG13: 5773 | BH13: 5846 | BI13: 5920 | BJ13: 5996 | BK13: 6072 | BL13: 6149 | BM13: 6227 | BN13: 6306 | BO13: 6386 | BP13: 6467 | BQ13: 6549 | BR13: 6633 | BS13: 6717 | BT13: 6802 | BU13: 6888 | BV13: 301254
A14: Licencia Weso ($) | B14: 0 | C14: 0 | D14: 0 | E14: 0 | F14: 0 | G14: 0 | H14: 0 | I14: 0 | J14: 0 | K14: 0 | L14: 0 | M14: 0 | N14: 0 | O14: 0 | P14: 0 | Q14: 0 | R14: 0 | S14: 0 | T14: 0 | U14: 0 | V14: 0 | W14: 0 | X14: 0 | Y14: 0 | Z14: 0 | AA14: 0 | AB14: 0 | AC14: 0 | AD14: 0 | AE14: 0 | AF14: 0 | AG14: 0 | AH14: 0 | AI14: 0 | AJ14: 0 | AK14: 0 | AL14: 0 | AM14: 0 | AN14: 0 | AO14: 0 | AP14: 0 | AQ14: 0 | AR14: 0 | AS14: 0 | AT14: 0 | AU14: 0 | AV14: 0 | AW14: 0 | AX14: 0 | AY14: 0 | AZ14: 0 | BA14: 0 | BB14: 0 | BC14: 0 | BD14: 0 | BE14: 0 | BF14: 0 | BG14: 0 | BH14: 0 | BI14: 0 | BJ14: 0 | BK14: 0 | BL14: 0 | BM14: 0 | BN14: 0 | BO14: 0 | BP14: 0 | BQ14: 0 | BR14: 0 | BS14: 0 | BT14: 0 | BU14: 0 | BV14: 0
A15: Revenue Weso ($) | B15: 0 | C15: 0 | D15: 0 | E15: 0 | F15: 0 | G15: 0 | H15: 0 | I15: 0 | J15: 0 | K15: 3150 | L15: 3190 | M15: 3231 | N15: 3272 | O15: 3313 | P15: 3355 | Q15: 3398 | R15: 3441 | S15: 3485 | T15: 3529 | U15: 3574 | V15: 3619 | W15: 3665 | X15: 3712 | Y15: 3759 | Z15: 3806 | AA15: 3855 | AB15: 3904 | AC15: 3953 | AD15: 4004 | AE15: 4054 | AF15: 4106 | AG15: 4158 | AH15: 4211 | AI15: 4264 | AJ15: 4318 | AK15: 4373 | AL15: 4429 | AM15: 4485 | AN15: 4542 | AO15: 4600 | AP15: 4658 | AQ15: 4717 | AR15: 4777 | AS15: 4838 | AT15: 4899 | AU15: 4962 | AV15: 5025 | AW15: 5088 | AX15: 5153 | AY15: 5218 | AZ15: 5285 | BA15: 5352 | BB15: 5420 | BC15: 5489 | BD15: 5558 | BE15: 5629 | BF15: 5700 | BG15: 5773 | BH15: 5846 | BI15: 5920 | BJ15: 5996 | BK15: 6072 | BL15: 6149 | BM15: 6227 | BN15: 6306 | BO15: 6386 | BP15: 6467 | BQ15: 6549 | BR15: 6633 | BS15: 6717 | BT15: 6802 | BU15: 6888 | BV15: 301254
A16: Costos Proveedor ($) | B16: 0 | C16: 0 | D16: 0 | E16: 0 | F16: 0 | G16: 0 | H16: 0 | I16: 0 | J16: 0 | K16: 7350 | L16: 7443 | M16: 7538 | N16: 7634 | O16: 7731 | P16: 7829 | Q16: 7928 | R16: 8029 | S16: 8131 | T16: 8234 | U16: 8339 | V16: 8445 | W16: 8552 | X16: 8660 | Y16: 8770 | Z16: 8882 | AA16: 8995 | AB16: 9109 | AC16: 9224 | AD16: 9342 | AE16: 9460 | AF16: 9580 | AG16: 9702 | AH16: 9825 | AI16: 9950 | AJ16: 10076 | AK16: 10204 | AL16: 10334 | AM16: 10465 | AN16: 10598 | AO16: 10733 | AP16: 10869 | AQ16: 11007 | AR16: 11147 | AS16: 11288 | AT16: 11432 | AU16: 11577 | AV16: 11724 | AW16: 11873 | AX16: 12024 | AY16: 12176 | AZ16: 12331 | BA16: 12488 | BB16: 12646 | BC16: 12807 | BD16: 12970 | BE16: 13134 | BF16: 13301 | BG16: 13470 | BH16: 13641 | BI16: 13814 | BJ16: 13990 | BK16: 14167 | BL16: 14347 | BM16: 14530 | BN16: 14714 | BO16: 14901 | BP16: 15090 | BQ16: 15282 | BR16: 15476 | BS16: 15672 | BT16: 15871 | BU16: 16073 | BV16: 702925

Sheet 10_METLIFE
A1: Actor: METLIFE
A2: Categoría: Salud y cuidado · Servicio: · País: Chile
A3: Crecimiento: 0.8% · Churn: 0.6%
A5: Métrica | B5: M1 | C5: M2 | D5: M3 | E5: M4 | F5: M5 | G5: M6 | H5: M7 | I5: M8 | J5: M9 | K5: M10 | L5: M11 | M5: M12 | N5: M13 | O5: M14 | P5: M15 | Q5: M16 | R5: M17 | S5: M18 | T5: M19 | U5: M20 | V5: M21 | W5: M22 | X5: M23 | Y5: M24 | Z5: M25 | AA5: M26 | AB5: M27 | AC5: M28 | AD5: M29 | AE5: M30 | AF5: M31 | AG5: M32 | AH5: M33 | AI5: M34 | AJ5: M35 | AK5: M36 | AL5: M37 | AM5: M38 | AN5: M39 | AO5: M40 | AP5: M41 | AQ5: M42 | AR5: M43 | AS5: M44 | AT5: M45 | AU5: M46 | AV5: M47 | AW5: M48 | AX5: M49 | AY5: M50 | AZ5: M51 | BA5: M52 | BB5: M53 | BC5: M54 | BD5: M55 | BE5: M56 | BF5: M57 | BG5: M58 | BH5: M59 | BI5: M60 | BJ5: M61 | BK5: M62 | BL5: M63 | BM5: M64 | BN5: M65 | BO5: M66 | BP5: M67 | BQ5: M68 | BR5: M69 | BS5: M70 | BT5: M71 | BU5: M72 | BV5: TOTAL
A6: Clientes | B6: 0 | C6: 0 | D6: 0 | E6: 0 | F6: 0 | G6: 0 | H6: 0 | I6: 30000 | J6: 30059 | K6: 30117 | L6: 30176 | M6: 30235 | N6: 30294 | O6: 30353 | P6: 30412 | Q6: 30472 | R6: 30531 | S6: 30591 | T6: 30650 | U6: 30710 | V6: 30770 | W6: 30830 | X6: 30891 | Y6: 30951 | Z6: 31011 | AA6: 31072 | AB6: 31132 | AC6: 31193 | AD6: 31254 | AE6: 31315 | AF6: 31376 | AG6: 31437 | AH6: 31499 | AI6: 31560 | AJ6: 31622 | AK6: 31684 | AL6: 31745 | AM6: 31807 | AN6: 31870 | AO6: 31932 | AP6: 31994 | AQ6: 32057 | AR6: 32119 | AS6: 32182 | AT6: 32245 | AU6: 32308 | AV6: 32371 | AW6: 32434 | AX6: 32497 | AY6: 32561 | AZ6: 32624 | BA6: 32688 | BB6: 32752 | BC6: 32816 | BD6: 32880 | BE6: 32944 | BF6: 33008 | BG6: 33073 | BH6: 33137 | BI6: 33202 | BJ6: 33267 | BK6: 33331 | BL6: 33397 | BM6: 33462 | BN6: 33527 | BO6: 33593 | BP6: 33658 | BQ6: 33724 | BR6: 33790 | BS6: 33856 | BT6: 33922 | BU6: 33988
A7: Clientes Perdidos (Churn) | B7: 0 | C7: 0 | D7: 0 | E7: 0 | F7: 0 | G7: 0 | H7: 0 | I7: 0 | J7: 180 | K7: 180 | L7: 181 | M7: 181 | N7: 181 | O7: 182 | P7: 182 | Q7: 182 | R7: 183 | S7: 183 | T7: 184 | U7: 184 | V7: 184 | W7: 185 | X7: 185 | Y7: 185 | Z7: 186 | AA7: 186 | AB7: 186 | AC7: 187 | AD7: 187 | AE7: 188 | AF7: 188 | AG7: 188 | AH7: 189 | AI7: 189 | AJ7: 189 | AK7: 190 | AL7: 190 | AM7: 190 | AN7: 191 | AO7: 191 | AP7: 192 | AQ7: 192 | AR7: 192 | AS7: 193 | AT7: 193 | AU7: 193 | AV7: 194 | AW7: 194 | AX7: 195 | AY7: 195 | AZ7: 195 | BA7: 196 | BB7: 196 | BC7: 197 | BD7: 197 | BE7: 197 | BF7: 198 | BG7: 198 | BH7: 198 | BI7: 199 | BJ7: 199 | BK7: 200 | BL7: 200 | BM7: 200 | BN7: 201 | BO7: 201 | BP7: 202 | BQ7: 202 | BR7: 202 | BS7: 203 | BT7: 203 | BU7: 204 | BV7: 12258
A8: Tasa Uso % | B8: 1.5 | C8: 1.5 | D8: 1.5 | E8: 1.5 | F8: 1.5 | G8: 1.5 | H8: 1.5 | I8: 1.5 | J8: 1.5 | K8: 1.5 | L8: 1.5 | M8: 1.5 | N8: 1.5 | O8: 1.5 | P8: 1.5 | Q8: 1.5 | R8: 1.5 | S8: 1.5 | T8: 1.5 | U8: 1.5 | V8: 1.5 | W8: 1.5 | X8: 1.5 | Y8: 1.5 | Z8: 1.5 | AA8: 1.5 | AB8: 1.5 | AC8: 1.5 | AD8: 1.5 | AE8: 1.5 | AF8: 1.5 | AG8: 1.5 | AH8: 1.5 | AI8: 1.5 | AJ8: 1.5 | AK8: 1.5 | AL8: 1.5 | AM8: 1.5 | AN8: 1.5 | AO8: 1.5 | AP8: 1.5 | AQ8: 1.5 | AR8: 1.5 | AS8: 1.5 | AT8: 1.5 | AU8: 1.5 | AV8: 1.5 | AW8: 1.5 | AX8: 1.5 | AY8: 1.5 | AZ8: 1.5 | BA8: 1.5 | BB8: 1.5 | BC8: 1.5 | BD8: 1.5 | BE8: 1.5 | BF8: 1.5 | BG8: 1.5 | BH8: 1.5 | BI8: 1.5 | BJ8: 1.5 | BK8: 1.5 | BL8: 1.5 | BM8: 1.5 | BN8: 1.5 | BO8: 1.5 | BP8: 1.5 | BQ8: 1.5 | BR8: 1.5 | BS8: 1.5 | BT8: 1.5 | BU8: 1.5
A9: Ticket ($) | B9: 70 | C9: 70 | D9: 70 | E9: 70 | F9: 70 | G9: 70 | H9: 70 | I9: 70 | J9: 70 | K9: 70 | L9: 70 | M9: 70 | N9: 70 | O9: 70 | P9: 70 | Q9: 70 | R9: 70 | S9: 70 | T9: 70 | U9: 70 | V9: 70 | W9: 70 | X9: 70 | Y9: 70 | Z9: 70 | AA9: 70 | AB9: 70 | AC9: 70 | AD9: 70 | AE9: 70 | AF9: 70 | AG9: 70 | AH9: 70 | AI9: 70 | AJ9: 70 | AK9: 70 | AL9: 70 | AM9: 70 | AN9: 70 | AO9: 70 | AP9: 70 | AQ9: 70 | AR9: 70 | AS9: 70 | AT9: 70 | AU9: 70 | AV9: 70 | AW9: 70 | AX9: 70 | AY9: 70 | AZ9: 70 | BA9: 70 | BB9: 70 | BC9: 70 | BD9: 70 | BE9: 70 | BF9: 70 | BG9: 70 | BH9: 70 | BI9: 70 | BJ9: 70 | BK9: 70 | BL9: 70 | BM9: 70 | BN9: 70 | BO9: 70 | BP9: 70 | BQ9: 70 | BR9: 70 | BS9: 70 | BT9: 70 | BU9: 70 | BV9: 70.00
A10: Fee Weso % | B10: 30 | C10: 30 | D10: 30 | E10: 30 | F10: 30 | G10: 30 | H10: 30 | I10: 30 | J10: 30 | K10: 30 | L10: 30 | M10: 30 | N10: 30 | O10: 30 | P10: 30 | Q10: 30 | R10: 30 | S10: 30 | T10: 30 | U10: 30 | V10: 30 | W10: 30 | X10: 30 | Y10: 30 | Z10: 30 | AA10: 30 | AB10: 30 | AC10: 30 | AD10: 30 | AE10: 30 | AF10: 30 | AG10: 30 | AH10: 30 | AI10: 30 | AJ10: 30 | AK10: 30 | AL10: 30 | AM10: 30 | AN10: 30 | AO10: 30 | AP10: 30 | AQ10: 30 | AR10: 30 | AS10: 30 | AT10: 30 | AU10: 30 | AV10: 30 | AW10: 30 | AX10: 30 | AY10: 30 | AZ10: 30 | BA10: 30 | BB10: 30 | BC10: 30 | BD10: 30 | BE10: 30 | BF10: 30 | BG10: 30 | BH10: 30 | BI10: 30 | BJ10: 30 | BK10: 30 | BL10: 30 | BM10: 30 | BN10: 30 | BO10: 30 | BP10: 30 | BQ10: 30 | BR10: 30 | BS10: 30 | BT10: 30 | BU10: 30 | BV10: 30.00
A11: Casos | B11: 0 | C11: 0 | D11: 0 | E11: 0 | F11: 0 | G11: 0 | H11: 0 | I11: 450 | J11: 451 | K11: 452 | L11: 453 | M11: 454 | N11: 454 | O11: 455 | P11: 456 | Q11: 457 | R11: 458 | S11: 459 | T11: 460 | U11: 461 | V11: 462 | W11: 462 | X11: 463 | Y11: 464 | Z11: 465 | AA11: 466 | AB11: 467 | AC11: 468 | AD11: 469 | AE11: 470 | AF11: 471 | AG11: 472 | AH11: 472 | AI11: 473 | AJ11: 474 | AK11: 475 | AL11: 476 | AM11: 477 | AN11: 478 | AO11: 479 | AP11: 480 | AQ11: 481 | AR11: 482 | AS11: 483 | AT11: 484 | AU11: 485 | AV11: 486 | AW11: 487 | AX11: 487 | AY11: 488 | AZ11: 489 | BA11: 490 | BB11: 491 | BC11: 492 | BD11: 493 | BE11: 494 | BF11: 495 | BG11: 496 | BH11: 497 | BI11: 498 | BJ11: 499 | BK11: 500 | BL11: 501 | BM11: 502 | BN11: 503 | BO11: 504 | BP11: 505 | BQ11: 506 | BR11: 507 | BS11: 508 | BT11: 509 | BU11: 510 | BV11: 31154
A12: Revenue Total ($) | B12: 0 | C12: 0 | D12: 0 | E12: 0 | F12: 0 | G12: 0 | H12: 0 | I12: 31500 | J12: 31561 | K12: 31623 | L12: 31685 | M12: 31747 | N12: 31809 | O12: 31871 | P12: 31933 | Q12: 31995 | R12: 32058 | S12: 32120 | T12: 32183 | U12: 32246 | V12: 32309 | W12: 32372 | X12: 32435 | Y12: 32498 | Z12: 32562 | AA12: 32625 | AB12: 32689 | AC12: 32753 | AD12: 32817 | AE12: 32881 | AF12: 32945 | AG12: 33009 | AH12: 33074 | AI12: 33138 | AJ12: 33203 | AK12: 33268 | AL12: 33333 | AM12: 33398 | AN12: 33463 | AO12: 33528 | AP12: 33594 | AQ12: 33659 | AR12: 33725 | AS12: 33791 | AT12: 33857 | AU12: 33923 | AV12: 33989 | AW12: 34055 | AX12: 34122 | AY12: 34189 | AZ12: 34255 | BA12: 34322 | BB12: 34389 | BC12: 34456 | BD12: 34524 | BE12: 34591 | BF12: 34658 | BG12: 34726 | BH12: 34794 | BI12: 34862 | BJ12: 34930 | BK12: 34998 | BL12: 35066 | BM12: 35135 | BN12: 35203 | BO12: 35272 | BP12: 35341 | BQ12: 35410 | BR12: 35479 | BS12: 35548 | BT12: 35618 | BU12: 35687 | BV12: 2180800
A13: Fee Variable Weso ($) | B13: 0 | C13: 0 | D13: 0 | E13: 0 | F13: 0 | G13: 0 | H13: 0 | I13: 9450 | J13: 9468 | K13: 9487 | L13: 9505 | M13: 9524 | N13: 9543 | O13: 9561 | P13: 9580 | Q13: 9599 | R13: 9617 | S13: 9636 | T13: 9655 | U13: 9674 | V13: 9693 | W13: 9712 | X13: 9731 | Y13: 9750 | Z13: 9769 | AA13: 9788 | AB13: 9807 | AC13: 9826 | AD13: 9845 | AE13: 9864 | AF13: 9884 | AG13: 9903 | AH13: 9922 | AI13: 9941 | AJ13: 9961 | AK13: 9980 | AL13: 10000 | AM13: 10019 | AN13: 10039 | AO13: 10058 | AP13: 10078 | AQ13: 10098 | AR13: 10118 | AS13: 10137 | AT13: 10157 | AU13: 10177 | AV13: 10197 | AW13: 10217 | AX13: 10237 | AY13: 10257 | AZ13: 10277 | BA13: 10297 | BB13: 10317 | BC13: 10337 | BD13: 10357 | BE13: 10377 | BF13: 10398 | BG13: 10418 | BH13: 10438 | BI13: 10459 | BJ13: 10479 | BK13: 10499 | BL13: 10520 | BM13: 10540 | BN13: 10561 | BO13: 10582 | BP13: 10602 | BQ13: 10623 | BR13: 10644 | BS13: 10665 | BT13: 10685 | BU13: 10706 | BV13: 654240
A14: Licencia Weso ($) | B14: 0 | C14: 0 | D14: 0 | E14: 0 | F14: 0 | G14: 0 | H14: 0 | I14: 2000 | J14: 2000 | K14: 2000 | L14: 2000 | M14: 2000 | N14: 2000 | O14: 2000 | P14: 2000 | Q14: 2000 | R14: 2000 | S14: 2000 | T14: 2000 | U14: 2000 | V14: 2000 | W14: 2000 | X14: 2000 | Y14: 2000 | Z14: 2000 | AA14: 2000 | AB14: 2000 | AC14: 2000 | AD14: 2000 | AE14: 2000 | AF14: 2000 | AG14: 2000 | AH14: 2000 | AI14: 2000 | AJ14: 2000 | AK14: 2000 | AL14: 2000 | AM14: 2000 | AN14: 2000 | AO14: 2000 | AP14: 2000 | AQ14: 2000 | AR14: 2000 | AS14: 2000 | AT14: 2000 | AU14: 2000 | AV14: 2000 | AW14: 2000 | AX14: 2000 | AY14: 2000 | AZ14: 2000 | BA14: 2000 | BB14: 2000 | BC14: 2000 | BD14: 2000 | BE14: 2000 | BF14: 2000 | BG14: 2000 | BH14: 2000 | BI14: 2000 | BJ14: 2000 | BK14: 2000 | BL14: 2000 | BM14: 2000 | BN14: 2000 | BO14: 2000 | BP14: 2000 | BQ14: 2000 | BR14: 2000 | BS14: 2000 | BT14: 2000 | BU14: 2000 | BV14: 130000
A15: Revenue Weso ($) | B15: 0 | C15: 0 | D15: 0 | E15: 0 | F15: 0 | G15: 0 | H15: 0 | I15: 11450 | J15: 11468 | K15: 11487 | L15: 11505 | M15: 11524 | N15: 11543 | O15: 11561 | P15: 11580 | Q15: 11599 | R15: 11617 | S15: 11636 | T15: 11655 | U15: 11674 | V15: 11693 | W15: 11712 | X15: 11731 | Y15: 11750 | Z15: 11769 | AA15: 11788 | AB15: 11807 | AC15: 11826 | AD15: 11845 | AE15: 11864 | AF15: 11884 | AG15: 11903 | AH15: 11922 | AI15: 11941 | AJ15: 11961 | AK15: 11980 | AL15: 12000 | AM15: 12019 | AN15: 12039 | AO15: 12058 | AP15: 12078 | AQ15: 12098 | AR15: 12118 | AS15: 12137 | AT15: 12157 | AU15: 12177 | AV15: 12197 | AW15: 12217 | AX15: 12237 | AY15: 12257 | AZ15: 12277 | BA15: 12297 | BB15: 12317 | BC15: 12337 | BD15: 12357 | BE15: 12377 | BF15: 12398 | BG15: 12418 | BH15: 12438 | BI15: 12459 | BJ15: 12479 | BK15: 12499 | BL15: 12520 | BM15: 12540 | BN15: 12561 | BO15: 12582 | BP15: 12602 | BQ15: 12623 | BR15: 12644 | BS15: 12665 | BT15: 12685 | BU15: 12706 | BV15: 784240
A16: Costos Proveedor ($) | B16: 0 | C16: 0 | D16: 0 | E16: 0 | F16: 0 | G16: 0 | H16: 0 | I16: 22050 | J16: 22093 | K16: 22136 | L16: 22179 | M16: 22223 | N16: 22266 | O16: 22310 | P16: 22353 | Q16: 22397 | R16: 22440 | S16: 22484 | T16: 22528 | U16: 22572 | V16: 22616 | W16: 22660 | X16: 22705 | Y16: 22749 | Z16: 22793 | AA16: 22838 | AB16: 22882 | AC16: 22927 | AD16: 22972 | AE16: 23017 | AF16: 23062 | AG16: 23107 | AH16: 23152 | AI16: 23197 | AJ16: 23242 | AK16: 23287 | AL16: 23333 | AM16: 23378 | AN16: 23424 | AO16: 23470 | AP16: 23516 | AQ16: 23562 | AR16: 23608 | AS16: 23654 | AT16: 23700 | AU16: 23746 | AV16: 23792 | AW16: 23839 | AX16: 23885 | AY16: 23932 | AZ16: 23979 | BA16: 24026 | BB16: 24072 | BC16: 24119 | BD16: 24166 | BE16: 24214 | BF16: 24261 | BG16: 24308 | BH16: 24356 | BI16: 24403 | BJ16: 24451 | BK16: 24499 | BL16: 24546 | BM16: 24594 | BN16: 24642 | BO16: 24690 | BP16: 24739 | BQ16: 24787 | BR16: 24835 | BS16: 24884 | BT16: 24932 | BU16: 24981 | BV16: 1526560

Sheet 11_METLIFE  - Salud
A1: Actor: METLIFE - Salud
A2: Categoría: Salud y cuidado · Servicio: · País: Colombia
A3: Crecimiento: 0.8% · Churn: 0.6%
A5: Métrica | B5: M1 | C5: M2 | D5: M3 | E5: M4 | F5: M5 | G5: M6 | H5: M7 | I5: M8 | J5: M9 | K5: M10 | L5: M11 | M5: M12 | N5: M13 | O5: M14 | P5: M15 | Q5: M16 | R5: M17 | S5: M18 | T5: M19 | U5: M20 | V5: M21 | W5: M22 | X5: M23 | Y5: M24 | Z5: M25 | AA5: M26 | AB5: M27 | AC5: M28 | AD5: M29 | AE5: M30 | AF5: M31 | AG5: M32 | AH5: M33 | AI5: M34 | AJ5: M35 | AK5: M36 | AL5: M37 | AM5: M38 | AN5: M39 | AO5: M40 | AP5: M41 | AQ5: M42 | AR5: M43 | AS5: M44 | AT5: M45 | AU5: M46 | AV5: M47 | AW5: M48 | AX5: M49 | AY5: M50 | AZ5: M51 | BA5: M52 | BB5: M53 | BC5: M54 | BD5: M55 | BE5: M56 | BF5: M57 | BG5: M58 | BH5: M59 | BI5: M60 | BJ5: M61 | BK5: M62 | BL5: M63 | BM5: M64 | BN5: M65 | BO5: M66 | BP5: M67 | BQ5: M68 | BR5: M69 | BS5: M70 | BT5: M71 | BU5: M72 | BV5: TOTAL
A6: Clientes | B6: 0 | C6: 0 | D6: 0 | E6: 0 | F6: 0 | G6: 0 | H6: 0 | I6: 0 | J6: 0 | K6: 0 | L6: 0 | M6: 35000 | N6: 35068 | O6: 35137 | P6: 35205 | Q6: 35274 | R6: 35343 | S6: 35412 | T6: 35481 | U6: 35550 | V6: 35620 | W6: 35689 | X6: 35759 | Y6: 35829 | Z6: 35899 | AA6: 35969 | AB6: 36039 | AC6: 36109 | AD6: 36180 | AE6: 36250 | AF6: 36321 | AG6: 36392 | AH6: 36463 | AI6: 36534 | AJ6: 36606 | AK6: 36677 | AL6: 36749 | AM6: 36820 | AN6: 36892 | AO6: 36964 | AP6: 37036 | AQ6: 37109 | AR6: 37181 | AS6: 37254 | AT6: 37326 | AU6: 37399 | AV6: 37472 | AW6: 37545 | AX6: 37619 | AY6: 37692 | AZ6: 37766 | BA6: 37839 | BB6: 37913 | BC6: 37987 | BD6: 38061 | BE6: 38136 | BF6: 38210 | BG6: 38285 | BH6: 38360 | BI6: 38434 | BJ6: 38509 | BK6: 38585 | BL6: 38660 | BM6: 38735 | BN6: 38811 | BO6: 38887 | BP6: 38963 | BQ6: 39039 | BR6: 39115 | BS6: 39191 | BT6: 39268 | BU6: 39344
A7: Clientes Perdidos (Churn) | B7: 0 | C7: 0 | D7: 0 | E7: 0 | F7: 0 | G7: 0 | H7: 0 | I7: 0 | J7: 0 | K7: 0 | L7: 0 | M7: 0 | N7: 210 | O7: 210 | P7: 211 | Q7: 211 | R7: 212 | S7: 212 | T7: 212 | U7: 213 | V7: 213 | W7: 214 | X7: 214 | Y7: 215 | Z7: 215 | AA7: 215 | AB7: 216 | AC7: 216 | AD7: 217 | AE7: 217 | AF7: 218 | AG7: 218 | AH7: 218 | AI7: 219 | AJ7: 219 | AK7: 220 | AL7: 220 | AM7: 220 | AN7: 221 | AO7: 221 | AP7: 222 | AQ7: 222 | AR7: 223 | AS7: 223 | AT7: 224 | AU7: 224 | AV7: 224 | AW7: 225 | AX7: 225 | AY7: 226 | AZ7: 226 | BA7: 227 | BB7: 227 | BC7: 227 | BD7: 228 | BE7: 228 | BF7: 229 | BG7: 229 | BH7: 230 | BI7: 230 | BJ7: 231 | BK7: 231 | BL7: 232 | BM7: 232 | BN7: 232 | BO7: 233 | BP7: 233 | BQ7: 234 | BR7: 234 | BS7: 235 | BT7: 235 | BU7: 236 | BV7: 13354
A8: Tasa Uso % | B8: 1.7 | C8: 1.7 | D8: 1.7 | E8: 1.7 | F8: 1.7 | G8: 1.7 | H8: 1.7 | I8: 1.7 | J8: 1.7 | K8: 1.7 | L8: 1.7 | M8: 1.7 | N8: 1.7 | O8: 1.7 | P8: 1.7 | Q8: 1.7 | R8: 1.7 | S8: 1.7 | T8: 1.7 | U8: 1.7 | V8: 1.7 | W8: 1.7 | X8: 1.7 | Y8: 1.7 | Z8: 1.7 | AA8: 1.7 | AB8: 1.7 | AC8: 1.7 | AD8: 1.7 | AE8: 1.7 | AF8: 1.7 | AG8: 1.7 | AH8: 1.7 | AI8: 1.7 | AJ8: 1.7 | AK8: 1.7 | AL8: 1.7 | AM8: 1.7 | AN8: 1.7 | AO8: 1.7 | AP8: 1.7 | AQ8: 1.7 | AR8: 1.7 | AS8: 1.7 | AT8: 1.7 | AU8: 1.7 | AV8: 1.7 | AW8: 1.7 | AX8: 1.7 | AY8: 1.7 | AZ8: 1.7 | BA8: 1.7 | BB8: 1.7 | BC8: 1.7 | BD8: 1.7 | BE8: 1.7 | BF8: 1.7 | BG8: 1.7 | BH8: 1.7 | BI8: 1.7 | BJ8: 1.7 | BK8: 1.7 | BL8: 1.7 | BM8: 1.7 | BN8: 1.7 | BO8: 1.7 | BP8: 1.7 | BQ8: 1.7 | BR8: 1.7 | BS8: 1.7 | BT8: 1.7 | BU8: 1.7
A9: Ticket ($) | B9: 50 | C9: 50 | D9: 50 | E9: 50 | F9: 50 | G9: 50 | H9: 50 | I9: 50 | J9: 50 | K9: 50 | L9: 50 | M9: 50 | N9: 50 | O9: 50 | P9: 50 | Q9: 50 | R9: 50 | S9: 50 | T9: 50 | U9: 50 | V9: 50 | W9: 50 | X9: 50 | Y9: 50 | Z9: 50 | AA9: 50 | AB9: 50 | AC9: 50 | AD9: 50 | AE9: 50 | AF9: 50 | AG9: 50 | AH9: 50 | AI9: 50 | AJ9: 50 | AK9: 50 | AL9: 50 | AM9: 50 | AN9: 50 | AO9: 50 | AP9: 50 | AQ9: 50 | AR9: 50 | AS9: 50 | AT9: 50 | AU9: 50 | AV9: 50 | AW9: 50 | AX9: 50 | AY9: 50 | AZ9: 50 | BA9: 50 | BB9: 50 | BC9: 50 | BD9: 50 | BE9: 50 | BF9: 50 | BG9: 50 | BH9: 50 | BI9: 50 | BJ9: 50 | BK9: 50 | BL9: 50 | BM9: 50 | BN9: 50 | BO9: 50 | BP9: 50 | BQ9: 50 | BR9: 50 | BS9: 50 | BT9: 50 | BU9: 50 | BV9: 50.00
A10: Fee Weso % | B10: 30 | C10: 30 | D10: 30 | E10: 30 | F10: 30 | G10: 30 | H10: 30 | I10: 30 | J10: 30 | K10: 30 | L10: 30 | M10: 30 | N10: 30 | O10: 30 | P10: 30 | Q10: 30 | R10: 30 | S10: 30 | T10: 30 | U10: 30 | V10: 30 | W10: 30 | X10: 30 | Y10: 30 | Z10: 30 | AA10: 30 | AB10: 30 | AC10: 30 | AD10: 30 | AE10: 30 | AF10: 30 | AG10: 30 | AH10: 30 | AI10: 30 | AJ10: 30 | AK10: 30 | AL10: 30 | AM10: 30 | AN10: 30 | AO10: 30 | AP10: 30 | AQ10: 30 | AR10: 30 | AS10: 30 | AT10: 30 | AU10: 30 | AV10: 30 | AW10: 30 | AX10: 30 | AY10: 30 | AZ10: 30 | BA10: 30 | BB10: 30 | BC10: 30 | BD10: 30 | BE10: 30 | BF10: 30 | BG10: 30 | BH10: 30 | BI10: 30 | BJ10: 30 | BK10: 30 | BL10: 30 | BM10: 30 | BN10: 30 | BO10: 30 | BP10: 30 | BQ10: 30 | BR10: 30 | BS10: 30 | BT10: 30 | BU10: 30 | BV10: 30.00
A11: Casos | B11: 0 | C11: 0 | D11: 0 | E11: 0 | F11: 0 | G11: 0 | H11: 0 | I11: 0 | J11: 0 | K11: 0 | L11: 0 | M11: 595 | N11: 596 | O11: 597 | P11: 598 | Q11: 600 | R11: 601 | S11: 602 | T11: 603 | U11: 604 | V11: 606 | W11: 607 | X11: 608 | Y11: 609 | Z11: 610 | AA11: 611 | AB11: 613 | AC11: 614 | AD11: 615 | AE11: 616 | AF11: 617 | AG11: 619 | AH11: 620 | AI11: 621 | AJ11: 622 | AK11: 624 | AL11: 625 | AM11: 626 | AN11: 627 | AO11: 628 | AP11: 630 | AQ11: 631 | AR11: 632 | AS11: 633 | AT11: 635 | AU11: 636 | AV11: 637 | AW11: 638 | AX11: 640 | AY11: 641 | AZ11: 642 | BA11: 643 | BB11: 645 | BC11: 646 | BD11: 647 | BE11: 648 | BF11: 650 | BG11: 651 | BH11: 652 | BI11: 653 | BJ11: 655 | BK11: 656 | BL11: 657 | BM11: 659 | BN11: 660 | BO11: 661 | BP11: 662 | BQ11: 664 | BR11: 665 | BS11: 666 | BT11: 668 | BU11: 669 | BV11: 38504
A12: Revenue Total ($) | B12: 0 | C12: 0 | D12: 0 | E12: 0 | F12: 0 | G12: 0 | H12: 0 | I12: 0 | J12: 0 | K12: 0 | L12: 0 | M12: 29750 | N12: 29808 | O12: 29866 | P12: 29925 | Q12: 29983 | R12: 30041 | S12: 30100 | T12: 30159 | U12: 30218 | V12: 30277 | W12: 30336 | X12: 30395 | Y12: 30454 | Z12: 30514 | AA12: 30573 | AB12: 30633 | AC12: 30693 | AD12: 30753 | AE12: 30813 | AF12: 30873 | AG12: 30933 | AH12: 30994 | AI12: 31054 | AJ12: 31115 | AK12: 31175 | AL12: 31236 | AM12: 31297 | AN12: 31358 | AO12: 31420 | AP12: 31481 | AQ12: 31542 | AR12: 31604 | AS12: 31666 | AT12: 31727 | AU12: 31789 | AV12: 31851 | AW12: 31914 | AX12: 31976 | AY12: 32038 | AZ12: 32101 | BA12: 32164 | BB12: 32226 | BC12: 32289 | BD12: 32352 | BE12: 32415 | BF12: 32479 | BG12: 32542 | BH12: 32606 | BI12: 32669 | BJ12: 32733 | BK12: 32797 | BL12: 32861 | BM12: 32925 | BN12: 32989 | BO12: 33054 | BP12: 33118 | BQ12: 33183 | BR12: 33248 | BS12: 33313 | BT12: 33378 | BU12: 33443 | BV12: 1925220
A13: Fee Variable Weso ($) | B13: 0 | C13: 0 | D13: 0 | E13: 0 | F13: 0 | G13: 0 | H13: 0 | I13: 0 | J13: 0 | K13: 0 | L13: 0 | M13: 8925 | N13: 8942 | O13: 8960 | P13: 8977 | Q13: 8995 | R13: 9012 | S13: 9030 | T13: 9048 | U13: 9065 | V13: 9083 | W13: 9101 | X13: 9119 | Y13: 9136 | Z13: 9154 | AA13: 9172 | AB13: 9190 | AC13: 9208 | AD13: 9226 | AE13: 9244 | AF13: 9262 | AG13: 9280 | AH13: 9298 | AI13: 9316 | AJ13: 9334 | AK13: 9353 | AL13: 9371 | AM13: 9389 | AN13: 9408 | AO13: 9426 | AP13: 9444 | AQ13: 9463 | AR13: 9481 | AS13: 9500 | AT13: 9518 | AU13: 9537 | AV13: 9555 | AW13: 9574 | AX13: 9593 | AY13: 9611 | AZ13: 9630 | BA13: 9649 | BB13: 9668 | BC13: 9687 | BD13: 9706 | BE13: 9725 | BF13: 9744 | BG13: 9763 | BH13: 9782 | BI13: 9801 | BJ13: 9820 | BK13: 9839 | BL13: 9858 | BM13: 9878 | BN13: 9897 | BO13: 9916 | BP13: 9935 | BQ13: 9955 | BR13: 9974 | BS13: 9994 | BT13: 10013 | BU13: 10033 | BV13: 577566
A14: Licencia Weso ($) | B14: 0 | C14: 0 | D14: 0 | E14: 0 | F14: 0 | G14: 0 | H14: 0 | I14: 0 | J14: 0 | K14: 0 | L14: 0 | M14: 0 | N14: 0 | O14: 0 | P14: 0 | Q14: 0 | R14: 0 | S14: 0 | T14: 0 | U14: 0 | V14: 0 | W14: 0 | X14: 0 | Y14: 0 | Z14: 0 | AA14: 0 | AB14: 0 | AC14: 0 | AD14: 0 | AE14: 0 | AF14: 0 | AG14: 0 | AH14: 0 | AI14: 0 | AJ14: 0 | AK14: 0 | AL14: 0 | AM14: 0 | AN14: 0 | AO14: 0 | AP14: 0 | AQ14: 0 | AR14: 0 | AS14: 0 | AT14: 0 | AU14: 0 | AV14: 0 | AW14: 0 | AX14: 0 | AY14: 0 | AZ14: 0 | BA14: 0 | BB14: 0 | BC14: 0 | BD14: 0 | BE14: 0 | BF14: 0 | BG14: 0 | BH14: 0 | BI14: 0 | BJ14: 0 | BK14: 0 | BL14: 0 | BM14: 0 | BN14: 0 | BO14: 0 | BP14: 0 | BQ14: 0 | BR14: 0 | BS14: 0 | BT14: 0 | BU14: 0 | BV14: 0
A15: Revenue Weso ($) | B15: 0 | C15: 0 | D15: 0 | E15: 0 | F15: 0 | G15: 0 | H15: 0 | I15: 0 | J15: 0 | K15: 0 | L15: 0 | M15: 8925 | N15: 8942 | O15: 8960 | P15: 8977 | Q15: 8995 | R15: 9012 | S15: 9030 | T15: 9048 | U15: 9065 | V15: 9083 | W15: 9101 | X15: 9119 | Y15: 9136 | Z15: 9154 | AA15: 9172 | AB15: 9190 | AC15: 9208 | AD15: 9226 | AE15: 9244 | AF15: 9262 | AG15: 9280 | AH15: 9298 | AI15: 9316 | AJ15: 9334 | AK15: 9353 | AL15: 9371 | AM15: 9389 | AN15: 9408 | AO15: 9426 | AP15: 9444 | AQ15: 9463 | AR15: 9481 | AS15: 9500 | AT15: 9518 | AU15: 9537 | AV15: 9555 | AW15: 9574 | AX15: 9593 | AY15: 9611 | AZ15: 9630 | BA15: 9649 | BB15: 9668 | BC15: 9687 | BD15: 9706 | BE15: 9725 | BF15: 9744 | BG15: 9763 | BH15: 9782 | BI15: 9801 | BJ15: 9820 | BK15: 9839 | BL15: 9858 | BM15: 9878 | BN15: 9897 | BO15: 9916 | BP15: 9935 | BQ15: 9955 | BR15: 9974 | BS15: 9994 | BT15: 10013 | BU15: 10033 | BV15: 577566
A16: Costos Proveedor ($) | B16: 0 | C16: 0 | D16: 0 | E16: 0 | F16: 0 | G16: 0 | H16: 0 | I16: 0 | J16: 0 | K16: 0 | L16: 0 | M16: 20825 | N16: 20866 | O16: 20906 | P16: 20947 | Q16: 20988 | R16: 21029 | S16: 21070 | T16: 21111 | U16: 21152 | V16: 21194 | W16: 21235 | X16: 21277 | Y16: 21318 | Z16: 21360 | AA16: 21401 | AB16: 21443 | AC16: 21485 | AD16: 21527 | AE16: 21569 | AF16: 21611 | AG16: 21653 | AH16: 21696 | AI16: 21738 | AJ16: 21780 | AK16: 21823 | AL16: 21865 | AM16: 21908 | AN16: 21951 | AO16: 21994 | AP16: 22037 | AQ16: 22080 | AR16: 22123 | AS16: 22166 | AT16: 22209 | AU16: 22253 | AV16: 22296 | AW16: 22340 | AX16: 22383 | AY16: 22427 | AZ16: 22471 | BA16: 22514 | BB16: 22558 | BC16: 22602 | BD16: 22647 | BE16: 22691 | BF16: 22735 | BG16: 22779 | BH16: 22824 | BI16: 22868 | BJ16: 22913 | BK16: 22958 | BL16: 23003 | BM16: 23048 | BN16: 23093 | BO16: 23138 | BP16: 23183 | BQ16: 23228 | BR16: 23273 | BS16: 23319 | BT16: 23364 | BU16: 23410 | BV16: 1347654

Sheet 12_Seguros Mundial 🇨🇴
A1: Actor: Seguros Mundial 🇨🇴
A2: Categoría: Asistencia en Ruta - Livianos · Servicio: · País: Colombia
A3: Crecimiento: 1% · Churn: 0.7%
A5: Métrica | B5: M1 | C5: M2 | D5: M3 | E5: M4 | F5: M5 | G5: M6 | H5: M7 | I5: M8 | J5: M9 | K5: M10 | L5: M11 | M5: M12 | N5: M13 | O5: M14 | P5: M15 | Q5: M16 | R5: M17 | S5: M18 | T5: M19 | U5: M20 | V5: M21 | W5: M22 | X5: M23 | Y5: M24 | Z5: M25 | AA5: M26 | AB5: M27 | AC5: M28 | AD5: M29 | AE5: M30 | AF5: M31 | AG5: M32 | AH5: M33 | AI5: M34 | AJ5: M35 | AK5: M36 | AL5: M37 | AM5: M38 | AN5: M39 | AO5: M40 | AP5: M41 | AQ5: M42 | AR5: M43 | AS5: M44 | AT5: M45 | AU5: M46 | AV5: M47 | AW5: M48 | AX5: M49 | AY5: M50 | AZ5: M51 | BA5: M52 | BB5: M53 | BC5: M54 | BD5: M55 | BE5: M56 | BF5: M57 | BG5: M58 | BH5: M59 | BI5: M60 | BJ5: M61 | BK5: M62 | BL5: M63 | BM5: M64 | BN5: M65 | BO5: M66 | BP5: M67 | BQ5: M68 | BR5: M69 | BS5: M70 | BT5: M71 | BU5: M72 | BV5: TOTAL
A6: Clientes | B6: 0 | C6: 0 | D6: 0 | E6: 0 | F6: 0 | G6: 0 | H6: 0 | I6: 0 | J6: 0 | K6: 0 | L6: 0 | M6: 0 | N6: 0 | O6: 30000 | P6: 30088 | Q6: 30176 | R6: 30264 | S6: 30353 | T6: 30442 | U6: 30531 | V6: 30621 | W6: 30710 | X6: 30800 | Y6: 30891 | Z6: 30981 | AA6: 31072 | AB6: 31163 | AC6: 31254 | AD6: 31346 | AE6: 31438 | AF6: 31530 | AG6: 31622 | AH6: 31715 | AI6: 31808 | AJ6: 31901 | AK6: 31994 | AL6: 32088 | AM6: 32182 | AN6: 32277 | AO6: 32371 | AP6: 32466 | AQ6: 32561 | AR6: 32656 | AS6: 32752 | AT6: 32848 | AU6: 32944 | AV6: 33041 | AW6: 33138 | AX6: 33235 | AY6: 33332 | AZ6: 33430 | BA6: 33528 | BB6: 33626 | BC6: 33725 | BD6: 33823 | BE6: 33922 | BF6: 34022 | BG6: 34122 | BH6: 34222 | BI6: 34322 | BJ6: 34422 | BK6: 34523 | BL6: 34624 | BM6: 34726 | BN6: 34828 | BO6: 34930 | BP6: 35032 | BQ6: 35135 | BR6: 35238 | BS6: 35341 | BT6: 35444 | BU6: 35548
A7: Clientes Perdidos (Churn) | B7: 0 | C7: 0 | D7: 0 | E7: 0 | F7: 0 | G7: 0 | H7: 0 | I7: 0 | J7: 0 | K7: 0 | L7: 0 | M7: 0 | N7: 0 | O7: 0 | P7: 210 | Q7: 211 | R7: 211 | S7: 212 | T7: 212 | U7: 213 | V7: 214 | W7: 214 | X7: 215 | Y7: 216 | Z7: 216 | AA7: 217 | AB7: 218 | AC7: 218 | AD7: 219 | AE7: 219 | AF7: 220 | AG7: 221 | AH7: 221 | AI7: 222 | AJ7: 223 | AK7: 223 | AL7: 224 | AM7: 225 | AN7: 225 | AO7: 226 | AP7: 227 | AQ7: 227 | AR7: 228 | AS7: 229 | AT7: 229 | AU7: 230 | AV7: 231 | AW7: 231 | AX7: 232 | AY7: 233 | AZ7: 233 | BA7: 234 | BB7: 235 | BC7: 235 | BD7: 236 | BE7: 237 | BF7: 237 | BG7: 238 | BH7: 239 | BI7: 240 | BJ7: 240 | BK7: 241 | BL7: 242 | BM7: 242 | BN7: 243 | BO7: 244 | BP7: 245 | BQ7: 245 | BR7: 246 | BS7: 247 | BT7: 247 | BU7: 248 | BV7: 13255
A8: Tasa Uso % | B8: 1.4 | C8: 1.4 | D8: 1.4 | E8: 1.4 | F8: 1.4 | G8: 1.4 | H8: 1.4 | I8: 1.4 | J8: 1.4 | K8: 1.4 | L8: 1.4 | M8: 1.4 | N8: 1.4 | O8: 1.4 | P8: 1.4 | Q8: 1.4 | R8: 1.4 | S8: 1.4 | T8: 1.4 | U8: 1.4 | V8: 1.4 | W8: 1.4 | X8: 1.4 | Y8: 1.4 | Z8: 1.4 | AA8: 1.4 | AB8: 1.4 | AC8: 1.4 | AD8: 1.4 | AE8: 1.4 | AF8: 1.4 | AG8: 1.4 | AH8: 1.4 | AI8: 1.4 | AJ8: 1.4 | AK8: 1.4 | AL8: 1.4 | AM8: 1.4 | AN8: 1.4 | AO8: 1.4 | AP8: 1.4 | AQ8: 1.4 | AR8: 1.4 | AS8: 1.4 | AT8: 1.4 | AU8: 1.4 | AV8: 1.4 | AW8: 1.4 | AX8: 1.4 | AY8: 1.4 | AZ8: 1.4 | BA8: 1.4 | BB8: 1.4 | BC8: 1.4 | BD8: 1.4 | BE8: 1.4 | BF8: 1.4 | BG8: 1.4 | BH8: 1.4 | BI8: 1.4 | BJ8: 1.4 | BK8: 1.4 | BL8: 1.4 | BM8: 1.4 | BN8: 1.4 | BO8: 1.4 | BP8: 1.4 | BQ8: 1.4 | BR8: 1.4 | BS8: 1.4 | BT8: 1.4 | BU8: 1.4
A9: Ticket ($) | B9: 60 | C9: 60 | D9: 60 | E9: 60 | F9: 60 | G9: 60 | H9: 60 | I9: 60 | J9: 60 | K9: 60 | L9: 60 | M9: 60 | N9: 60 | O9: 60 | P9: 60 | Q9: 60 | R9: 60 | S9: 60 | T9: 60 | U9: 60 | V9: 60 | W9: 60 | X9: 60 | Y9: 60 | Z9: 60 | AA9: 60 | AB9: 60 | AC9: 60 | AD9: 60 | AE9: 60 | AF9: 60 | AG9: 60 | AH9: 60 | AI9: 60 | AJ9: 60 | AK9: 60 | AL9: 60 | AM9: 60 | AN9: 60 | AO9: 60 | AP9: 60 | AQ9: 60 | AR9: 60 | AS9: 60 | AT9: 60 | AU9: 60 | AV9: 60 | AW9: 60 | AX9: 60 | AY9: 60 | AZ9: 60 | BA9: 60 | BB9: 60 | BC9: 60 | BD9: 60 | BE9: 60 | BF9: 60 | BG9: 60 | BH9: 60 | BI9: 60 | BJ9: 60 | BK9: 60 | BL9: 60 | BM9: 60 | BN9: 60 | BO9: 60 | BP9: 60 | BQ9: 60 | BR9: 60 | BS9: 60 | BT9: 60 | BU9: 60 | BV9: 60.00
A10: Fee Weso % | B10: 30 | C10: 30 | D10: 30 | E10: 30 | F10: 30 | G10: 30 | H10: 30 | I10: 30 | J10: 30 | K10: 30 | L10: 30 | M10: 30 | N10: 30 | O10: 30 | P10: 30 | Q10: 30 | R10: 30 | S10: 30 | T10: 30 | U10: 30 | V10: 30 | W10: 30 | X10: 30 | Y10: 30 | Z10: 30 | AA10: 30 | AB10: 30 | AC10: 30 | AD10: 30 | AE10: 30 | AF10: 30 | AG10: 30 | AH10: 30 | AI10: 30 | AJ10: 30 | AK10: 30 | AL10: 30 | AM10: 30 | AN10: 30 | AO10: 30 | AP10: 30 | AQ10: 30 | AR10: 30 | AS10: 30 | AT10: 30 | AU10: 30 | AV10: 30 | AW10: 30 | AX10: 30 | AY10: 30 | AZ10: 30 | BA10: 30 | BB10: 30 | BC10: 30 | BD10: 30 | BE10: 30 | BF10: 30 | BG10: 30 | BH10: 30 | BI10: 30 | BJ10: 30 | BK10: 30 | BL10: 30 | BM10: 30 | BN10: 30 | BO10: 30 | BP10: 30 | BQ10: 30 | BR10: 30 | BS10: 30 | BT10: 30 | BU10: 30 | BV10: 30.00
A11: Casos | B11: 0 | C11: 0 | D11: 0 | E11: 0 | F11: 0 | G11: 0 | H11: 0 | I11: 0 | J11: 0 | K11: 0 | L11: 0 | M11: 0 | N11: 0 | O11: 420 | P11: 421 | Q11: 422 | R11: 424 | S11: 425 | T11: 426 | U11: 427 | V11: 429 | W11: 430 | X11: 431 | Y11: 432 | Z11: 434 | AA11: 435 | AB11: 436 | AC11: 438 | AD11: 439 | AE11: 440 | AF11: 441 | AG11: 443 | AH11: 444 | AI11: 445 | AJ11: 447 | AK11: 448 | AL11: 449 | AM11: 451 | AN11: 452 | AO11: 453 | AP11: 455 | AQ11: 456 | AR11: 457 | AS11: 459 | AT11: 460 | AU11: 461 | AV11: 463 | AW11: 464 | AX11: 465 | AY11: 467 | AZ11: 468 | BA11: 469 | BB11: 471 | BC11: 472 | BD11: 474 | BE11: 475 | BF11: 476 | BG11: 478 | BH11: 479 | BI11: 481 | BJ11: 482 | BK11: 483 | BL11: 485 | BM11: 486 | BN11: 488 | BO11: 489 | BP11: 490 | BQ11: 492 | BR11: 493 | BS11: 495 | BT11: 496 | BU11: 498 | BV11: 27008
A12: Revenue Total ($) | B12: 0 | C12: 0 | D12: 0 | E12: 0 | F12: 0 | G12: 0 | H12: 0 | I12: 0 | J12: 0 | K12: 0 | L12: 0 | M12: 0 | N12: 0 | O12: 25200 | P12: 25274 | Q12: 25348 | R12: 25422 | S12: 25497 | T12: 25571 | U12: 25646 | V12: 25721 | W12: 25797 | X12: 25872 | Y12: 25948 | Z12: 26024 | AA12: 26100 | AB12: 26177 | AC12: 26254 | AD12: 26331 | AE12: 26408 | AF12: 26485 | AG12: 26563 | AH12: 26640 | AI12: 26719 | AJ12: 26797 | AK12: 26875 | AL12: 26954 | AM12: 27033 | AN12: 27112 | AO12: 27192 | AP12: 27271 | AQ12: 27351 | AR12: 27431 | AS12: 27512 | AT12: 27592 | AU12: 27673 | AV12: 27754 | AW12: 27836 | AX12: 27917 | AY12: 27999 | AZ12: 28081 | BA12: 28163 | BB12: 28246 | BC12: 28329 | BD12: 28412 | BE12: 28495 | BF12: 28578 | BG12: 28662 | BH12: 28746 | BI12: 28830 | BJ12: 28915 | BK12: 28999 | BL12: 29084 | BM12: 29170 | BN12: 29255 | BO12: 29341 | BP12: 29427 | BQ12: 29513 | BR12: 29600 | BS12: 29686 | BT12: 29773 | BU12: 29860 | BV12: 1620464
A13: Fee Variable Weso ($) | B13: 0 | C13: 0 | D13: 0 | E13: 0 | F13: 0 | G13: 0 | H13: 0 | I13: 0 | J13: 0 | K13: 0 | L13: 0 | M13: 0 | N13: 0 | O13: 7560 | P13: 7582 | Q13: 7604 | R13: 7627 | S13: 7649 | T13: 7671 | U13: 7694 | V13: 7716 | W13: 7739 | X13: 7762 | Y13: 7784 | Z13: 7807 | AA13: 7830 | AB13: 7853 | AC13: 7876 | AD13: 7899 | AE13: 7922 | AF13: 7946 | AG13: 7969 | AH13: 7992 | AI13: 8016 | AJ13: 8039 | AK13: 8063 | AL13: 8086 | AM13: 8110 | AN13: 8134 | AO13: 8158 | AP13: 8181 | AQ13: 8205 | AR13: 8229 | AS13: 8254 | AT13: 8278 | AU13: 8302 | AV13: 8326 | AW13: 8351 | AX13: 8375 | AY13: 8400 | AZ13: 8424 | BA13: 8449 | BB13: 8474 | BC13: 8499 | BD13: 8523 | BE13: 8548 | BF13: 8574 | BG13: 8599 | BH13: 8624 | BI13: 8649 | BJ13: 8674 | BK13: 8700 | BL13: 8725 | BM13: 8751 | BN13: 8777 | BO13: 8802 | BP13: 8828 | BQ13: 8854 | BR13: 8880 | BS13: 8906 | BT13: 8932 | BU13: 8958 | BV13: 486139
A14: Licencia Weso ($) | B14: 0 | C14: 0 | D14: 0 | E14: 0 | F14: 0 | G14: 0 | H14: 0 | I14: 0 | J14: 0 | K14: 0 | L14: 0 | M14: 0 | N14: 0 | O14: 2000 | P14: 2000 | Q14: 2000 | R14: 2000 | S14: 2000 | T14: 2000 | U14: 2000 | V14: 2000 | W14: 2000 | X14: 2000 | Y14: 2000 | Z14: 2000 | AA14: 2000 | AB14: 2000 | AC14: 2000 | AD14: 2000 | AE14: 2000 | AF14: 2000 | AG14: 2000 | AH14: 2000 | AI14: 2000 | AJ14: 2000 | AK14: 2000 | AL14: 2000 | AM14: 2000 | AN14: 2000 | AO14: 2000 | AP14: 2000 | AQ14: 2000 | AR14: 2000 | AS14: 2000 | AT14: 2000 | AU14: 2000 | AV14: 2000 | AW14: 2000 | AX14: 2000 | AY14: 2000 | AZ14: 2000 | BA14: 2000 | BB14: 2000 | BC14: 2000 | BD14: 2000 | BE14: 2000 | BF14: 2000 | BG14: 2000 | BH14: 2000 | BI14: 2000 | BJ14: 2000 | BK14: 2000 | BL14: 2000 | BM14: 2000 | BN14: 2000 | BO14: 2000 | BP14: 2000 | BQ14: 2000 | BR14: 2000 | BS14: 2000 | BT14: 2000 | BU14: 2000 | BV14: 118000
A15: Revenue Weso ($) | B15: 0 | C15: 0 | D15: 0 | E15: 0 | F15: 0 | G15: 0 | H15: 0 | I15: 0 | J15: 0 | K15: 0 | L15: 0 | M15: 0 | N15: 0 | O15: 9560 | P15: 9582 | Q15: 9604 | R15: 9627 | S15: 9649 | T15: 9671 | U15: 9694 | V15: 9716 | W15: 9739 | X15: 9762 | Y15: 9784 | Z15: 9807 | AA15: 9830 | AB15: 9853 | AC15: 9876 | AD15: 9899 | AE15: 9922 | AF15: 9946 | AG15: 9969 | AH15: 9992 | AI15: 10016 | AJ15: 10039 | AK15: 10063 | AL15: 10086 | AM15: 10110 | AN15: 10134 | AO15: 10158 | AP15: 10181 | AQ15: 10205 | AR15: 10229 | AS15: 10254 | AT15: 10278 | AU15: 10302 | AV15: 10326 | AW15: 10351 | AX15: 10375 | AY15: 10400 | AZ15: 10424 | BA15: 10449 | BB15: 10474 | BC15: 10499 | BD15: 10523 | BE15: 10548 | BF15: 10574 | BG15: 10599 | BH15: 10624 | BI15: 10649 | BJ15: 10674 | BK15: 10700 | BL15: 10725 | BM15: 10751 | BN15: 10777 | BO15: 10802 | BP15: 10828 | BQ15: 10854 | BR15: 10880 | BS15: 10906 | BT15: 10932 | BU15: 10958 | BV15: 604139
A16: Costos Proveedor ($) | B16: 0 | C16: 0 | D16: 0 | E16: 0 | F16: 0 | G16: 0 | H16: 0 | I16: 0 | J16: 0 | K16: 0 | L16: 0 | M16: 0 | N16: 0 | O16: 17640 | P16: 17692 | Q16: 17744 | R16: 17796 | S16: 17848 | T16: 17900 | U16: 17952 | V16: 18005 | W16: 18058 | X16: 18111 | Y16: 18164 | Z16: 18217 | AA16: 18270 | AB16: 18324 | AC16: 18378 | AD16: 18431 | AE16: 18485 | AF16: 18540 | AG16: 18594 | AH16: 18648 | AI16: 18703 | AJ16: 18758 | AK16: 18813 | AL16: 18868 | AM16: 18923 | AN16: 18979 | AO16: 19034 | AP16: 19090 | AQ16: 19146 | AR16: 19202 | AS16: 19258 | AT16: 19315 | AU16: 19371 | AV16: 19428 | AW16: 19485 | AX16: 19542 | AY16: 19599 | AZ16: 19657 | BA16: 19714 | BB16: 19772 | BC16: 19830 | BD16: 19888 | BE16: 19946 | BF16: 20005 | BG16: 20063 | BH16: 20122 | BI16: 20181 | BJ16: 20240 | BK16: 20300 | BL16: 20359 | BM16: 20419 | BN16: 20479 | BO16: 20539 | BP16: 20599 | BQ16: 20659 | BR16: 20720 | BS16: 20780 | BT16: 20841 | BU16: 20902 | BV16: 1134325

Sheet 13_Seguros Mundial 🇨🇴 - Hogar
A1: Actor: Seguros Mundial 🇨🇴 - Hogar
A2: Categoría: Hogar y Propiedades · Servicio: · País: Colombia
A3: Crecimiento: 1% · Churn: 0.7%
A5: Métrica | B5: M1 | C5: M2 | D5: M3 | E5: M4 | F5: M5 | G5: M6 | H5: M7 | I5: M8 | J5: M9 | K5: M10 | L5: M11 | M5: M12 | N5: M13 | O5: M14 | P5: M15 | Q5: M16 | R5: M17 | S5: M18 | T5: M19 | U5: M20 | V5: M21 | W5: M22 | X5: M23 | Y5: M24 | Z5: M25 | AA5: M26 | AB5: M27 | AC5: M28 | AD5: M29 | AE5: M30 | AF5: M31 | AG5: M32 | AH5: M33 | AI5: M34 | AJ5: M35 | AK5: M36 | AL5: M37 | AM5: M38 | AN5: M39 | AO5: M40 | AP5: M41 | AQ5: M42 | AR5: M43 | AS5: M44 | AT5: M45 | AU5: M46 | AV5: M47 | AW5: M48 | AX5: M49 | AY5: M50 | AZ5: M51 | BA5: M52 | BB5: M53 | BC5: M54 | BD5: M55 | BE5: M56 | BF5: M57 | BG5: M58 | BH5: M59 | BI5: M60 | BJ5: M61 | BK5: M62 | BL5: M63 | BM5: M64 | BN5: M65 | BO5: M66 | BP5: M67 | BQ5: M68 | BR5: M69 | BS5: M70 | BT5: M71 | BU5: M72 | BV5: TOTAL
A6: Clientes | B6: 0 | C6: 0 | D6: 0 | E6: 0 | F6: 0 | G6: 0 | H6: 0 | I6: 0 | J6: 5000 | K6: 5015 | L6: 5029 | M6: 5044 | N6: 5059 | O6: 5074 | P6: 5089 | Q6: 5103 | R6: 5118 | S6: 5133 | T6: 5148 | U6: 5164 | V6: 5179 | W6: 5194 | X6: 5209 | Y6: 5224 | Z6: 5240 | AA6: 5255 | AB6: 5270 | AC6: 5286 | AD6: 5301 | AE6: 5317 | AF6: 5332 | AG6: 5348 | AH6: 5364 | AI6: 5379 | AJ6: 5395 | AK6: 5411 | AL6: 5427 | AM6: 5443 | AN6: 5459 | AO6: 5475 | AP6: 5491 | AQ6: 5507 | AR6: 5523 | AS6: 5539 | AT6: 5555 | AU6: 5572 | AV6: 5588 | AW6: 5604 | AX6: 5621 | AY6: 5637 | AZ6: 5654 | BA6: 5670 | BB6: 5687 | BC6: 5704 | BD6: 5720 | BE6: 5737 | BF6: 5754 | BG6: 5771 | BH6: 5788 | BI6: 5805 | BJ6: 5822 | BK6: 5839 | BL6: 5856 | BM6: 5873 | BN6: 5890 | BO6: 5907 | BP6: 5925 | BQ6: 5942 | BR6: 5959 | BS6: 5977 | BT6: 5994 | BU6: 6012
A7: Clientes Perdidos (Churn) | B7: 0 | C7: 0 | D7: 0 | E7: 0 | F7: 0 | G7: 0 | H7: 0 | I7: 0 | J7: 0 | K7: 35 | L7: 35 | M7: 35 | N7: 35 | O7: 35 | P7: 36 | Q7: 36 | R7: 36 | S7: 36 | T7: 36 | U7: 36 | V7: 36 | W7: 36 | X7: 36 | Y7: 36 | Z7: 37 | AA7: 37 | AB7: 37 | AC7: 37 | AD7: 37 | AE7: 37 | AF7: 37 | AG7: 37 | AH7: 37 | AI7: 38 | AJ7: 38 | AK7: 38 | AL7: 38 | AM7: 38 | AN7: 38 | AO7: 38 | AP7: 38 | AQ7: 38 | AR7: 39 | AS7: 39 | AT7: 39 | AU7: 39 | AV7: 39 | AW7: 39 | AX7: 39 | AY7: 39 | AZ7: 39 | BA7: 40 | BB7: 40 | BC7: 40 | BD7: 40 | BE7: 40 | BF7: 40 | BG7: 40 | BH7: 40 | BI7: 41 | BJ7: 41 | BK7: 41 | BL7: 41 | BM7: 41 | BN7: 41 | BO7: 41 | BP7: 41 | BQ7: 41 | BR7: 42 | BS7: 42 | BT7: 42 | BU7: 42 | BV7: 2418
A8: Tasa Uso % | B8: 1.2 | C8: 1.2 | D8: 1.2 | E8: 1.2 | F8: 1.2 | G8: 1.2 | H8: 1.2 | I8: 1.2 | J8: 1.2 | K8: 1.2 | L8: 1.2 | M8: 1.2 | N8: 1.2 | O8: 1.2 | P8: 1.2 | Q8: 1.2 | R8: 1.2 | S8: 1.2 | T8: 1.2 | U8: 1.2 | V8: 1.2 | W8: 1.2 | X8: 1.2 | Y8: 1.2 | Z8: 1.2 | AA8: 1.2 | AB8: 1.2 | AC8: 1.2 | AD8: 1.2 | AE8: 1.2 | AF8: 1.2 | AG8: 1.2 | AH8: 1.2 | AI8: 1.2 | AJ8: 1.2 | AK8: 1.2 | AL8: 1.2 | AM8: 1.2 | AN8: 1.2 | AO8: 1.2 | AP8: 1.2 | AQ8: 1.2 | AR8: 1.2 | AS8: 1.2 | AT8: 1.2 | AU8: 1.2 | AV8: 1.2 | AW8: 1.2 | AX8: 1.2 | AY8: 1.2 | AZ8: 1.2 | BA8: 1.2 | BB8: 1.2 | BC8: 1.2 | BD8: 1.2 | BE8: 1.2 | BF8: 1.2 | BG8: 1.2 | BH8: 1.2 | BI8: 1.2 | BJ8: 1.2 | BK8: 1.2 | BL8: 1.2 | BM8: 1.2 | BN8: 1.2 | BO8: 1.2 | BP8: 1.2 | BQ8: 1.2 | BR8: 1.2 | BS8: 1.2 | BT8: 1.2 | BU8: 1.2
A9: Ticket ($) | B9: 40 | C9: 40 | D9: 40 | E9: 40 | F9: 40 | G9: 40 | H9: 40 | I9: 40 | J9: 40 | K9: 40 | L9: 40 | M9: 40 | N9: 40 | O9: 40 | P9: 40 | Q9: 40 | R9: 40 | S9: 40 | T9: 40 | U9: 40 | V9: 40 | W9: 40 | X9: 40 | Y9: 40 | Z9: 40 | AA9: 40 | AB9: 40 | AC9: 40 | AD9: 40 | AE9: 40 | AF9: 40 | AG9: 40 | AH9: 40 | AI9: 40 | AJ9: 40 | AK9: 40 | AL9: 40 | AM9: 40 | AN9: 40 | AO9: 40 | AP9: 40 | AQ9: 40 | AR9: 40 | AS9: 40 | AT9: 40 | AU9: 40 | AV9: 40 | AW9: 40 | AX9: 40 | AY9: 40 | AZ9: 40 | BA9: 40 | BB9: 40 | BC9: 40 | BD9: 40 | BE9: 40 | BF9: 40 | BG9: 40 | BH9: 40 | BI9: 40 | BJ9: 40 | BK9: 40 | BL9: 40 | BM9: 40 | BN9: 40 | BO9: 40 | BP9: 40 | BQ9: 40 | BR9: 40 | BS9: 40 | BT9: 40 | BU9: 40 | BV9: 40.00
A10: Fee Weso % | B10: 30 | C10: 30 | D10: 30 | E10: 30 | F10: 30 | G10: 30 | H10: 30 | I10: 30 | J10: 30 | K10: 30 | L10: 30 | M10: 30 | N10: 30 | O10: 30 | P10: 30 | Q10: 30 | R10: 30 | S10: 30 | T10: 30 | U10: 30 | V10: 30 | W10: 30 | X10: 30 | Y10: 30 | Z10: 30 | AA10: 30 | AB10: 30 | AC10: 30 | AD10: 30 | AE10: 30 | AF10: 30 | AG10: 30 | AH10: 30 | AI10: 30 | AJ10: 30 | AK10: 30 | AL10: 30 | AM10: 30 | AN10: 30 | AO10: 30 | AP10: 30 | AQ10: 30 | AR10: 30 | AS10: 30 | AT10: 30 | AU10: 30 | AV10: 30 | AW10: 30 | AX10: 30 | AY10: 30 | AZ10: 30 | BA10: 30 | BB10: 30 | BC10: 30 | BD10: 30 | BE10: 30 | BF10: 30 | BG10: 30 | BH10: 30 | BI10: 30 | BJ10: 30 | BK10: 30 | BL10: 30 | BM10: 30 | BN10: 30 | BO10: 30 | BP10: 30 | BQ10: 30 | BR10: 30 | BS10: 30 | BT10: 30 | BU10: 30 | BV10: 30.00
A11: Casos | B11: 0 | C11: 0 | D11: 0 | E11: 0 | F11: 0 | G11: 0 | H11: 0 | I11: 0 | J11: 60 | K11: 60 | L11: 60 | M11: 61 | N11: 61 | O11: 61 | P11: 61 | Q11: 61 | R11: 61 | S11: 62 | T11: 62 | U11: 62 | V11: 62 | W11: 62 | X11: 63 | Y11: 63 | Z11: 63 | AA11: 63 | AB11: 63 | AC11: 63 | AD11: 64 | AE11: 64 | AF11: 64 | AG11: 64 | AH11: 64 | AI11: 65 | AJ11: 65 | AK11: 65 | AL11: 65 | AM11: 65 | AN11: 66 | AO11: 66 | AP11: 66 | AQ11: 66 | AR11: 66 | AS11: 66 | AT11: 67 | AU11: 67 | AV11: 67 | AW11: 67 | AX11: 67 | AY11: 68 | AZ11: 68 | BA11: 68 | BB11: 68 | BC11: 68 | BD11: 69 | BE11: 69 | BF11: 69 | BG11: 69 | BH11: 69 | BI11: 70 | BJ11: 70 | BK11: 70 | BL11: 70 | BM11: 70 | BN11: 71 | BO11: 71 | BP11: 71 | BQ11: 71 | BR11: 72 | BS11: 72 | BT11: 72 | BU11: 72 | BV11: 4217
A12: Revenue Total ($) | B12: 0 | C12: 0 | D12: 0 | E12: 0 | F12: 0 | G12: 0 | H12: 0 | I12: 0 | J12: 2400 | K12: 2407 | L12: 2414 | M12: 2421 | N12: 2428 | O12: 2435 | P12: 2443 | Q12: 2450 | R12: 2457 | S12: 2464 | T12: 2471 | U12: 2478 | V12: 2486 | W12: 2493 | X12: 2500 | Y12: 2508 | Z12: 2515 | AA12: 2522 | AB12: 2530 | AC12: 2537 | AD12: 2545 | AE12: 2552 | AF12: 2560 | AG12: 2567 | AH12: 2575 | AI12: 2582 | AJ12: 2590 | AK12: 2597 | AL12: 2605 | AM12: 2613 | AN12: 2620 | AO12: 2628 | AP12: 2636 | AQ12: 2643 | AR12: 2651 | AS12: 2659 | AT12: 2667 | AU12: 2674 | AV12: 2682 | AW12: 2690 | AX12: 2698 | AY12: 2706 | AZ12: 2714 | BA12: 2722 | BB12: 2730 | BC12: 2738 | BD12: 2746 | BE12: 2754 | BF12: 2762 | BG12: 2770 | BH12: 2778 | BI12: 2786 | BJ12: 2794 | BK12: 2803 | BL12: 2811 | BM12: 2819 | BN12: 2827 | BO12: 2836 | BP12: 2844 | BQ12: 2852 | BR12: 2861 | BS12: 2869 | BT12: 2877 | BU12: 2886 | BV12: 168675
A13: Fee Variable Weso ($) | B13: 0 | C13: 0 | D13: 0 | E13: 0 | F13: 0 | G13: 0 | H13: 0 | I13: 0 | J13: 720 | K13: 722 | L13: 724 | M13: 726 | N13: 728 | O13: 731 | P13: 733 | Q13: 735 | R13: 737 | S13: 739 | T13: 741 | U13: 744 | V13: 746 | W13: 748 | X13: 750 | Y13: 752 | Z13: 755 | AA13: 757 | AB13: 759 | AC13: 761 | AD13: 763 | AE13: 766 | AF13: 768 | AG13: 770 | AH13: 772 | AI13: 775 | AJ13: 777 | AK13: 779 | AL13: 781 | AM13: 784 | AN13: 786 | AO13: 788 | AP13: 791 | AQ13: 793 | AR13: 795 | AS13: 798 | AT13: 800 | AU13: 802 | AV13: 805 | AW13: 807 | AX13: 809 | AY13: 812 | AZ13: 814 | BA13: 817 | BB13: 819 | BC13: 821 | BD13: 824 | BE13: 826 | BF13: 829 | BG13: 831 | BH13: 833 | BI13: 836 | BJ13: 838 | BK13: 841 | BL13: 843 | BM13: 846 | BN13: 848 | BO13: 851 | BP13: 853 | BQ13: 856 | BR13: 858 | BS13: 861 | BT13: 863 | BU13: 866 | BV13: 50602
A14: Licencia Weso ($) | B14: 0 | C14: 0 | D14: 0 | E14: 0 | F14: 0 | G14: 0 | H14: 0 | I14: 0 | J14: 0 | K14: 0 | L14: 0 | M14: 0 | N14: 0 | O14: 0 | P14: 0 | Q14: 0 | R14: 0 | S14: 0 | T14: 0 | U14: 0 | V14: 0 | W14: 0 | X14: 0 | Y14: 0 | Z14: 0 | AA14: 0 | AB14: 0 | AC14: 0 | AD14: 0 | AE14: 0 | AF14: 0 | AG14: 0 | AH14: 0 | AI14: 0 | AJ14: 0 | AK14: 0 | AL14: 0 | AM14: 0 | AN14: 0 | AO14: 0 | AP14: 0 | AQ14: 0 | AR14: 0 | AS14: 0 | AT14: 0 | AU14: 0 | AV14: 0 | AW14: 0 | AX14: 0 | AY14: 0 | AZ14: 0 | BA14: 0 | BB14: 0 | BC14: 0 | BD14: 0 | BE14: 0 | BF14: 0 | BG14: 0 | BH14: 0 | BI14: 0 | BJ14: 0 | BK14: 0 | BL14: 0 | BM14: 0 | BN14: 0 | BO14: 0 | BP14: 0 | BQ14: 0 | BR14: 0 | BS14: 0 | BT14: 0 | BU14: 0 | BV14: 0
A15: Revenue Weso ($) | B15: 0 | C15: 0 | D15: 0 | E15: 0 | F15: 0 | G15: 0 | H15: 0 | I15: 0 | J15: 720 | K15: 722 | L15: 724 | M15: 726 | N15: 728 | O15: 731 | P15: 733 | Q15: 735 | R15: 737 | S15: 739 | T15: 741 | U15: 744 | V15: 746 | W15: 748 | X15: 750 | Y15: 752 | Z15: 755 | AA15: 757 | AB15: 759 | AC15: 761 | AD15: 763 | AE15: 766 | AF15: 768 | AG15: 770 | AH15: 772 | AI15: 775 | AJ15: 777 | AK15: 779 | AL15: 781 | AM15: 784 | AN15: 786 | AO15: 788 | AP15: 791 | AQ15: 793 | AR15: 795 | AS15: 798 | AT15: 800 | AU15: 802 | AV15: 805 | AW15: 807 | AX15: 809 | AY15: 812 | AZ15: 814 | BA15: 817 | BB15: 819 | BC15: 821 | BD15: 824 | BE15: 826 | BF15: 829 | BG15: 831 | BH15: 833 | BI15: 836 | BJ15: 838 | BK15: 841 | BL15: 843 | BM15: 846 | BN15: 848 | BO15: 851 | BP15: 853 | BQ15: 856 | BR15: 858 | BS15: 861 | BT15: 863 | BU15: 866 | BV15: 50602
A16: Costos Proveedor ($) | B16: 0 | C16: 0 | D16: 0 | E16: 0 | F16: 0 | G16: 0 | H16: 0 | I16: 0 | J16: 1680 | K16: 1685 | L16: 1690 | M16: 1695 | N16: 1700 | O16: 1705 | P16: 1710 | Q16: 1715 | R16: 1720 | S16: 1725 | T16: 1730 | U16: 1735 | V16: 1740 | W16: 1745 | X16: 1750 | Y16: 1755 | Z16: 1761 | AA16: 1766 | AB16: 1771 | AC16: 1776 | AD16: 1781 | AE16: 1786 | AF16: 1792 | AG16: 1797 | AH16: 1802 | AI16: 1807 | AJ16: 1813 | AK16: 1818 | AL16: 1823 | AM16: 1829 | AN16: 1834 | AO16: 1839 | AP16: 1845 | AQ16: 1850 | AR16: 1856 | AS16: 1861 | AT16: 1867 | AU16: 1872 | AV16: 1878 | AW16: 1883 | AX16: 1889 | AY16: 1894 | AZ16: 1900 | BA16: 1905 | BB16: 1911 | BC16: 1916 | BD16: 1922 | BE16: 1928 | BF16: 1933 | BG16: 1939 | BH16: 1945 | BI16: 1950 | BJ16: 1956 | BK16: 1962 | BL16: 1968 | BM16: 1973 | BN16: 1979 | BO16: 1985 | BP16: 1991 | BQ16: 1997 | BR16: 2002 | BS16: 2008 | BT16: 2014 | BU16: 2020 | BV16: 118072

Sheet 14_BNP Paribas Cardif
A1: Actor: BNP Paribas Cardif
A2: Categoría: Salud y cuidado · Servicio: · País: Chile
A3: Crecimiento: 1% · Churn: 0.7%
A5: Métrica | B5: M1 | C5: M2 | D5: M3 | E5: M4 | F5: M5 | G5: M6 | H5: M7 | I5: M8 | J5: M9 | K5: M10 | L5: M11 | M5: M12 | N5: M13 | O5: M14 | P5: M15 | Q5: M16 | R5: M17 | S5: M18 | T5: M19 | U5: M20 | V5: M21 | W5: M22 | X5: M23 | Y5: M24 | Z5: M25 | AA5: M26 | AB5: M27 | AC5: M28 | AD5: M29 | AE5: M30 | AF5: M31 | AG5: M32 | AH5: M33 | AI5: M34 | AJ5: M35 | AK5: M36 | AL5: M37 | AM5: M38 | AN5: M39 | AO5: M40 | AP5: M41 | AQ5: M42 | AR5: M43 | AS5: M44 | AT5: M45 | AU5: M46 | AV5: M47 | AW5: M48 | AX5: M49 | AY5: M50 | AZ5: M51 | BA5: M52 | BB5: M53 | BC5: M54 | BD5: M55 | BE5: M56 | BF5: M57 | BG5: M58 | BH5: M59 | BI5: M60 | BJ5: M61 | BK5: M62 | BL5: M63 | BM5: M64 | BN5: M65 | BO5: M66 | BP5: M67 | BQ5: M68 | BR5: M69 | BS5: M70 | BT5: M71 | BU5: M72 | BV5: TOTAL
A6: Clientes | B6: 0 | C6: 0 | D6: 0 | E6: 0 | F6: 0 | G6: 0 | H6: 0 | I6: 0 | J6: 0 | K6: 0 | L6: 0 | M6: 20000 | N6: 20059 | O6: 20117 | P6: 20176 | Q6: 20235 | R6: 20295 | S6: 20354 | T6: 20414 | U6: 20474 | V6: 20534 | W6: 20594 | X6: 20654 | Y6: 20715 | Z6: 20775 | AA6: 20836 | AB6: 20897 | AC6: 20958 | AD6: 21020 | AE6: 21081 | AF6: 21143 | AG6: 21205 | AH6: 21267 | AI6: 21330 | AJ6: 21392 | AK6: 21455 | AL6: 21518 | AM6: 21581 | AN6: 21644 | AO6: 21707 | AP6: 21771 | AQ6: 21835 | AR6: 21899 | AS6: 21963 | AT6: 22027 | AU6: 22092 | AV6: 22157 | AW6: 22221 | AX6: 22287 | AY6: 22352 | AZ6: 22417 | BA6: 22483 | BB6: 22549 | BC6: 22615 | BD6: 22681 | BE6: 22748 | BF6: 22814 | BG6: 22881 | BH6: 22948 | BI6: 23015 | BJ6: 23083 | BK6: 23151 | BL6: 23218 | BM6: 23286 | BN6: 23355 | BO6: 23423 | BP6: 23492 | BQ6: 23561 | BR6: 23630 | BS6: 23699 | BT6: 23768 | BU6: 23838
A7: Clientes Perdidos (Churn) | B7: 0 | C7: 0 | D7: 0 | E7: 0 | F7: 0 | G7: 0 | H7: 0 | I7: 0 | J7: 0 | K7: 0 | L7: 0 | M7: 0 | N7: 140 | O7: 140 | P7: 141 | Q7: 141 | R7: 142 | S7: 142 | T7: 142 | U7: 143 | V7: 143 | W7: 144 | X7: 144 | Y7: 145 | Z7: 145 | AA7: 145 | AB7: 146 | AC7: 146 | AD7: 147 | AE7: 147 | AF7: 148 | AG7: 148 | AH7: 148 | AI7: 149 | AJ7: 149 | AK7: 150 | AL7: 150 | AM7: 151 | AN7: 151 | AO7: 152 | AP7: 152 | AQ7: 152 | AR7: 153 | AS7: 153 | AT7: 154 | AU7: 154 | AV7: 155 | AW7: 155 | AX7: 156 | AY7: 156 | AZ7: 156 | BA7: 157 | BB7: 157 | BC7: 158 | BD7: 158 | BE7: 159 | BF7: 159 | BG7: 160 | BH7: 160 | BI7: 161 | BJ7: 161 | BK7: 162 | BL7: 162 | BM7: 163 | BN7: 163 | BO7: 163 | BP7: 164 | BQ7: 164 | BR7: 165 | BS7: 165 | BT7: 166 | BU7: 166 | BV7: 9169
A8: Tasa Uso % | B8: 1.5 | C8: 1.5 | D8: 1.5 | E8: 1.5 | F8: 1.5 | G8: 1.5 | H8: 1.5 | I8: 1.5 | J8: 1.5 | K8: 1.5 | L8: 1.5 | M8: 1.5 | N8: 1.5 | O8: 1.5 | P8: 1.5 | Q8: 1.5 | R8: 1.5 | S8: 1.5 | T8: 1.5 | U8: 1.5 | V8: 1.5 | W8: 1.5 | X8: 1.5 | Y8: 1.5 | Z8: 1.5 | AA8: 1.5 | AB8: 1.5 | AC8: 1.5 | AD8: 1.5 | AE8: 1.5 | AF8: 1.5 | AG8: 1.5 | AH8: 1.5 | AI8: 1.5 | AJ8: 1.5 | AK8: 1.5 | AL8: 1.5 | AM8: 1.5 | AN8: 1.5 | AO8: 1.5 | AP8: 1.5 | AQ8: 1.5 | AR8: 1.5 | AS8: 1.5 | AT8: 1.5 | AU8: 1.5 | AV8: 1.5 | AW8: 1.5 | AX8: 1.5 | AY8: 1.5 | AZ8: 1.5 | BA8: 1.5 | BB8: 1.5 | BC8: 1.5 | BD8: 1.5 | BE8: 1.5 | BF8: 1.5 | BG8: 1.5 | BH8: 1.5 | BI8: 1.5 | BJ8: 1.5 | BK8: 1.5 | BL8: 1.5 | BM8: 1.5 | BN8: 1.5 | BO8: 1.5 | BP8: 1.5 | BQ8: 1.5 | BR8: 1.5 | BS8: 1.5 | BT8: 1.5 | BU8: 1.5
A9: Ticket ($) | B9: 70 | C9: 70 | D9: 70 | E9: 70 | F9: 70 | G9: 70 | H9: 70 | I9: 70 | J9: 70 | K9: 70 | L9: 70 | M9: 70 | N9: 70 | O9: 70 | P9: 70 | Q9: 70 | R9: 70 | S9: 70 | T9: 70 | U9: 70 | V9: 70 | W9: 70 | X9: 70 | Y9: 70 | Z9: 70 | AA9: 70 | AB9: 70 | AC9: 70 | AD9: 70 | AE9: 70 | AF9: 70 | AG9: 70 | AH9: 70 | AI9: 70 | AJ9: 70 | AK9: 70 | AL9: 70 | AM9: 70 | AN9: 70 | AO9: 70 | AP9: 70 | AQ9: 70 | AR9: 70 | AS9: 70 | AT9: 70 | AU9: 70 | AV9: 70 | AW9: 70 | AX9: 70 | AY9: 70 | AZ9: 70 | BA9: 70 | BB9: 70 | BC9: 70 | BD9: 70 | BE9: 70 | BF9: 70 | BG9: 70 | BH9: 70 | BI9: 70 | BJ9: 70 | BK9: 70 | BL9: 70 | BM9: 70 | BN9: 70 | BO9: 70 | BP9: 70 | BQ9: 70 | BR9: 70 | BS9: 70 | BT9: 70 | BU9: 70 | BV9: 70.00
A10: Fee Weso % | B10: 30 | C10: 30 | D10: 30 | E10: 30 | F10: 30 | G10: 30 | H10: 30 | I10: 30 | J10: 30 | K10: 30 | L10: 30 | M10: 30 | N10: 30 | O10: 30 | P10: 30 | Q10: 30 | R10: 30 | S10: 30 | T10: 30 | U10: 30 | V10: 30 | W10: 30 | X10: 30 | Y10: 30 | Z10: 30 | AA10: 30 | AB10: 30 | AC10: 30 | AD10: 30 | AE10: 30 | AF10: 30 | AG10: 30 | AH10: 30 | AI10: 30 | AJ10: 30 | AK10: 30 | AL10: 30 | AM10: 30 | AN10: 30 | AO10: 30 | AP10: 30 | AQ10: 30 | AR10: 30 | AS10: 30 | AT10: 30 | AU10: 30 | AV10: 30 | AW10: 30 | AX10: 30 | AY10: 30 | AZ10: 30 | BA10: 30 | BB10: 30 | BC10: 30 | BD10: 30 | BE10: 30 | BF10: 30 | BG10: 30 | BH10: 30 | BI10: 30 | BJ10: 30 | BK10: 30 | BL10: 30 | BM10: 30 | BN10: 30 | BO10: 30 | BP10: 30 | BQ10: 30 | BR10: 30 | BS10: 30 | BT10: 30 | BU10: 30 | BV10: 30.00
A11: Casos | B11: 0 | C11: 0 | D11: 0 | E11: 0 | F11: 0 | G11: 0 | H11: 0 | I11: 0 | J11: 0 | K11: 0 | L11: 0 | M11: 300 | N11: 301 | O11: 302 | P11: 303 | Q11: 304 | R11: 304 | S11: 305 | T11: 306 | U11: 307 | V11: 308 | W11: 309 | X11: 310 | Y11: 311 | Z11: 312 | AA11: 313 | AB11: 313 | AC11: 314 | AD11: 315 | AE11: 316 | AF11: 317 | AG11: 318 | AH11: 319 | AI11: 320 | AJ11: 321 | AK11: 322 | AL11: 323 | AM11: 324 | AN11: 325 | AO11: 326 | AP11: 327 | AQ11: 328 | AR11: 328 | AS11: 329 | AT11: 330 | AU11: 331 | AV11: 332 | AW11: 333 | AX11: 334 | AY11: 335 | AZ11: 336 | BA11: 337 | BB11: 338 | BC11: 339 | BD11: 340 | BE11: 341 | BF11: 342 | BG11: 343 | BH11: 344 | BI11: 345 | BJ11: 346 | BK11: 347 | BL11: 348 | BM11: 349 | BN11: 350 | BO11: 351 | BP11: 352 | BQ11: 353 | BR11: 354 | BS11: 355 | BT11: 357 | BU11: 358 | BV11: 20005
A12: Revenue Total ($) | B12: 0 | C12: 0 | D12: 0 | E12: 0 | F12: 0 | G12: 0 | H12: 0 | I12: 0 | J12: 0 | K12: 0 | L12: 0 | M12: 21000 | N12: 21062 | O12: 21123 | P12: 21185 | Q12: 21247 | R12: 21309 | S12: 21372 | T12: 21435 | U12: 21497 | V12: 21560 | W12: 21623 | X12: 21687 | Y12: 21750 | Z12: 21814 | AA12: 21878 | AB12: 21942 | AC12: 22006 | AD12: 22071 | AE12: 22136 | AF12: 22200 | AG12: 22265 | AH12: 22331 | AI12: 22396 | AJ12: 22462 | AK12: 22528 | AL12: 22594 | AM12: 22660 | AN12: 22726 | AO12: 22793 | AP12: 22860 | AQ12: 22927 | AR12: 22994 | AS12: 23061 | AT12: 23129 | AU12: 23196 | AV12: 23264 | AW12: 23333 | AX12: 23401 | AY12: 23469 | AZ12: 23538 | BA12: 23607 | BB12: 23676 | BC12: 23746 | BD12: 23815 | BE12: 23885 | BF12: 23955 | BG12: 24025 | BH12: 24096 | BI12: 24166 | BJ12: 24237 | BK12: 24308 | BL12: 24379 | BM12: 24451 | BN12: 24522 | BO12: 24594 | BP12: 24666 | BQ12: 24739 | BR12: 24811 | BS12: 24884 | BT12: 24957 | BU12: 25030 | BV12: 1400373
A13: Fee Variable Weso ($) | B13: 0 | C13: 0 | D13: 0 | E13: 0 | F13: 0 | G13: 0 | H13: 0 | I13: 0 | J13: 0 | K13: 0 | L13: 0 | M13: 6300 | N13: 6318 | O13: 6337 | P13: 6356 | Q13: 6374 | R13: 6393 | S13: 6412 | T13: 6430 | U13: 6449 | V13: 6468 | W13: 6487 | X13: 6506 | Y13: 6525 | Z13: 6544 | AA13: 6563 | AB13: 6583 | AC13: 6602 | AD13: 6621 | AE13: 6641 | AF13: 6660 | AG13: 6680 | AH13: 6699 | AI13: 6719 | AJ13: 6739 | AK13: 6758 | AL13: 6778 | AM13: 6798 | AN13: 6818 | AO13: 6838 | AP13: 6858 | AQ13: 6878 | AR13: 6898 | AS13: 6918 | AT13: 6939 | AU13: 6959 | AV13: 6979 | AW13: 7000 | AX13: 7020 | AY13: 7041 | AZ13: 7061 | BA13: 7082 | BB13: 7103 | BC13: 7124 | BD13: 7145 | BE13: 7166 | BF13: 7187 | BG13: 7208 | BH13: 7229 | BI13: 7250 | BJ13: 7271 | BK13: 7292 | BL13: 7314 | BM13: 7335 | BN13: 7357 | BO13: 7378 | BP13: 7400 | BQ13: 7422 | BR13: 7443 | BS13: 7465 | BT13: 7487 | BU13: 7509 | BV13: 420112
A14: Licencia Weso ($) | B14: 0 | C14: 0 | D14: 0 | E14: 0 | F14: 0 | G14: 0 | H14: 0 | I14: 0 | J14: 0 | K14: 0 | L14: 0 | M14: 2000 | N14: 2000 | O14: 2000 | P14: 2000 | Q14: 2000 | R14: 2000 | S14: 2000 | T14: 2000 | U14: 2000 | V14: 2000 | W14: 2000 | X14: 2000 | Y14: 2000 | Z14: 2000 | AA14: 2000 | AB14: 2000 | AC14: 2000 | AD14: 2000 | AE14: 2000 | AF14: 2000 | AG14: 2000 | AH14: 2000 | AI14: 2000 | AJ14: 2000 | AK14: 2000 | AL14: 2000 | AM14: 2000 | AN14: 2000 | AO14: 2000 | AP14: 2000 | AQ14: 2000 | AR14: 2000 | AS14: 2000 | AT14: 2000 | AU14: 2000 | AV14: 2000 | AW14: 2000 | AX14: 2000 | AY14: 2000 | AZ14: 2000 | BA14: 2000 | BB14: 2000 | BC14: 2000 | BD14: 2000 | BE14: 2000 | BF14: 2000 | BG14: 2000 | BH14: 2000 | BI14: 2000 | BJ14: 2000 | BK14: 2000 | BL14: 2000 | BM14: 2000 | BN14: 2000 | BO14: 2000 | BP14: 2000 | BQ14: 2000 | BR14: 2000 | BS14: 2000 | BT14: 2000 | BU14: 2000 | BV14: 122000
A15: Revenue Weso ($) | B15: 0 | C15: 0 | D15: 0 | E15: 0 | F15: 0 | G15: 0 | H15: 0 | I15: 0 | J15: 0 | K15: 0 | L15: 0 | M15: 8300 | N15: 8318 | O15: 8337 | P15: 8356 | Q15: 8374 | R15: 8393 | S15: 8412 | T15: 8430 | U15: 8449 | V15: 8468 | W15: 8487 | X15: 8506 | Y15: 8525 | Z15: 8544 | AA15: 8563 | AB15: 8583 | AC15: 8602 | AD15: 8621 | AE15: 8641 | AF15: 8660 | AG15: 8680 | AH15: 8699 | AI15: 8719 | AJ15: 8739 | AK15: 8758 | AL15: 8778 | AM15: 8798 | AN15: 8818 | AO15: 8838 | AP15: 8858 | AQ15: 8878 | AR15: 8898 | AS15: 8918 | AT15: 8939 | AU15: 8959 | AV15: 8979 | AW15: 9000 | AX15: 9020 | AY15: 9041 | AZ15: 9061 | BA15: 9082 | BB15: 9103 | BC15: 9124 | BD15: 9145 | BE15: 9166 | BF15: 9187 | BG15: 9208 | BH15: 9229 | BI15: 9250 | BJ15: 9271 | BK15: 9292 | BL15: 9314 | BM15: 9335 | BN15: 9357 | BO15: 9378 | BP15: 9400 | BQ15: 9422 | BR15: 9443 | BS15: 9465 | BT15: 9487 | BU15: 9509 | BV15: 542112
